Workbook

Sheet Notes
A1: Autonomic function testing — hospital price transparency summary
A3: Scope | B3: CPT 95921, 95922, 95923, 95924 (autonomic function tests) and 93660 (tilt table, context). Hospitals: MGH, Brigham and Women's, BW Faulkner, Wentworth-Douglass, BIDMC.
A4: Source | B4: Hospital machine-readable files (CMS HPT, schema v3.0.0) found via each system's cms-hpt.txt; normalised in hpt_autonomic_rates.csv (Rates_data tab).
A5: IMPORTANT | B5: These are HOSPITAL FACILITY rates (hospital outpatient department). They bound independent-site rates from above. They are NOT AutoLabs' expected rates.
A6: OPPS Addendum B | B6: CY2026 OPPS Addendum B (July 2026 update) rates are NATIONAL and UNADJUSTED for the Massachusetts wage index.
A7: Physician fee | B7: The 142.57 physician component is the Medicare MPFS professional component (95924 PC 95.23 + 95923 PC 47.34), used as an APPROXIMATION: physician-group rates are not in hospital files.
A8: Headline figures | B8: Where a row carries median / 10th / 90th percentile allowed amounts and a count, the median allowed amount (what was actually paid) is the headline; otherwise the negotiated rate.
A9: Medicare packaging | B9: 95923 has OPPS status indicator Q1: when billed on the same claim as 95924 (SI S) it is packaged and not paid separately. Battery tab shows Medicare both with packaging applied and as listed.
A10: Comparator | B10: Medicare facility comparator = the hospital's own Medicare FFS (APC-priced) row where listed; OPPS Addendum B national otherwise (always for BIDMC). Cross-check in Medicare_check.
A11: Colour key | B11: Blue text = input value; green text = link to another sheet; black = formula; yellow fill = key derived total.
A12: Tabs | B12: By_code_payer · Battery · Multiples · Focus_payers · Coverage · Reconciliation · Medicare_check · QA · Reference · Rates_data

Sheet By_code_payer
A1: Outpatient facility rates by hospital, code and payer (plans grouped within payer and segment)
A2: Included rows only (see QA). Headline = median allowed amount where the file gives one (what was actually paid), otherwise the median negotiated rate. All cells are formulas over Rates_data.
A4: Hospital | B4: Code | C4: Payer (as in file) | D4: Payer family | E4: Segment | F4: Plan count | G4: Min implied $ | H4: Median implied $ | I4: Max implied $ | J4: Share percentage-based | K4: Median allowed (median of plan medians) | L4: Lowest 10th pct allowed | M4: Highest 90th pct allowed | N4: Allowed counts (as in file) | O4: Headline rate | P4: Headline basis
A5: Massachusetts General Hospital | B5: 95921 | C5: UNITED HEALTHCARE [1016] | D5: UnitedHealthcare | E5: Commercial | F5: =COUNTIFS(Rates_data!$B$2:$B$75,$A5,Rates_data!$D$2:$D$75,$B5,Rates_data!$E$2:$E$75,$C5,Rates_data!$G$2:$G$75,$E5,Rates_data!$Y$2:$Y$75,1) -> 1 | G5: =_xlfn.MINIFS(Rates_data!$P$2:$P$75,Rates_data!$B$2:$B$75,$A5,Rates_data!$D$2:$D$75,$B5,Rates_data!$E$2:$E$75,$C5,Rates_data!$G$2:$G$75,$E5,Rates_data!$Y$2:$Y$75,1) -> 500.13 | H5: {=MEDIAN(IF((Rates_data!$B$2:$B$75=$A5)*(Rates_data!$D$2:$D$75=$B5)*(Rates_data!$G$2:$G$75=$E5)*(Rates_data!$E$2:$E$75=$C5)*(Rates_data!$Y$2:$Y$75=1)*(Rates_data!$P$2:$P$75<>""),Rates_data!$P$2:$P$75))} -> 500.13 | I5: =_xlfn.MAXIFS(Rates_data!$P$2:$P$75,Rates_data!$B$2:$B$75,$A5,Rates_data!$D$2:$D$75,$B5,Rates_data!$E$2:$E$75,$C5,Rates_data!$G$2:$G$75,$E5,Rates_data!$Y$2:$Y$75,1) -> 500.13 | J5: =IF(F5=0,"",SUMIFS(Rates_data!$R$2:$R$75,Rates_data!$B$2:$B$75,$A5,Rates_data!$D$2:$D$75,$B5,Rates_data!$E$2:$E$75,$C5,Rates_data!$G$2:$G$75,$E5,Rates_data!$Y$2:$Y$75,1)/F5) -> 1 | K5: {=IF(COUNTIFS(Rates_data!$B$2:$B$75,$A5,Rates_data!$D$2:$D$75,$B5,Rates_data!$E$2:$E$75,$C5,Rates_data!$G$2:$G$75,$E5,Rates_data!$Y$2:$Y$75,1,Rates_data!$S$2:$S$75,"<>")=0,"",MEDIAN(IF((Rates_data!$B$2:$B$75=$A5)*(Rates_data!$D$2:$D$75=$B5)*(Rates_data!$G$2:$G$75=$E5)*(Rates_data!$E$2:$E$75=$C5)*(Rates_data!$Y$2:$Y$75=1)*(Rates_data!$S$2:$S$75<>""),Rates_data!$S$2:$S$75)))} -> 474.04 | L5: =IF(COUNTIFS(Rates_data!$B$2:$B$75,$A5,Rates_data!$D$2:$D$75,$B5,Rates_data!$E$2:$E$75,$C5,Rates_data!$G$2:$G$75,$E5,Rates_data!$Y$2:$Y$75,1,Rates_data!$T$2:$T$75,"<>")=0,"",_xlfn.MINIFS(Rates_data!$T$2:$T$75,Rates_data!$B$2:$B$75,$A5,Rates_data!$D$2:$D$75,$B5,Rates_data!$E$2:$E$75,$C5,Rates_data!$G$2:$G$75,$E5,Rates_data!$Y$2:$Y$75,1)) -> 474.04 | M5: =IF(COUNTIFS(Rates_data!$B$2:$B$75,$A5,Rates_data!$D$2:$D$75,$B5,Rates_data!$E$2:$E$75,$C5,Rates_data!$G$2:$G$75,$E5,Rates_data!$Y$2:$Y$75,1,Rates_data!$U$2:$U$75,"<>")=0,"",_xlfn.MAXIFS(Rates_data!$U$2:$U$75,Rates_data!$B$2:$B$75,$A5,Rates_data!$D$2:$D$75,$B5,Rates_data!$E$2:$E$75,$C5,Rates_data!$G$2:$G$75,$E5,Rates_data!$Y$2:$Y$75,1)) -> 474.04 | N5: 1 through 10 | O5: =IF(K5<>"",K5,H5) -> 474.04 | P5: =IF(K5<>"","median allowed","median negotiated") -> median allowed
A6: Massachusetts General Hospital | B6: 95923 | C6: AETNA [1001] | D6: Aetna | E6: Commercial | F6: =COUNTIFS(Rates_data!$B$2:$B$75,$A6,Rates_data!$D$2:$D$75,$B6,Rates_data!$E$2:$E$75,$C6,Rates_data!$G$2:$G$75,$E6,Rates_data!$Y$2:$Y$75,1) -> 1 | G6: =_xlfn.MINIFS(Rates_data!$P$2:$P$75,Rates_data!$B$2:$B$75,$A6,Rates_data!$D$2:$D$75,$B6,Rates_data!$E$2:$E$75,$C6,Rates_data!$G$2:$G$75,$E6,Rates_data!$Y$2:$Y$75,1) -> 686.13 | H6: {=MEDIAN(IF((Rates_data!$B$2:$B$75=$A6)*(Rates_data!$D$2:$D$75=$B6)*(Rates_data!$G$2:$G$75=$E6)*(Rates_data!$E$2:$E$75=$C6)*(Rates_data!$Y$2:$Y$75=1)*(Rates_data!$P$2:$P$75<>""),Rates_data!$P$2:$P$75))} -> 686.13 | I6: =_xlfn.MAXIFS(Rates_data!$P$2:$P$75,Rates_data!$B$2:$B$75,$A6,Rates_data!$D$2:$D$75,$B6,Rates_data!$E$2:$E$75,$C6,Rates_data!$G$2:$G$75,$E6,Rates_data!$Y$2:$Y$75,1) -> 686.13 | J6: =IF(F6=0,"",SUMIFS(Rates_data!$R$2:$R$75,Rates_data!$B$2:$B$75,$A6,Rates_data!$D$2:$D$75,$B6,Rates_data!$E$2:$E$75,$C6,Rates_data!$G$2:$G$75,$E6,Rates_data!$Y$2:$Y$75,1)/F6) -> 1 | K6: {=IF(COUNTIFS(Rates_data!$B$2:$B$75,$A6,Rates_data!$D$2:$D$75,$B6,Rates_data!$E$2:$E$75,$C6,Rates_data!$G$2:$G$75,$E6,Rates_data!$Y$2:$Y$75,1,Rates_data!$S$2:$S$75,"<>")=0,"",MEDIAN(IF((Rates_data!$B$2:$B$75=$A6)*(Rates_data!$D$2:$D$75=$B6)*(Rates_data!$G$2:$G$75=$E6)*(Rates_data!$E$2:$E$75=$C6)*(Rates_data!$Y$2:$Y$75=1)*(Rates_data!$S$2:$S$75<>""),Rates_data!$S$2:$S$75)))} -> 1212.81 | L6: =IF(COUNTIFS(Rates_data!$B$2:$B$75,$A6,Rates_data!$D$2:$D$75,$B6,Rates_data!$E$2:$E$75,$C6,Rates_data!$G$2:$G$75,$E6,Rates_data!$Y$2:$Y$75,1,Rates_data!$T$2:$T$75,"<>")=0,"",_xlfn.MINIFS(Rates_data!$T$2:$T$75,Rates_data!$B$2:$B$75,$A6,Rates_data!$D$2:$D$75,$B6,Rates_data!$E$2:$E$75,$C6,Rates_data!$G$2:$G$75,$E6,Rates_data!$Y$2:$Y$75,1)) -> 645.18 | M6: =IF(COUNTIFS(Rates_data!$B$2:$B$75,$A6,Rates_data!$D$2:$D$75,$B6,Rates_data!$E$2:$E$75,$C6,Rates_data!$G$2:$G$75,$E6,Rates_data!$Y$2:$Y$75,1,Rates_data!$U$2:$U$75,"<>")=0,"",_xlfn.MAXIFS(Rates_data!$U$2:$U$75,Rates_data!$B$2:$B$75,$A6,Rates_data!$D$2:$D$75,$B6,Rates_data!$E$2:$E$75,$C6,Rates_data!$G$2:$G$75,$E6,Rates_data!$Y$2:$Y$75,1)) -> 1212.81 | N6: 1 through 10 | O6: =IF(K6<>"",K6,H6) -> 1212.81 | P6: =IF(K6<>"","median allowed","median negotiated") -> median allowed
A7: Massachusetts General Hospital | B7: 95923 | C7: CIGNA ALTERNATE [1018] | D7: Cigna | E7: Commercial | F7: =COUNTIFS(Rates_data!$B$2:$B$75,$A7,Rates_data!$D$2:$D$75,$B7,Rates_data!$E$2:$E$75,$C7,Rates_data!$G$2:$G$75,$E7,Rates_data!$Y$2:$Y$75,1) -> 1 | G7: =_xlfn.MINIFS(Rates_data!$P$2:$P$75,Rates_data!$B$2:$B$75,$A7,Rates_data!$D$2:$D$75,$B7,Rates_data!$E$2:$E$75,$C7,Rates_data!$G$2:$G$75,$E7,Rates_data!$Y$2:$Y$75,1) -> 523.94 | H7: {=MEDIAN(IF((Rates_data!$B$2:$B$75=$A7)*(Rates_data!$D$2:$D$75=$B7)*(Rates_data!$G$2:$G$75=$E7)*(Rates_data!$E$2:$E$75=$C7)*(Rates_data!$Y$2:$Y$75=1)*(Rates_data!$P$2:$P$75<>""),Rates_data!$P$2:$P$75))} -> 523.94 | I7: =_xlfn.MAXIFS(Rates_data!$P$2:$P$75,Rates_data!$B$2:$B$75,$A7,Rates_data!$D$2:$D$75,$B7,Rates_data!$E$2:$E$75,$C7,Rates_data!$G$2:$G$75,$E7,Rates_data!$Y$2:$Y$75,1) -> 523.94 | J7: =IF(F7=0,"",SUMIFS(Rates_data!$R$2:$R$75,Rates_data!$B$2:$B$75,$A7,Rates_data!$D$2:$D$75,$B7,Rates_data!$E$2:$E$75,$C7,Rates_data!$G$2:$G$75,$E7,Rates_data!$Y$2:$Y$75,1)/F7) -> 1 | K7: {=IF(COUNTIFS(Rates_data!$B$2:$B$75,$A7,Rates_data!$D$2:$D$75,$B7,Rates_data!$E$2:$E$75,$C7,Rates_data!$G$2:$G$75,$E7,Rates_data!$Y$2:$Y$75,1,Rates_data!$S$2:$S$75,"<>")=0,"",MEDIAN(IF((Rates_data!$B$2:$B$75=$A7)*(Rates_data!$D$2:$D$75=$B7)*(Rates_data!$G$2:$G$75=$E7)*(Rates_data!$E$2:$E$75=$C7)*(Rates_data!$Y$2:$Y$75=1)*(Rates_data!$S$2:$S$75<>""),Rates_data!$S$2:$S$75)))} -> 503.18 | L7: =IF(COUNTIFS(Rates_data!$B$2:$B$75,$A7,Rates_data!$D$2:$D$75,$B7,Rates_data!$E$2:$E$75,$C7,Rates_data!$G$2:$G$75,$E7,Rates_data!$Y$2:$Y$75,1,Rates_data!$T$2:$T$75,"<>")=0,"",_xlfn.MINIFS(Rates_data!$T$2:$T$75,Rates_data!$B$2:$B$75,$A7,Rates_data!$D$2:$D$75,$B7,Rates_data!$E$2:$E$75,$C7,Rates_data!$G$2:$G$75,$E7,Rates_data!$Y$2:$Y$75,1)) -> 503.18 | M7: =IF(COUNTIFS(Rates_data!$B$2:$B$75,$A7,Rates_data!$D$2:$D$75,$B7,Rates_data!$E$2:$E$75,$C7,Rates_data!$G$2:$G$75,$E7,Rates_data!$Y$2:$Y$75,1,Rates_data!$U$2:$U$75,"<>")=0,"",_xlfn.MAXIFS(Rates_data!$U$2:$U$75,Rates_data!$B$2:$B$75,$A7,Rates_data!$D$2:$D$75,$B7,Rates_data!$E$2:$E$75,$C7,Rates_data!$G$2:$G$75,$E7,Rates_data!$Y$2:$Y$75,1)) -> 503.18 | N7: 1 through 10 | O7: =IF(K7<>"",K7,H7) -> 503.18 | P7: =IF(K7<>"","median allowed","median negotiated") -> median allowed
A8: Massachusetts General Hospital | B8: 95923 | C8: CIGNA [1006] | D8: Cigna | E8: Commercial | F8: =COUNTIFS(Rates_data!$B$2:$B$75,$A8,Rates_data!$D$2:$D$75,$B8,Rates_data!$E$2:$E$75,$C8,Rates_data!$G$2:$G$75,$E8,Rates_data!$Y$2:$Y$75,1) -> 1 | G8: =_xlfn.MINIFS(Rates_data!$P$2:$P$75,Rates_data!$B$2:$B$75,$A8,Rates_data!$D$2:$D$75,$B8,Rates_data!$E$2:$E$75,$C8,Rates_data!$G$2:$G$75,$E8,Rates_data!$Y$2:$Y$75,1) -> 781.49 | H8: {=MEDIAN(IF((Rates_data!$B$2:$B$75=$A8)*(Rates_data!$D$2:$D$75=$B8)*(Rates_data!$G$2:$G$75=$E8)*(Rates_data!$E$2:$E$75=$C8)*(Rates_data!$Y$2:$Y$75=1)*(Rates_data!$P$2:$P$75<>""),Rates_data!$P$2:$P$75))} -> 781.49 | I8: =_xlfn.MAXIFS(Rates_data!$P$2:$P$75,Rates_data!$B$2:$B$75,$A8,Rates_data!$D$2:$D$75,$B8,Rates_data!$E$2:$E$75,$C8,Rates_data!$G$2:$G$75,$E8,Rates_data!$Y$2:$Y$75,1) -> 781.49 | J8: =IF(F8=0,"",SUMIFS(Rates_data!$R$2:$R$75,Rates_data!$B$2:$B$75,$A8,Rates_data!$D$2:$D$75,$B8,Rates_data!$E$2:$E$75,$C8,Rates_data!$G$2:$G$75,$E8,Rates_data!$Y$2:$Y$75,1)/F8) -> 1 | K8: {=IF(COUNTIFS(Rates_data!$B$2:$B$75,$A8,Rates_data!$D$2:$D$75,$B8,Rates_data!$E$2:$E$75,$C8,Rates_data!$G$2:$G$75,$E8,Rates_data!$Y$2:$Y$75,1,Rates_data!$S$2:$S$75,"<>")=0,"",MEDIAN(IF((Rates_data!$B$2:$B$75=$A8)*(Rates_data!$D$2:$D$75=$B8)*(Rates_data!$G$2:$G$75=$E8)*(Rates_data!$E$2:$E$75=$C8)*(Rates_data!$Y$2:$Y$75=1)*(Rates_data!$S$2:$S$75<>""),Rates_data!$S$2:$S$75)))} -> 750.01 | L8: =IF(COUNTIFS(Rates_data!$B$2:$B$75,$A8,Rates_data!$D$2:$D$75,$B8,Rates_data!$E$2:$E$75,$C8,Rates_data!$G$2:$G$75,$E8,Rates_data!$Y$2:$Y$75,1,Rates_data!$T$2:$T$75,"<>")=0,"",_xlfn.MINIFS(Rates_data!$T$2:$T$75,Rates_data!$B$2:$B$75,$A8,Rates_data!$D$2:$D$75,$B8,Rates_data!$E$2:$E$75,$C8,Rates_data!$G$2:$G$75,$E8,Rates_data!$Y$2:$Y$75,1)) -> 503.18 | M8: =IF(COUNTIFS(Rates_data!$B$2:$B$75,$A8,Rates_data!$D$2:$D$75,$B8,Rates_data!$E$2:$E$75,$C8,Rates_data!$G$2:$G$75,$E8,Rates_data!$Y$2:$Y$75,1,Rates_data!$U$2:$U$75,"<>")=0,"",_xlfn.MAXIFS(Rates_data!$U$2:$U$75,Rates_data!$B$2:$B$75,$A8,Rates_data!$D$2:$D$75,$B8,Rates_data!$E$2:$E$75,$C8,Rates_data!$G$2:$G$75,$E8,Rates_data!$Y$2:$Y$75,1)) -> 750.01 | N8: 17 | O8: =IF(K8<>"",K8,H8) -> 750.01 | P8: =IF(K8<>"","median allowed","median negotiated") -> median allowed
A9: Massachusetts General Hospital | B9: 95923 | C9: INTERNATIONAL COMMERCIAL [140001] | D9: International commercial | E9: Commercial | F9: =COUNTIFS(Rates_data!$B$2:$B$75,$A9,Rates_data!$D$2:$D$75,$B9,Rates_data!$E$2:$E$75,$C9,Rates_data!$G$2:$G$75,$E9,Rates_data!$Y$2:$Y$75,1) -> 1 | G9: =_xlfn.MINIFS(Rates_data!$P$2:$P$75,Rates_data!$B$2:$B$75,$A9,Rates_data!$D$2:$D$75,$B9,Rates_data!$E$2:$E$75,$C9,Rates_data!$G$2:$G$75,$E9,Rates_data!$Y$2:$Y$75,1) -> 638.95 | H9: {=MEDIAN(IF((Rates_data!$B$2:$B$75=$A9)*(Rates_data!$D$2:$D$75=$B9)*(Rates_data!$G$2:$G$75=$E9)*(Rates_data!$E$2:$E$75=$C9)*(Rates_data!$Y$2:$Y$75=1)*(Rates_data!$P$2:$P$75<>""),Rates_data!$P$2:$P$75))} -> 638.95 | I9: =_xlfn.MAXIFS(Rates_data!$P$2:$P$75,Rates_data!$B$2:$B$75,$A9,Rates_data!$D$2:$D$75,$B9,Rates_data!$E$2:$E$75,$C9,Rates_data!$G$2:$G$75,$E9,Rates_data!$Y$2:$Y$75,1) -> 638.95 | J9: =IF(F9=0,"",SUMIFS(Rates_data!$R$2:$R$75,Rates_data!$B$2:$B$75,$A9,Rates_data!$D$2:$D$75,$B9,Rates_data!$E$2:$E$75,$C9,Rates_data!$G$2:$G$75,$E9,Rates_data!$Y$2:$Y$75,1)/F9) -> 1 | K9: {=IF(COUNTIFS(Rates_data!$B$2:$B$75,$A9,Rates_data!$D$2:$D$75,$B9,Rates_data!$E$2:$E$75,$C9,Rates_data!$G$2:$G$75,$E9,Rates_data!$Y$2:$Y$75,1,Rates_data!$S$2:$S$75,"<>")=0,"",MEDIAN(IF((Rates_data!$B$2:$B$75=$A9)*(Rates_data!$D$2:$D$75=$B9)*(Rates_data!$G$2:$G$75=$E9)*(Rates_data!$E$2:$E$75=$C9)*(Rates_data!$Y$2:$Y$75=1)*(Rates_data!$S$2:$S$75<>""),Rates_data!$S$2:$S$75)))} -> 619.45 | L9: =IF(COUNTIFS(Rates_data!$B$2:$B$75,$A9,Rates_data!$D$2:$D$75,$B9,Rates_data!$E$2:$E$75,$C9,Rates_data!$G$2:$G$75,$E9,Rates_data!$Y$2:$Y$75,1,Rates_data!$T$2:$T$75,"<>")=0,"",_xlfn.MINIFS(Rates_data!$T$2:$T$75,Rates_data!$B$2:$B$75,$A9,Rates_data!$D$2:$D$75,$B9,Rates_data!$E$2:$E$75,$C9,Rates_data!$G$2:$G$75,$E9,Rates_data!$Y$2:$Y$75,1)) -> 619.45 | M9: =IF(COUNTIFS(Rates_data!$B$2:$B$75,$A9,Rates_data!$D$2:$D$75,$B9,Rates_data!$E$2:$E$75,$C9,Rates_data!$G$2:$G$75,$E9,Rates_data!$Y$2:$Y$75,1,Rates_data!$U$2:$U$75,"<>")=0,"",_xlfn.MAXIFS(Rates_data!$U$2:$U$75,Rates_data!$B$2:$B$75,$A9,Rates_data!$D$2:$D$75,$B9,Rates_data!$E$2:$E$75,$C9,Rates_data!$G$2:$G$75,$E9,Rates_data!$Y$2:$Y$75,1)) -> 619.45 | N9: 1 through 10 | O9: =IF(K9<>"",K9,H9) -> 619.45 | P9: =IF(K9<>"","median allowed","median negotiated") -> median allowed
A10: Massachusetts General Hospital | B10: 95923 | C10: MGB HEALTH PLAN [150001] | D10: Mass General Brigham Health Plan | E10: Commercial | F10: =COUNTIFS(Rates_data!$B$2:$B$75,$A10,Rates_data!$D$2:$D$75,$B10,Rates_data!$E$2:$E$75,$C10,Rates_data!$G$2:$G$75,$E10,Rates_data!$Y$2:$Y$75,1) -> 2 | G10: =_xlfn.MINIFS(Rates_data!$P$2:$P$75,Rates_data!$B$2:$B$75,$A10,Rates_data!$D$2:$D$75,$B10,Rates_data!$E$2:$E$75,$C10,Rates_data!$G$2:$G$75,$E10,Rates_data!$Y$2:$Y$75,1) -> 358.8 | H10: {=MEDIAN(IF((Rates_data!$B$2:$B$75=$A10)*(Rates_data!$D$2:$D$75=$B10)*(Rates_data!$G$2:$G$75=$E10)*(Rates_data!$E$2:$E$75=$C10)*(Rates_data!$Y$2:$Y$75=1)*(Rates_data!$P$2:$P$75<>""),Rates_data!$P$2:$P$75))} -> 367.645 | I10: =_xlfn.MAXIFS(Rates_data!$P$2:$P$75,Rates_data!$B$2:$B$75,$A10,Rates_data!$D$2:$D$75,$B10,Rates_data!$E$2:$E$75,$C10,Rates_data!$G$2:$G$75,$E10,Rates_data!$Y$2:$Y$75,1) -> 376.49 | J10: =IF(F10=0,"",SUMIFS(Rates_data!$R$2:$R$75,Rates_data!$B$2:$B$75,$A10,Rates_data!$D$2:$D$75,$B10,Rates_data!$E$2:$E$75,$C10,Rates_data!$G$2:$G$75,$E10,Rates_data!$Y$2:$Y$75,1)/F10) -> 1 | K10: {=IF(COUNTIFS(Rates_data!$B$2:$B$75,$A10,Rates_data!$D$2:$D$75,$B10,Rates_data!$E$2:$E$75,$C10,Rates_data!$G$2:$G$75,$E10,Rates_data!$Y$2:$Y$75,1,Rates_data!$S$2:$S$75,"<>")=0,"",MEDIAN(IF((Rates_data!$B$2:$B$75=$A10)*(Rates_data!$D$2:$D$75=$B10)*(Rates_data!$G$2:$G$75=$E10)*(Rates_data!$E$2:$E$75=$C10)*(Rates_data!$Y$2:$Y$75=1)*(Rates_data!$S$2:$S$75<>""),Rates_data!$S$2:$S$75)))} -> 364.045 | L10: =IF(COUNTIFS(Rates_data!$B$2:$B$75,$A10,Rates_data!$D$2:$D$75,$B10,Rates_data!$E$2:$E$75,$C10,Rates_data!$G$2:$G$75,$E10,Rates_data!$Y$2:$Y$75,1,Rates_data!$T$2:$T$75,"<>")=0,"",_xlfn.MINIFS(Rates_data!$T$2:$T$75,Rates_data!$B$2:$B$75,$A10,Rates_data!$D$2:$D$75,$B10,Rates_data!$E$2:$E$75,$C10,Rates_data!$G$2:$G$75,$E10,Rates_data!$Y$2:$Y$75,1)) -> 302.1 | M10: =IF(COUNTIFS(Rates_data!$B$2:$B$75,$A10,Rates_data!$D$2:$D$75,$B10,Rates_data!$E$2:$E$75,$C10,Rates_data!$G$2:$G$75,$E10,Rates_data!$Y$2:$Y$75,1,Rates_data!$U$2:$U$75,"<>")=0,"",_xlfn.MAXIFS(Rates_data!$U$2:$U$75,Rates_data!$B$2:$B$75,$A10,Rates_data!$D$2:$D$75,$B10,Rates_data!$E$2:$E$75,$C10,Rates_data!$G$2:$G$75,$E10,Rates_data!$Y$2:$Y$75,1)) -> 372.62 | N10: 13; 36 | O10: =IF(K10<>"",K10,H10) -> 364.045 | P10: =IF(K10<>"","median allowed","median negotiated") -> median allowed
A11: Massachusetts General Hospital | B11: 95923 | C11: UNITED HEALTHCARE [1016] | D11: UnitedHealthcare | E11: Commercial | F11: =COUNTIFS(Rates_data!$B$2:$B$75,$A11,Rates_data!$D$2:$D$75,$B11,Rates_data!$E$2:$E$75,$C11,Rates_data!$G$2:$G$75,$E11,Rates_data!$Y$2:$Y$75,1) -> 2 | G11: =_xlfn.MINIFS(Rates_data!$P$2:$P$75,Rates_data!$B$2:$B$75,$A11,Rates_data!$D$2:$D$75,$B11,Rates_data!$E$2:$E$75,$C11,Rates_data!$G$2:$G$75,$E11,Rates_data!$Y$2:$Y$75,1) -> 421.71 | H11: {=MEDIAN(IF((Rates_data!$B$2:$B$75=$A11)*(Rates_data!$D$2:$D$75=$B11)*(Rates_data!$G$2:$G$75=$E11)*(Rates_data!$E$2:$E$75=$C11)*(Rates_data!$Y$2:$Y$75=1)*(Rates_data!$P$2:$P$75<>""),Rates_data!$P$2:$P$75))} -> 612.51 | I11: =_xlfn.MAXIFS(Rates_data!$P$2:$P$75,Rates_data!$B$2:$B$75,$A11,Rates_data!$D$2:$D$75,$B11,Rates_data!$E$2:$E$75,$C11,Rates_data!$G$2:$G$75,$E11,Rates_data!$Y$2:$Y$75,1) -> 803.31 | J11: =IF(F11=0,"",SUMIFS(Rates_data!$R$2:$R$75,Rates_data!$B$2:$B$75,$A11,Rates_data!$D$2:$D$75,$B11,Rates_data!$E$2:$E$75,$C11,Rates_data!$G$2:$G$75,$E11,Rates_data!$Y$2:$Y$75,1)/F11) -> 1 | K11: {=IF(COUNTIFS(Rates_data!$B$2:$B$75,$A11,Rates_data!$D$2:$D$75,$B11,Rates_data!$E$2:$E$75,$C11,Rates_data!$G$2:$G$75,$E11,Rates_data!$Y$2:$Y$75,1,Rates_data!$S$2:$S$75,"<>")=0,"",MEDIAN(IF((Rates_data!$B$2:$B$75=$A11)*(Rates_data!$D$2:$D$75=$B11)*(Rates_data!$G$2:$G$75=$E11)*(Rates_data!$E$2:$E$75=$C11)*(Rates_data!$Y$2:$Y$75=1)*(Rates_data!$S$2:$S$75<>""),Rates_data!$S$2:$S$75)))} -> 761.83 | L11: =IF(COUNTIFS(Rates_data!$B$2:$B$75,$A11,Rates_data!$D$2:$D$75,$B11,Rates_data!$E$2:$E$75,$C11,Rates_data!$G$2:$G$75,$E11,Rates_data!$Y$2:$Y$75,1,Rates_data!$T$2:$T$75,"<>")=0,"",_xlfn.MINIFS(Rates_data!$T$2:$T$75,Rates_data!$B$2:$B$75,$A11,Rates_data!$D$2:$D$75,$B11,Rates_data!$E$2:$E$75,$C11,Rates_data!$G$2:$G$75,$E11,Rates_data!$Y$2:$Y$75,1)) -> 761.83 | M11: =IF(COUNTIFS(Rates_data!$B$2:$B$75,$A11,Rates_data!$D$2:$D$75,$B11,Rates_data!$E$2:$E$75,$C11,Rates_data!$G$2:$G$75,$E11,Rates_data!$Y$2:$Y$75,1,Rates_data!$U$2:$U$75,"<>")=0,"",_xlfn.MAXIFS(Rates_data!$U$2:$U$75,Rates_data!$B$2:$B$75,$A11,Rates_data!$D$2:$D$75,$B11,Rates_data!$E$2:$E$75,$C11,Rates_data!$G$2:$G$75,$E11,Rates_data!$Y$2:$Y$75,1)) -> 1212.81 | N11: 1 through 10; 18 | O11: =IF(K11<>"",K11,H11) -> 761.83 | P11: =IF(K11<>"","median allowed","median negotiated") -> median allowed
A12: Massachusetts General Hospital | B12: 95923 | C12: WELLPOINT [1015] | D12: Wellpoint | E12: Commercial | F12: =COUNTIFS(Rates_data!$B$2:$B$75,$A12,Rates_data!$D$2:$D$75,$B12,Rates_data!$E$2:$E$75,$C12,Rates_data!$G$2:$G$75,$E12,Rates_data!$Y$2:$Y$75,1) -> 1 | G12: =_xlfn.MINIFS(Rates_data!$P$2:$P$75,Rates_data!$B$2:$B$75,$A12,Rates_data!$D$2:$D$75,$B12,Rates_data!$E$2:$E$75,$C12,Rates_data!$G$2:$G$75,$E12,Rates_data!$Y$2:$Y$75,1) -> 725.26 | H12: {=MEDIAN(IF((Rates_data!$B$2:$B$75=$A12)*(Rates_data!$D$2:$D$75=$B12)*(Rates_data!$G$2:$G$75=$E12)*(Rates_data!$E$2:$E$75=$C12)*(Rates_data!$Y$2:$Y$75=1)*(Rates_data!$P$2:$P$75<>""),Rates_data!$P$2:$P$75))} -> 725.26 | I12: =_xlfn.MAXIFS(Rates_data!$P$2:$P$75,Rates_data!$B$2:$B$75,$A12,Rates_data!$D$2:$D$75,$B12,Rates_data!$E$2:$E$75,$C12,Rates_data!$G$2:$G$75,$E12,Rates_data!$Y$2:$Y$75,1) -> 725.26 | J12: =IF(F12=0,"",SUMIFS(Rates_data!$R$2:$R$75,Rates_data!$B$2:$B$75,$A12,Rates_data!$D$2:$D$75,$B12,Rates_data!$E$2:$E$75,$C12,Rates_data!$G$2:$G$75,$E12,Rates_data!$Y$2:$Y$75,1)/F12) -> 1 | K12: {=IF(COUNTIFS(Rates_data!$B$2:$B$75,$A12,Rates_data!$D$2:$D$75,$B12,Rates_data!$E$2:$E$75,$C12,Rates_data!$G$2:$G$75,$E12,Rates_data!$Y$2:$Y$75,1,Rates_data!$S$2:$S$75,"<>")=0,"",MEDIAN(IF((Rates_data!$B$2:$B$75=$A12)*(Rates_data!$D$2:$D$75=$B12)*(Rates_data!$G$2:$G$75=$E12)*(Rates_data!$E$2:$E$75=$C12)*(Rates_data!$Y$2:$Y$75=1)*(Rates_data!$S$2:$S$75<>""),Rates_data!$S$2:$S$75)))} -> 709.51 | L12: =IF(COUNTIFS(Rates_data!$B$2:$B$75,$A12,Rates_data!$D$2:$D$75,$B12,Rates_data!$E$2:$E$75,$C12,Rates_data!$G$2:$G$75,$E12,Rates_data!$Y$2:$Y$75,1,Rates_data!$T$2:$T$75,"<>")=0,"",_xlfn.MINIFS(Rates_data!$T$2:$T$75,Rates_data!$B$2:$B$75,$A12,Rates_data!$D$2:$D$75,$B12,Rates_data!$E$2:$E$75,$C12,Rates_data!$G$2:$G$75,$E12,Rates_data!$Y$2:$Y$75,1)) -> 709.51 | M12: =IF(COUNTIFS(Rates_data!$B$2:$B$75,$A12,Rates_data!$D$2:$D$75,$B12,Rates_data!$E$2:$E$75,$C12,Rates_data!$G$2:$G$75,$E12,Rates_data!$Y$2:$Y$75,1,Rates_data!$U$2:$U$75,"<>")=0,"",_xlfn.MAXIFS(Rates_data!$U$2:$U$75,Rates_data!$B$2:$B$75,$A12,Rates_data!$D$2:$D$75,$B12,Rates_data!$E$2:$E$75,$C12,Rates_data!$G$2:$G$75,$E12,Rates_data!$Y$2:$Y$75,1)) -> 709.51 | N12: 1 through 10 | O12: =IF(K12<>"",K12,H12) -> 709.51 | P12: =IF(K12<>"","median allowed","median negotiated") -> median allowed
A13: Massachusetts General Hospital | B13: 95924 | C13: AETNA [1001] | D13: Aetna | E13: Commercial | F13: =COUNTIFS(Rates_data!$B$2:$B$75,$A13,Rates_data!$D$2:$D$75,$B13,Rates_data!$E$2:$E$75,$C13,Rates_data!$G$2:$G$75,$E13,Rates_data!$Y$2:$Y$75,1) -> 1 | G13: =_xlfn.MINIFS(Rates_data!$P$2:$P$75,Rates_data!$B$2:$B$75,$A13,Rates_data!$D$2:$D$75,$B13,Rates_data!$E$2:$E$75,$C13,Rates_data!$G$2:$G$75,$E13,Rates_data!$Y$2:$Y$75,1) -> 801.3 | H13: {=MEDIAN(IF((Rates_data!$B$2:$B$75=$A13)*(Rates_data!$D$2:$D$75=$B13)*(Rates_data!$G$2:$G$75=$E13)*(Rates_data!$E$2:$E$75=$C13)*(Rates_data!$Y$2:$Y$75=1)*(Rates_data!$P$2:$P$75<>""),Rates_data!$P$2:$P$75))} -> 801.3 | I13: =_xlfn.MAXIFS(Rates_data!$P$2:$P$75,Rates_data!$B$2:$B$75,$A13,Rates_data!$D$2:$D$75,$B13,Rates_data!$E$2:$E$75,$C13,Rates_data!$G$2:$G$75,$E13,Rates_data!$Y$2:$Y$75,1) -> 801.3 | J13: =IF(F13=0,"",SUMIFS(Rates_data!$R$2:$R$75,Rates_data!$B$2:$B$75,$A13,Rates_data!$D$2:$D$75,$B13,Rates_data!$E$2:$E$75,$C13,Rates_data!$G$2:$G$75,$E13,Rates_data!$Y$2:$Y$75,1)/F13) -> 1 | K13: {=IF(COUNTIFS(Rates_data!$B$2:$B$75,$A13,Rates_data!$D$2:$D$75,$B13,Rates_data!$E$2:$E$75,$C13,Rates_data!$G$2:$G$75,$E13,Rates_data!$Y$2:$Y$75,1,Rates_data!$S$2:$S$75,"<>")=0,"",MEDIAN(IF((Rates_data!$B$2:$B$75=$A13)*(Rates_data!$D$2:$D$75=$B13)*(Rates_data!$G$2:$G$75=$E13)*(Rates_data!$E$2:$E$75=$C13)*(Rates_data!$Y$2:$Y$75=1)*(Rates_data!$S$2:$S$75<>""),Rates_data!$S$2:$S$75)))} -> 1444.72 | L13: =IF(COUNTIFS(Rates_data!$B$2:$B$75,$A13,Rates_data!$D$2:$D$75,$B13,Rates_data!$E$2:$E$75,$C13,Rates_data!$G$2:$G$75,$E13,Rates_data!$Y$2:$Y$75,1,Rates_data!$T$2:$T$75,"<>")=0,"",_xlfn.MINIFS(Rates_data!$T$2:$T$75,Rates_data!$B$2:$B$75,$A13,Rates_data!$D$2:$D$75,$B13,Rates_data!$E$2:$E$75,$C13,Rates_data!$G$2:$G$75,$E13,Rates_data!$Y$2:$Y$75,1)) -> 753.5 | M13: =IF(COUNTIFS(Rates_data!$B$2:$B$75,$A13,Rates_data!$D$2:$D$75,$B13,Rates_data!$E$2:$E$75,$C13,Rates_data!$G$2:$G$75,$E13,Rates_data!$Y$2:$Y$75,1,Rates_data!$U$2:$U$75,"<>")=0,"",_xlfn.MAXIFS(Rates_data!$U$2:$U$75,Rates_data!$B$2:$B$75,$A13,Rates_data!$D$2:$D$75,$B13,Rates_data!$E$2:$E$75,$C13,Rates_data!$G$2:$G$75,$E13,Rates_data!$Y$2:$Y$75,1)) -> 1444.72 | N13: 1 through 10 | O13: =IF(K13<>"",K13,H13) -> 1444.72 | P13: =IF(K13<>"","median allowed","median negotiated") -> median allowed
A14: Massachusetts General Hospital | B14: 95924 | C14: CIGNA ALTERNATE [1018] | D14: Cigna | E14: Commercial | F14: =COUNTIFS(Rates_data!$B$2:$B$75,$A14,Rates_data!$D$2:$D$75,$B14,Rates_data!$E$2:$E$75,$C14,Rates_data!$G$2:$G$75,$E14,Rates_data!$Y$2:$Y$75,1) -> 1 | G14: =_xlfn.MINIFS(Rates_data!$P$2:$P$75,Rates_data!$B$2:$B$75,$A14,Rates_data!$D$2:$D$75,$B14,Rates_data!$E$2:$E$75,$C14,Rates_data!$G$2:$G$75,$E14,Rates_data!$Y$2:$Y$75,1) -> 611.88 | H14: {=MEDIAN(IF((Rates_data!$B$2:$B$75=$A14)*(Rates_data!$D$2:$D$75=$B14)*(Rates_data!$G$2:$G$75=$E14)*(Rates_data!$E$2:$E$75=$C14)*(Rates_data!$Y$2:$Y$75=1)*(Rates_data!$P$2:$P$75<>""),Rates_data!$P$2:$P$75))} -> 611.88 | I14: =_xlfn.MAXIFS(Rates_data!$P$2:$P$75,Rates_data!$B$2:$B$75,$A14,Rates_data!$D$2:$D$75,$B14,Rates_data!$E$2:$E$75,$C14,Rates_data!$G$2:$G$75,$E14,Rates_data!$Y$2:$Y$75,1) -> 611.88 | J14: =IF(F14=0,"",SUMIFS(Rates_data!$R$2:$R$75,Rates_data!$B$2:$B$75,$A14,Rates_data!$D$2:$D$75,$B14,Rates_data!$E$2:$E$75,$C14,Rates_data!$G$2:$G$75,$E14,Rates_data!$Y$2:$Y$75,1)/F14) -> 1 | K14: {=IF(COUNTIFS(Rates_data!$B$2:$B$75,$A14,Rates_data!$D$2:$D$75,$B14,Rates_data!$E$2:$E$75,$C14,Rates_data!$G$2:$G$75,$E14,Rates_data!$Y$2:$Y$75,1,Rates_data!$S$2:$S$75,"<>")=0,"",MEDIAN(IF((Rates_data!$B$2:$B$75=$A14)*(Rates_data!$D$2:$D$75=$B14)*(Rates_data!$G$2:$G$75=$E14)*(Rates_data!$E$2:$E$75=$C14)*(Rates_data!$Y$2:$Y$75=1)*(Rates_data!$S$2:$S$75<>""),Rates_data!$S$2:$S$75)))} -> 587.66 | L14: =IF(COUNTIFS(Rates_data!$B$2:$B$75,$A14,Rates_data!$D$2:$D$75,$B14,Rates_data!$E$2:$E$75,$C14,Rates_data!$G$2:$G$75,$E14,Rates_data!$Y$2:$Y$75,1,Rates_data!$T$2:$T$75,"<>")=0,"",_xlfn.MINIFS(Rates_data!$T$2:$T$75,Rates_data!$B$2:$B$75,$A14,Rates_data!$D$2:$D$75,$B14,Rates_data!$E$2:$E$75,$C14,Rates_data!$G$2:$G$75,$E14,Rates_data!$Y$2:$Y$75,1)) -> 587.66 | M14: =IF(COUNTIFS(Rates_data!$B$2:$B$75,$A14,Rates_data!$D$2:$D$75,$B14,Rates_data!$E$2:$E$75,$C14,Rates_data!$G$2:$G$75,$E14,Rates_data!$Y$2:$Y$75,1,Rates_data!$U$2:$U$75,"<>")=0,"",_xlfn.MAXIFS(Rates_data!$U$2:$U$75,Rates_data!$B$2:$B$75,$A14,Rates_data!$D$2:$D$75,$B14,Rates_data!$E$2:$E$75,$C14,Rates_data!$G$2:$G$75,$E14,Rates_data!$Y$2:$Y$75,1)) -> 587.66 | N14: 1 through 10 | O14: =IF(K14<>"",K14,H14) -> 587.66 | P14: =IF(K14<>"","median allowed","median negotiated") -> median allowed
A15: Massachusetts General Hospital | B15: 95924 | C15: CIGNA [1006] | D15: Cigna | E15: Commercial | F15: =COUNTIFS(Rates_data!$B$2:$B$75,$A15,Rates_data!$D$2:$D$75,$B15,Rates_data!$E$2:$E$75,$C15,Rates_data!$G$2:$G$75,$E15,Rates_data!$Y$2:$Y$75,1) -> 1 | G15: =_xlfn.MINIFS(Rates_data!$P$2:$P$75,Rates_data!$B$2:$B$75,$A15,Rates_data!$D$2:$D$75,$B15,Rates_data!$E$2:$E$75,$C15,Rates_data!$G$2:$G$75,$E15,Rates_data!$Y$2:$Y$75,1) -> 912.66 | H15: {=MEDIAN(IF((Rates_data!$B$2:$B$75=$A15)*(Rates_data!$D$2:$D$75=$B15)*(Rates_data!$G$2:$G$75=$E15)*(Rates_data!$E$2:$E$75=$C15)*(Rates_data!$Y$2:$Y$75=1)*(Rates_data!$P$2:$P$75<>""),Rates_data!$P$2:$P$75))} -> 912.66 | I15: =_xlfn.MAXIFS(Rates_data!$P$2:$P$75,Rates_data!$B$2:$B$75,$A15,Rates_data!$D$2:$D$75,$B15,Rates_data!$E$2:$E$75,$C15,Rates_data!$G$2:$G$75,$E15,Rates_data!$Y$2:$Y$75,1) -> 912.66 | J15: =IF(F15=0,"",SUMIFS(Rates_data!$R$2:$R$75,Rates_data!$B$2:$B$75,$A15,Rates_data!$D$2:$D$75,$B15,Rates_data!$E$2:$E$75,$C15,Rates_data!$G$2:$G$75,$E15,Rates_data!$Y$2:$Y$75,1)/F15) -> 1 | K15: {=IF(COUNTIFS(Rates_data!$B$2:$B$75,$A15,Rates_data!$D$2:$D$75,$B15,Rates_data!$E$2:$E$75,$C15,Rates_data!$G$2:$G$75,$E15,Rates_data!$Y$2:$Y$75,1,Rates_data!$S$2:$S$75,"<>")=0,"",MEDIAN(IF((Rates_data!$B$2:$B$75=$A15)*(Rates_data!$D$2:$D$75=$B15)*(Rates_data!$G$2:$G$75=$E15)*(Rates_data!$E$2:$E$75=$C15)*(Rates_data!$Y$2:$Y$75=1)*(Rates_data!$S$2:$S$75<>""),Rates_data!$S$2:$S$75)))} -> 875.93 | L15: =IF(COUNTIFS(Rates_data!$B$2:$B$75,$A15,Rates_data!$D$2:$D$75,$B15,Rates_data!$E$2:$E$75,$C15,Rates_data!$G$2:$G$75,$E15,Rates_data!$Y$2:$Y$75,1,Rates_data!$T$2:$T$75,"<>")=0,"",_xlfn.MINIFS(Rates_data!$T$2:$T$75,Rates_data!$B$2:$B$75,$A15,Rates_data!$D$2:$D$75,$B15,Rates_data!$E$2:$E$75,$C15,Rates_data!$G$2:$G$75,$E15,Rates_data!$Y$2:$Y$75,1)) -> 587.66 | M15: =IF(COUNTIFS(Rates_data!$B$2:$B$75,$A15,Rates_data!$D$2:$D$75,$B15,Rates_data!$E$2:$E$75,$C15,Rates_data!$G$2:$G$75,$E15,Rates_data!$Y$2:$Y$75,1,Rates_data!$U$2:$U$75,"<>")=0,"",_xlfn.MAXIFS(Rates_data!$U$2:$U$75,Rates_data!$B$2:$B$75,$A15,Rates_data!$D$2:$D$75,$B15,Rates_data!$E$2:$E$75,$C15,Rates_data!$G$2:$G$75,$E15,Rates_data!$Y$2:$Y$75,1)) -> 875.93 | N15: 18 | O15: =IF(K15<>"",K15,H15) -> 875.93 | P15: =IF(K15<>"","median allowed","median negotiated") -> median allowed
A16: Massachusetts General Hospital | B16: 95924 | C16: INTERNATIONAL COMMERCIAL [140001] | D16: International commercial | E16: Commercial | F16: =COUNTIFS(Rates_data!$B$2:$B$75,$A16,Rates_data!$D$2:$D$75,$B16,Rates_data!$E$2:$E$75,$C16,Rates_data!$G$2:$G$75,$E16,Rates_data!$Y$2:$Y$75,1) -> 1 | G16: =_xlfn.MINIFS(Rates_data!$P$2:$P$75,Rates_data!$B$2:$B$75,$A16,Rates_data!$D$2:$D$75,$B16,Rates_data!$E$2:$E$75,$C16,Rates_data!$G$2:$G$75,$E16,Rates_data!$Y$2:$Y$75,1) -> 746.2 | H16: {=MEDIAN(IF((Rates_data!$B$2:$B$75=$A16)*(Rates_data!$D$2:$D$75=$B16)*(Rates_data!$G$2:$G$75=$E16)*(Rates_data!$E$2:$E$75=$C16)*(Rates_data!$Y$2:$Y$75=1)*(Rates_data!$P$2:$P$75<>""),Rates_data!$P$2:$P$75))} -> 746.2 | I16: =_xlfn.MAXIFS(Rates_data!$P$2:$P$75,Rates_data!$B$2:$B$75,$A16,Rates_data!$D$2:$D$75,$B16,Rates_data!$E$2:$E$75,$C16,Rates_data!$G$2:$G$75,$E16,Rates_data!$Y$2:$Y$75,1) -> 746.2 | J16: =IF(F16=0,"",SUMIFS(Rates_data!$R$2:$R$75,Rates_data!$B$2:$B$75,$A16,Rates_data!$D$2:$D$75,$B16,Rates_data!$E$2:$E$75,$C16,Rates_data!$G$2:$G$75,$E16,Rates_data!$Y$2:$Y$75,1)/F16) -> 1 | K16: {=IF(COUNTIFS(Rates_data!$B$2:$B$75,$A16,Rates_data!$D$2:$D$75,$B16,Rates_data!$E$2:$E$75,$C16,Rates_data!$G$2:$G$75,$E16,Rates_data!$Y$2:$Y$75,1,Rates_data!$S$2:$S$75,"<>")=0,"",MEDIAN(IF((Rates_data!$B$2:$B$75=$A16)*(Rates_data!$D$2:$D$75=$B16)*(Rates_data!$G$2:$G$75=$E16)*(Rates_data!$E$2:$E$75=$C16)*(Rates_data!$Y$2:$Y$75=1)*(Rates_data!$S$2:$S$75<>""),Rates_data!$S$2:$S$75)))} -> 723.45 | L16: =IF(COUNTIFS(Rates_data!$B$2:$B$75,$A16,Rates_data!$D$2:$D$75,$B16,Rates_data!$E$2:$E$75,$C16,Rates_data!$G$2:$G$75,$E16,Rates_data!$Y$2:$Y$75,1,Rates_data!$T$2:$T$75,"<>")=0,"",_xlfn.MINIFS(Rates_data!$T$2:$T$75,Rates_data!$B$2:$B$75,$A16,Rates_data!$D$2:$D$75,$B16,Rates_data!$E$2:$E$75,$C16,Rates_data!$G$2:$G$75,$E16,Rates_data!$Y$2:$Y$75,1)) -> 723.45 | M16: =IF(COUNTIFS(Rates_data!$B$2:$B$75,$A16,Rates_data!$D$2:$D$75,$B16,Rates_data!$E$2:$E$75,$C16,Rates_data!$G$2:$G$75,$E16,Rates_data!$Y$2:$Y$75,1,Rates_data!$U$2:$U$75,"<>")=0,"",_xlfn.MAXIFS(Rates_data!$U$2:$U$75,Rates_data!$B$2:$B$75,$A16,Rates_data!$D$2:$D$75,$B16,Rates_data!$E$2:$E$75,$C16,Rates_data!$G$2:$G$75,$E16,Rates_data!$Y$2:$Y$75,1)) -> 723.45 | N16: 1 through 10 | O16: =IF(K16<>"",K16,H16) -> 723.45 | P16: =IF(K16<>"","median allowed","median negotiated") -> median allowed
... A51: Brigham and Women's Faulkner Hospital | B51: 95924 | C51: TRICARE [160005] | D51: TRICARE | E51: TRICARE | F51: =COUNTIFS(Rates_data!$B$2:$B$75,$A51,Rates_data!$D$2:$D$75,$B51,Rates_data!$E$2:$E$75,$C51,Rates_data!$G$2:$G$75,$E51,Rates_data!$Y$2:$Y$75,1) -> 1 | G51: =_xlfn.MINIFS(Rates_data!$P$2:$P$75,Rates_data!$B$2:$B$75,$A51,Rates_data!$D$2:$D$75,$B51,Rates_data!$E$2:$E$75,$C51,Rates_data!$G$2:$G$75,$E51,Rates_data!$Y$2:$Y$75,1) -> 351.32 | H51: {=MEDIAN(IF((Rates_data!$B$2:$B$75=$A51)*(Rates_data!$D$2:$D$75=$B51)*(Rates_data!$G$2:$G$75=$E51)*(Rates_data!$E$2:$E$75=$C51)*(Rates_data!$Y$2:$Y$75=1)*(Rates_data!$P$2:$P$75<>""),Rates_data!$P$2:$P$75))} -> 351.32 | I51: =_xlfn.MAXIFS(Rates_data!$P$2:$P$75,Rates_data!$B$2:$B$75,$A51,Rates_data!$D$2:$D$75,$B51,Rates_data!$E$2:$E$75,$C51,Rates_data!$G$2:$G$75,$E51,Rates_data!$Y$2:$Y$75,1) -> 351.32 | J51: =IF(F51=0,"",SUMIFS(Rates_data!$R$2:$R$75,Rates_data!$B$2:$B$75,$A51,Rates_data!$D$2:$D$75,$B51,Rates_data!$E$2:$E$75,$C51,Rates_data!$G$2:$G$75,$E51,Rates_data!$Y$2:$Y$75,1)/F51) -> 0 | K51: {=IF(COUNTIFS(Rates_data!$B$2:$B$75,$A51,Rates_data!$D$2:$D$75,$B51,Rates_data!$E$2:$E$75,$C51,Rates_data!$G$2:$G$75,$E51,Rates_data!$Y$2:$Y$75,1,Rates_data!$S$2:$S$75,"<>")=0,"",MEDIAN(IF((Rates_data!$B$2:$B$75=$A51)*(Rates_data!$D$2:$D$75=$B51)*(Rates_data!$G$2:$G$75=$E51)*(Rates_data!$E$2:$E$75=$C51)*(Rates_data!$Y$2:$Y$75=1)*(Rates_data!$S$2:$S$75<>""),Rates_data!$S$2:$S$75)))} -> 351.32 | L51: =IF(COUNTIFS(Rates_data!$B$2:$B$75,$A51,Rates_data!$D$2:$D$75,$B51,Rates_data!$E$2:$E$75,$C51,Rates_data!$G$2:$G$75,$E51,Rates_data!$Y$2:$Y$75,1,Rates_data!$T$2:$T$75,"<>")=0,"",_xlfn.MINIFS(Rates_data!$T$2:$T$75,Rates_data!$B$2:$B$75,$A51,Rates_data!$D$2:$D$75,$B51,Rates_data!$E$2:$E$75,$C51,Rates_data!$G$2:$G$75,$E51,Rates_data!$Y$2:$Y$75,1)) -> 351.32 | M51: =IF(COUNTIFS(Rates_data!$B$2:$B$75,$A51,Rates_data!$D$2:$D$75,$B51,Rates_data!$E$2:$E$75,$C51,Rates_data!$G$2:$G$75,$E51,Rates_data!$Y$2:$Y$75,1,Rates_data!$U$2:$U$75,"<>")=0,"",_xlfn.MAXIFS(Rates_data!$U$2:$U$75,Rates_data!$B$2:$B$75,$A51,Rates_data!$D$2:$D$75,$B51,Rates_data!$E$2:$E$75,$C51,Rates_data!$G$2:$G$75,$E51,Rates_data!$Y$2:$Y$75,1)) -> 351.32 | N51: 1 through 10 | O51: =IF(K51<>"",K51,H51) -> 351.32 | P51: =IF(K51<>"","median allowed","median negotiated") -> median allowed
A52: Beth Israel Deaconess Medical Center | B52: 93660 | C52: BCBS | D52: Blue Cross Blue Shield of MA | E52: Commercial | F52: =COUNTIFS(Rates_data!$B$2:$B$75,$A52,Rates_data!$D$2:$D$75,$B52,Rates_data!$E$2:$E$75,$C52,Rates_data!$G$2:$G$75,$E52,Rates_data!$Y$2:$Y$75,1) -> 2 | G52: =_xlfn.MINIFS(Rates_data!$P$2:$P$75,Rates_data!$B$2:$B$75,$A52,Rates_data!$D$2:$D$75,$B52,Rates_data!$E$2:$E$75,$C52,Rates_data!$G$2:$G$75,$E52,Rates_data!$Y$2:$Y$75,1) -> 1091.24 | H52: {=MEDIAN(IF((Rates_data!$B$2:$B$75=$A52)*(Rates_data!$D$2:$D$75=$B52)*(Rates_data!$G$2:$G$75=$E52)*(Rates_data!$E$2:$E$75=$C52)*(Rates_data!$Y$2:$Y$75=1)*(Rates_data!$P$2:$P$75<>""),Rates_data!$P$2:$P$75))} -> 1116.23 | I52: =_xlfn.MAXIFS(Rates_data!$P$2:$P$75,Rates_data!$B$2:$B$75,$A52,Rates_data!$D$2:$D$75,$B52,Rates_data!$E$2:$E$75,$C52,Rates_data!$G$2:$G$75,$E52,Rates_data!$Y$2:$Y$75,1) -> 1141.22 | J52: =IF(F52=0,"",SUMIFS(Rates_data!$R$2:$R$75,Rates_data!$B$2:$B$75,$A52,Rates_data!$D$2:$D$75,$B52,Rates_data!$E$2:$E$75,$C52,Rates_data!$G$2:$G$75,$E52,Rates_data!$Y$2:$Y$75,1)/F52) -> 0 | K52: {=IF(COUNTIFS(Rates_data!$B$2:$B$75,$A52,Rates_data!$D$2:$D$75,$B52,Rates_data!$E$2:$E$75,$C52,Rates_data!$G$2:$G$75,$E52,Rates_data!$Y$2:$Y$75,1,Rates_data!$S$2:$S$75,"<>")=0,"",MEDIAN(IF((Rates_data!$B$2:$B$75=$A52)*(Rates_data!$D$2:$D$75=$B52)*(Rates_data!$G$2:$G$75=$E52)*(Rates_data!$E$2:$E$75=$C52)*(Rates_data!$Y$2:$Y$75=1)*(Rates_data!$S$2:$S$75<>""),Rates_data!$S$2:$S$75)))} | L52: =IF(COUNTIFS(Rates_data!$B$2:$B$75,$A52,Rates_data!$D$2:$D$75,$B52,Rates_data!$E$2:$E$75,$C52,Rates_data!$G$2:$G$75,$E52,Rates_data!$Y$2:$Y$75,1,Rates_data!$T$2:$T$75,"<>")=0,"",_xlfn.MINIFS(Rates_data!$T$2:$T$75,Rates_data!$B$2:$B$75,$A52,Rates_data!$D$2:$D$75,$B52,Rates_data!$E$2:$E$75,$C52,Rates_data!$G$2:$G$75,$E52,Rates_data!$Y$2:$Y$75,1)) | M52: =IF(COUNTIFS(Rates_data!$B$2:$B$75,$A52,Rates_data!$D$2:$D$75,$B52,Rates_data!$E$2:$E$75,$C52,Rates_data!$G$2:$G$75,$E52,Rates_data!$Y$2:$Y$75,1,Rates_data!$U$2:$U$75,"<>")=0,"",_xlfn.MAXIFS(Rates_data!$U$2:$U$75,Rates_data!$B$2:$B$75,$A52,Rates_data!$D$2:$D$75,$B52,Rates_data!$E$2:$E$75,$C52,Rates_data!$G$2:$G$75,$E52,Rates_data!$Y$2:$Y$75,1)) | O52: =IF(K52<>"",K52,H52) -> 1116.23 | P52: =IF(K52<>"","median allowed","median negotiated") -> median negotiated
A53: Beth Israel Deaconess Medical Center | B53: 93660 | C53: Harvard Pilgrim Healthcare | D53: Harvard Pilgrim / Point32Health | E53: Commercial | F53: =COUNTIFS(Rates_data!$B$2:$B$75,$A53,Rates_data!$D$2:$D$75,$B53,Rates_data!$E$2:$E$75,$C53,Rates_data!$G$2:$G$75,$E53,Rates_data!$Y$2:$Y$75,1) -> 1 | G53: =_xlfn.MINIFS(Rates_data!$P$2:$P$75,Rates_data!$B$2:$B$75,$A53,Rates_data!$D$2:$D$75,$B53,Rates_data!$E$2:$E$75,$C53,Rates_data!$G$2:$G$75,$E53,Rates_data!$Y$2:$Y$75,1) -> 1329.39 | H53: {=MEDIAN(IF((Rates_data!$B$2:$B$75=$A53)*(Rates_data!$D$2:$D$75=$B53)*(Rates_data!$G$2:$G$75=$E53)*(Rates_data!$E$2:$E$75=$C53)*(Rates_data!$Y$2:$Y$75=1)*(Rates_data!$P$2:$P$75<>""),Rates_data!$P$2:$P$75))} -> 1329.39 | I53: =_xlfn.MAXIFS(Rates_data!$P$2:$P$75,Rates_data!$B$2:$B$75,$A53,Rates_data!$D$2:$D$75,$B53,Rates_data!$E$2:$E$75,$C53,Rates_data!$G$2:$G$75,$E53,Rates_data!$Y$2:$Y$75,1) -> 1329.39 | J53: =IF(F53=0,"",SUMIFS(Rates_data!$R$2:$R$75,Rates_data!$B$2:$B$75,$A53,Rates_data!$D$2:$D$75,$B53,Rates_data!$E$2:$E$75,$C53,Rates_data!$G$2:$G$75,$E53,Rates_data!$Y$2:$Y$75,1)/F53) -> 0 | K53: {=IF(COUNTIFS(Rates_data!$B$2:$B$75,$A53,Rates_data!$D$2:$D$75,$B53,Rates_data!$E$2:$E$75,$C53,Rates_data!$G$2:$G$75,$E53,Rates_data!$Y$2:$Y$75,1,Rates_data!$S$2:$S$75,"<>")=0,"",MEDIAN(IF((Rates_data!$B$2:$B$75=$A53)*(Rates_data!$D$2:$D$75=$B53)*(Rates_data!$G$2:$G$75=$E53)*(Rates_data!$E$2:$E$75=$C53)*(Rates_data!$Y$2:$Y$75=1)*(Rates_data!$S$2:$S$75<>""),Rates_data!$S$2:$S$75)))} | L53: =IF(COUNTIFS(Rates_data!$B$2:$B$75,$A53,Rates_data!$D$2:$D$75,$B53,Rates_data!$E$2:$E$75,$C53,Rates_data!$G$2:$G$75,$E53,Rates_data!$Y$2:$Y$75,1,Rates_data!$T$2:$T$75,"<>")=0,"",_xlfn.MINIFS(Rates_data!$T$2:$T$75,Rates_data!$B$2:$B$75,$A53,Rates_data!$D$2:$D$75,$B53,Rates_data!$E$2:$E$75,$C53,Rates_data!$G$2:$G$75,$E53,Rates_data!$Y$2:$Y$75,1)) | M53: =IF(COUNTIFS(Rates_data!$B$2:$B$75,$A53,Rates_data!$D$2:$D$75,$B53,Rates_data!$E$2:$E$75,$C53,Rates_data!$G$2:$G$75,$E53,Rates_data!$Y$2:$Y$75,1,Rates_data!$U$2:$U$75,"<>")=0,"",_xlfn.MAXIFS(Rates_data!$U$2:$U$75,Rates_data!$B$2:$B$75,$A53,Rates_data!$D$2:$D$75,$B53,Rates_data!$E$2:$E$75,$C53,Rates_data!$G$2:$G$75,$E53,Rates_data!$Y$2:$Y$75,1)) | O53: =IF(K53<>"",K53,H53) -> 1329.39 | P53: =IF(K53<>"","median allowed","median negotiated") -> median negotiated
A54: Beth Israel Deaconess Medical Center | B54: 93660 | C54: Unicare | D54: Unicare (GIC) | E54: Commercial | F54: =COUNTIFS(Rates_data!$B$2:$B$75,$A54,Rates_data!$D$2:$D$75,$B54,Rates_data!$E$2:$E$75,$C54,Rates_data!$G$2:$G$75,$E54,Rates_data!$Y$2:$Y$75,1) -> 1 | G54: =_xlfn.MINIFS(Rates_data!$P$2:$P$75,Rates_data!$B$2:$B$75,$A54,Rates_data!$D$2:$D$75,$B54,Rates_data!$E$2:$E$75,$C54,Rates_data!$G$2:$G$75,$E54,Rates_data!$Y$2:$Y$75,1) -> 502.78 | H54: {=MEDIAN(IF((Rates_data!$B$2:$B$75=$A54)*(Rates_data!$D$2:$D$75=$B54)*(Rates_data!$G$2:$G$75=$E54)*(Rates_data!$E$2:$E$75=$C54)*(Rates_data!$Y$2:$Y$75=1)*(Rates_data!$P$2:$P$75<>""),Rates_data!$P$2:$P$75))} -> 502.78 | I54: =_xlfn.MAXIFS(Rates_data!$P$2:$P$75,Rates_data!$B$2:$B$75,$A54,Rates_data!$D$2:$D$75,$B54,Rates_data!$E$2:$E$75,$C54,Rates_data!$G$2:$G$75,$E54,Rates_data!$Y$2:$Y$75,1) -> 502.78 | J54: =IF(F54=0,"",SUMIFS(Rates_data!$R$2:$R$75,Rates_data!$B$2:$B$75,$A54,Rates_data!$D$2:$D$75,$B54,Rates_data!$E$2:$E$75,$C54,Rates_data!$G$2:$G$75,$E54,Rates_data!$Y$2:$Y$75,1)/F54) -> 0 | K54: {=IF(COUNTIFS(Rates_data!$B$2:$B$75,$A54,Rates_data!$D$2:$D$75,$B54,Rates_data!$E$2:$E$75,$C54,Rates_data!$G$2:$G$75,$E54,Rates_data!$Y$2:$Y$75,1,Rates_data!$S$2:$S$75,"<>")=0,"",MEDIAN(IF((Rates_data!$B$2:$B$75=$A54)*(Rates_data!$D$2:$D$75=$B54)*(Rates_data!$G$2:$G$75=$E54)*(Rates_data!$E$2:$E$75=$C54)*(Rates_data!$Y$2:$Y$75=1)*(Rates_data!$S$2:$S$75<>""),Rates_data!$S$2:$S$75)))} | L54: =IF(COUNTIFS(Rates_data!$B$2:$B$75,$A54,Rates_data!$D$2:$D$75,$B54,Rates_data!$E$2:$E$75,$C54,Rates_data!$G$2:$G$75,$E54,Rates_data!$Y$2:$Y$75,1,Rates_data!$T$2:$T$75,"<>")=0,"",_xlfn.MINIFS(Rates_data!$T$2:$T$75,Rates_data!$B$2:$B$75,$A54,Rates_data!$D$2:$D$75,$B54,Rates_data!$E$2:$E$75,$C54,Rates_data!$G$2:$G$75,$E54,Rates_data!$Y$2:$Y$75,1)) | M54: =IF(COUNTIFS(Rates_data!$B$2:$B$75,$A54,Rates_data!$D$2:$D$75,$B54,Rates_data!$E$2:$E$75,$C54,Rates_data!$G$2:$G$75,$E54,Rates_data!$Y$2:$Y$75,1,Rates_data!$U$2:$U$75,"<>")=0,"",_xlfn.MAXIFS(Rates_data!$U$2:$U$75,Rates_data!$B$2:$B$75,$A54,Rates_data!$D$2:$D$75,$B54,Rates_data!$E$2:$E$75,$C54,Rates_data!$G$2:$G$75,$E54,Rates_data!$Y$2:$Y$75,1)) | O54: =IF(K54<>"",K54,H54) -> 502.78 | P54: =IF(K54<>"","median allowed","median negotiated") -> median negotiated
A55: Beth Israel Deaconess Medical Center | B55: 95921 | C55: BCBS | D55: Blue Cross Blue Shield of MA | E55: Commercial | F55: =COUNTIFS(Rates_data!$B$2:$B$75,$A55,Rates_data!$D$2:$D$75,$B55,Rates_data!$E$2:$E$75,$C55,Rates_data!$G$2:$G$75,$E55,Rates_data!$Y$2:$Y$75,1) -> 2 | G55: =_xlfn.MINIFS(Rates_data!$P$2:$P$75,Rates_data!$B$2:$B$75,$A55,Rates_data!$D$2:$D$75,$B55,Rates_data!$E$2:$E$75,$C55,Rates_data!$G$2:$G$75,$E55,Rates_data!$Y$2:$Y$75,1) -> 325.87 | H55: {=MEDIAN(IF((Rates_data!$B$2:$B$75=$A55)*(Rates_data!$D$2:$D$75=$B55)*(Rates_data!$G$2:$G$75=$E55)*(Rates_data!$E$2:$E$75=$C55)*(Rates_data!$Y$2:$Y$75=1)*(Rates_data!$P$2:$P$75<>""),Rates_data!$P$2:$P$75))} -> 333.33 | I55: =_xlfn.MAXIFS(Rates_data!$P$2:$P$75,Rates_data!$B$2:$B$75,$A55,Rates_data!$D$2:$D$75,$B55,Rates_data!$E$2:$E$75,$C55,Rates_data!$G$2:$G$75,$E55,Rates_data!$Y$2:$Y$75,1) -> 340.79 | J55: =IF(F55=0,"",SUMIFS(Rates_data!$R$2:$R$75,Rates_data!$B$2:$B$75,$A55,Rates_data!$D$2:$D$75,$B55,Rates_data!$E$2:$E$75,$C55,Rates_data!$G$2:$G$75,$E55,Rates_data!$Y$2:$Y$75,1)/F55) -> 0 | K55: {=IF(COUNTIFS(Rates_data!$B$2:$B$75,$A55,Rates_data!$D$2:$D$75,$B55,Rates_data!$E$2:$E$75,$C55,Rates_data!$G$2:$G$75,$E55,Rates_data!$Y$2:$Y$75,1,Rates_data!$S$2:$S$75,"<>")=0,"",MEDIAN(IF((Rates_data!$B$2:$B$75=$A55)*(Rates_data!$D$2:$D$75=$B55)*(Rates_data!$G$2:$G$75=$E55)*(Rates_data!$E$2:$E$75=$C55)*(Rates_data!$Y$2:$Y$75=1)*(Rates_data!$S$2:$S$75<>""),Rates_data!$S$2:$S$75)))} | L55: =IF(COUNTIFS(Rates_data!$B$2:$B$75,$A55,Rates_data!$D$2:$D$75,$B55,Rates_data!$E$2:$E$75,$C55,Rates_data!$G$2:$G$75,$E55,Rates_data!$Y$2:$Y$75,1,Rates_data!$T$2:$T$75,"<>")=0,"",_xlfn.MINIFS(Rates_data!$T$2:$T$75,Rates_data!$B$2:$B$75,$A55,Rates_data!$D$2:$D$75,$B55,Rates_data!$E$2:$E$75,$C55,Rates_data!$G$2:$G$75,$E55,Rates_data!$Y$2:$Y$75,1)) | M55: =IF(COUNTIFS(Rates_data!$B$2:$B$75,$A55,Rates_data!$D$2:$D$75,$B55,Rates_data!$E$2:$E$75,$C55,Rates_data!$G$2:$G$75,$E55,Rates_data!$Y$2:$Y$75,1,Rates_data!$U$2:$U$75,"<>")=0,"",_xlfn.MAXIFS(Rates_data!$U$2:$U$75,Rates_data!$B$2:$B$75,$A55,Rates_data!$D$2:$D$75,$B55,Rates_data!$E$2:$E$75,$C55,Rates_data!$G$2:$G$75,$E55,Rates_data!$Y$2:$Y$75,1)) | O55: =IF(K55<>"",K55,H55) -> 333.33 | P55: =IF(K55<>"","median allowed","median negotiated") -> median negotiated
A56: Beth Israel Deaconess Medical Center | B56: 95921 | C56: Harvard Pilgrim Healthcare | D56: Harvard Pilgrim / Point32Health | E56: Commercial | F56: =COUNTIFS(Rates_data!$B$2:$B$75,$A56,Rates_data!$D$2:$D$75,$B56,Rates_data!$E$2:$E$75,$C56,Rates_data!$G$2:$G$75,$E56,Rates_data!$Y$2:$Y$75,1) -> 1 | G56: =_xlfn.MINIFS(Rates_data!$P$2:$P$75,Rates_data!$B$2:$B$75,$A56,Rates_data!$D$2:$D$75,$B56,Rates_data!$E$2:$E$75,$C56,Rates_data!$G$2:$G$75,$E56,Rates_data!$Y$2:$Y$75,1) -> 396.97 | H56: {=MEDIAN(IF((Rates_data!$B$2:$B$75=$A56)*(Rates_data!$D$2:$D$75=$B56)*(Rates_data!$G$2:$G$75=$E56)*(Rates_data!$E$2:$E$75=$C56)*(Rates_data!$Y$2:$Y$75=1)*(Rates_data!$P$2:$P$75<>""),Rates_data!$P$2:$P$75))} -> 396.97 | I56: =_xlfn.MAXIFS(Rates_data!$P$2:$P$75,Rates_data!$B$2:$B$75,$A56,Rates_data!$D$2:$D$75,$B56,Rates_data!$E$2:$E$75,$C56,Rates_data!$G$2:$G$75,$E56,Rates_data!$Y$2:$Y$75,1) -> 396.97 | J56: =IF(F56=0,"",SUMIFS(Rates_data!$R$2:$R$75,Rates_data!$B$2:$B$75,$A56,Rates_data!$D$2:$D$75,$B56,Rates_data!$E$2:$E$75,$C56,Rates_data!$G$2:$G$75,$E56,Rates_data!$Y$2:$Y$75,1)/F56) -> 0 | K56: {=IF(COUNTIFS(Rates_data!$B$2:$B$75,$A56,Rates_data!$D$2:$D$75,$B56,Rates_data!$E$2:$E$75,$C56,Rates_data!$G$2:$G$75,$E56,Rates_data!$Y$2:$Y$75,1,Rates_data!$S$2:$S$75,"<>")=0,"",MEDIAN(IF((Rates_data!$B$2:$B$75=$A56)*(Rates_data!$D$2:$D$75=$B56)*(Rates_data!$G$2:$G$75=$E56)*(Rates_data!$E$2:$E$75=$C56)*(Rates_data!$Y$2:$Y$75=1)*(Rates_data!$S$2:$S$75<>""),Rates_data!$S$2:$S$75)))} | L56: =IF(COUNTIFS(Rates_data!$B$2:$B$75,$A56,Rates_data!$D$2:$D$75,$B56,Rates_data!$E$2:$E$75,$C56,Rates_data!$G$2:$G$75,$E56,Rates_data!$Y$2:$Y$75,1,Rates_data!$T$2:$T$75,"<>")=0,"",_xlfn.MINIFS(Rates_data!$T$2:$T$75,Rates_data!$B$2:$B$75,$A56,Rates_data!$D$2:$D$75,$B56,Rates_data!$E$2:$E$75,$C56,Rates_data!$G$2:$G$75,$E56,Rates_data!$Y$2:$Y$75,1)) | M56: =IF(COUNTIFS(Rates_data!$B$2:$B$75,$A56,Rates_data!$D$2:$D$75,$B56,Rates_data!$E$2:$E$75,$C56,Rates_data!$G$2:$G$75,$E56,Rates_data!$Y$2:$Y$75,1,Rates_data!$U$2:$U$75,"<>")=0,"",_xlfn.MAXIFS(Rates_data!$U$2:$U$75,Rates_data!$B$2:$B$75,$A56,Rates_data!$D$2:$D$75,$B56,Rates_data!$E$2:$E$75,$C56,Rates_data!$G$2:$G$75,$E56,Rates_data!$Y$2:$Y$75,1)) | O56: =IF(K56<>"",K56,H56) -> 396.97 | P56: =IF(K56<>"","median allowed","median negotiated") -> median negotiated
A57: Beth Israel Deaconess Medical Center | B57: 95922 | C57: BCBS | D57: Blue Cross Blue Shield of MA | E57: Commercial | F57: =COUNTIFS(Rates_data!$B$2:$B$75,$A57,Rates_data!$D$2:$D$75,$B57,Rates_data!$E$2:$E$75,$C57,Rates_data!$G$2:$G$75,$E57,Rates_data!$Y$2:$Y$75,1) -> 2 | G57: =_xlfn.MINIFS(Rates_data!$P$2:$P$75,Rates_data!$B$2:$B$75,$A57,Rates_data!$D$2:$D$75,$B57,Rates_data!$E$2:$E$75,$C57,Rates_data!$G$2:$G$75,$E57,Rates_data!$Y$2:$Y$75,1) -> 255.23 | H57: {=MEDIAN(IF((Rates_data!$B$2:$B$75=$A57)*(Rates_data!$D$2:$D$75=$B57)*(Rates_data!$G$2:$G$75=$E57)*(Rates_data!$E$2:$E$75=$C57)*(Rates_data!$Y$2:$Y$75=1)*(Rates_data!$P$2:$P$75<>""),Rates_data!$P$2:$P$75))} -> 261.075 | I57: =_xlfn.MAXIFS(Rates_data!$P$2:$P$75,Rates_data!$B$2:$B$75,$A57,Rates_data!$D$2:$D$75,$B57,Rates_data!$E$2:$E$75,$C57,Rates_data!$G$2:$G$75,$E57,Rates_data!$Y$2:$Y$75,1) -> 266.92 | J57: =IF(F57=0,"",SUMIFS(Rates_data!$R$2:$R$75,Rates_data!$B$2:$B$75,$A57,Rates_data!$D$2:$D$75,$B57,Rates_data!$E$2:$E$75,$C57,Rates_data!$G$2:$G$75,$E57,Rates_data!$Y$2:$Y$75,1)/F57) -> 0 | K57: {=IF(COUNTIFS(Rates_data!$B$2:$B$75,$A57,Rates_data!$D$2:$D$75,$B57,Rates_data!$E$2:$E$75,$C57,Rates_data!$G$2:$G$75,$E57,Rates_data!$Y$2:$Y$75,1,Rates_data!$S$2:$S$75,"<>")=0,"",MEDIAN(IF((Rates_data!$B$2:$B$75=$A57)*(Rates_data!$D$2:$D$75=$B57)*(Rates_data!$G$2:$G$75=$E57)*(Rates_data!$E$2:$E$75=$C57)*(Rates_data!$Y$2:$Y$75=1)*(Rates_data!$S$2:$S$75<>""),Rates_data!$S$2:$S$75)))} | L57: =IF(COUNTIFS(Rates_data!$B$2:$B$75,$A57,Rates_data!$D$2:$D$75,$B57,Rates_data!$E$2:$E$75,$C57,Rates_data!$G$2:$G$75,$E57,Rates_data!$Y$2:$Y$75,1,Rates_data!$T$2:$T$75,"<>")=0,"",_xlfn.MINIFS(Rates_data!$T$2:$T$75,Rates_data!$B$2:$B$75,$A57,Rates_data!$D$2:$D$75,$B57,Rates_data!$E$2:$E$75,$C57,Rates_data!$G$2:$G$75,$E57,Rates_data!$Y$2:$Y$75,1)) | M57: =IF(COUNTIFS(Rates_data!$B$2:$B$75,$A57,Rates_data!$D$2:$D$75,$B57,Rates_data!$E$2:$E$75,$C57,Rates_data!$G$2:$G$75,$E57,Rates_data!$Y$2:$Y$75,1,Rates_data!$U$2:$U$75,"<>")=0,"",_xlfn.MAXIFS(Rates_data!$U$2:$U$75,Rates_data!$B$2:$B$75,$A57,Rates_data!$D$2:$D$75,$B57,Rates_data!$E$2:$E$75,$C57,Rates_data!$G$2:$G$75,$E57,Rates_data!$Y$2:$Y$75,1)) | O57: =IF(K57<>"",K57,H57) -> 261.075 | P57: =IF(K57<>"","median allowed","median negotiated") -> median negotiated
A58: Beth Israel Deaconess Medical Center | B58: 95922 | C58: Harvard Pilgrim Healthcare | D58: Harvard Pilgrim / Point32Health | E58: Commercial | F58: =COUNTIFS(Rates_data!$B$2:$B$75,$A58,Rates_data!$D$2:$D$75,$B58,Rates_data!$E$2:$E$75,$C58,Rates_data!$G$2:$G$75,$E58,Rates_data!$Y$2:$Y$75,1) -> 1 | G58: =_xlfn.MINIFS(Rates_data!$P$2:$P$75,Rates_data!$B$2:$B$75,$A58,Rates_data!$D$2:$D$75,$B58,Rates_data!$E$2:$E$75,$C58,Rates_data!$G$2:$G$75,$E58,Rates_data!$Y$2:$Y$75,1) -> 310.92 | H58: {=MEDIAN(IF((Rates_data!$B$2:$B$75=$A58)*(Rates_data!$D$2:$D$75=$B58)*(Rates_data!$G$2:$G$75=$E58)*(Rates_data!$E$2:$E$75=$C58)*(Rates_data!$Y$2:$Y$75=1)*(Rates_data!$P$2:$P$75<>""),Rates_data!$P$2:$P$75))} -> 310.92 | I58: =_xlfn.MAXIFS(Rates_data!$P$2:$P$75,Rates_data!$B$2:$B$75,$A58,Rates_data!$D$2:$D$75,$B58,Rates_data!$E$2:$E$75,$C58,Rates_data!$G$2:$G$75,$E58,Rates_data!$Y$2:$Y$75,1) -> 310.92 | J58: =IF(F58=0,"",SUMIFS(Rates_data!$R$2:$R$75,Rates_data!$B$2:$B$75,$A58,Rates_data!$D$2:$D$75,$B58,Rates_data!$E$2:$E$75,$C58,Rates_data!$G$2:$G$75,$E58,Rates_data!$Y$2:$Y$75,1)/F58) -> 0 | K58: {=IF(COUNTIFS(Rates_data!$B$2:$B$75,$A58,Rates_data!$D$2:$D$75,$B58,Rates_data!$E$2:$E$75,$C58,Rates_data!$G$2:$G$75,$E58,Rates_data!$Y$2:$Y$75,1,Rates_data!$S$2:$S$75,"<>")=0,"",MEDIAN(IF((Rates_data!$B$2:$B$75=$A58)*(Rates_data!$D$2:$D$75=$B58)*(Rates_data!$G$2:$G$75=$E58)*(Rates_data!$E$2:$E$75=$C58)*(Rates_data!$Y$2:$Y$75=1)*(Rates_data!$S$2:$S$75<>""),Rates_data!$S$2:$S$75)))} | L58: =IF(COUNTIFS(Rates_data!$B$2:$B$75,$A58,Rates_data!$D$2:$D$75,$B58,Rates_data!$E$2:$E$75,$C58,Rates_data!$G$2:$G$75,$E58,Rates_data!$Y$2:$Y$75,1,Rates_data!$T$2:$T$75,"<>")=0,"",_xlfn.MINIFS(Rates_data!$T$2:$T$75,Rates_data!$B$2:$B$75,$A58,Rates_data!$D$2:$D$75,$B58,Rates_data!$E$2:$E$75,$C58,Rates_data!$G$2:$G$75,$E58,Rates_data!$Y$2:$Y$75,1)) | M58: =IF(COUNTIFS(Rates_data!$B$2:$B$75,$A58,Rates_data!$D$2:$D$75,$B58,Rates_data!$E$2:$E$75,$C58,Rates_data!$G$2:$G$75,$E58,Rates_data!$Y$2:$Y$75,1,Rates_data!$U$2:$U$75,"<>")=0,"",_xlfn.MAXIFS(Rates_data!$U$2:$U$75,Rates_data!$B$2:$B$75,$A58,Rates_data!$D$2:$D$75,$B58,Rates_data!$E$2:$E$75,$C58,Rates_data!$G$2:$G$75,$E58,Rates_data!$Y$2:$Y$75,1)) | O58: =IF(K58<>"",K58,H58) -> 310.92 | P58: =IF(K58<>"","median allowed","median negotiated") -> median negotiated
A59: Beth Israel Deaconess Medical Center | B59: 95923 | C59: BCBS | D59: Blue Cross Blue Shield of MA | E59: Commercial | F59: =COUNTIFS(Rates_data!$B$2:$B$75,$A59,Rates_data!$D$2:$D$75,$B59,Rates_data!$E$2:$E$75,$C59,Rates_data!$G$2:$G$75,$E59,Rates_data!$Y$2:$Y$75,1) -> 2 | G59: =_xlfn.MINIFS(Rates_data!$P$2:$P$75,Rates_data!$B$2:$B$75,$A59,Rates_data!$D$2:$D$75,$B59,Rates_data!$E$2:$E$75,$C59,Rates_data!$G$2:$G$75,$E59,Rates_data!$Y$2:$Y$75,1) -> 255.23 | H59: {=MEDIAN(IF((Rates_data!$B$2:$B$75=$A59)*(Rates_data!$D$2:$D$75=$B59)*(Rates_data!$G$2:$G$75=$E59)*(Rates_data!$E$2:$E$75=$C59)*(Rates_data!$Y$2:$Y$75=1)*(Rates_data!$P$2:$P$75<>""),Rates_data!$P$2:$P$75))} -> 261.075 | I59: =_xlfn.MAXIFS(Rates_data!$P$2:$P$75,Rates_data!$B$2:$B$75,$A59,Rates_data!$D$2:$D$75,$B59,Rates_data!$E$2:$E$75,$C59,Rates_data!$G$2:$G$75,$E59,Rates_data!$Y$2:$Y$75,1) -> 266.92 | J59: =IF(F59=0,"",SUMIFS(Rates_data!$R$2:$R$75,Rates_data!$B$2:$B$75,$A59,Rates_data!$D$2:$D$75,$B59,Rates_data!$E$2:$E$75,$C59,Rates_data!$G$2:$G$75,$E59,Rates_data!$Y$2:$Y$75,1)/F59) -> 0 | K59: {=IF(COUNTIFS(Rates_data!$B$2:$B$75,$A59,Rates_data!$D$2:$D$75,$B59,Rates_data!$E$2:$E$75,$C59,Rates_data!$G$2:$G$75,$E59,Rates_data!$Y$2:$Y$75,1,Rates_data!$S$2:$S$75,"<>")=0,"",MEDIAN(IF((Rates_data!$B$2:$B$75=$A59)*(Rates_data!$D$2:$D$75=$B59)*(Rates_data!$G$2:$G$75=$E59)*(Rates_data!$E$2:$E$75=$C59)*(Rates_data!$Y$2:$Y$75=1)*(Rates_data!$S$2:$S$75<>""),Rates_data!$S$2:$S$75)))} | L59: =IF(COUNTIFS(Rates_data!$B$2:$B$75,$A59,Rates_data!$D$2:$D$75,$B59,Rates_data!$E$2:$E$75,$C59,Rates_data!$G$2:$G$75,$E59,Rates_data!$Y$2:$Y$75,1,Rates_data!$T$2:$T$75,"<>")=0,"",_xlfn.MINIFS(Rates_data!$T$2:$T$75,Rates_data!$B$2:$B$75,$A59,Rates_data!$D$2:$D$75,$B59,Rates_data!$E$2:$E$75,$C59,Rates_data!$G$2:$G$75,$E59,Rates_data!$Y$2:$Y$75,1)) | M59: =IF(COUNTIFS(Rates_data!$B$2:$B$75,$A59,Rates_data!$D$2:$D$75,$B59,Rates_data!$E$2:$E$75,$C59,Rates_data!$G$2:$G$75,$E59,Rates_data!$Y$2:$Y$75,1,Rates_data!$U$2:$U$75,"<>")=0,"",_xlfn.MAXIFS(Rates_data!$U$2:$U$75,Rates_data!$B$2:$B$75,$A59,Rates_data!$D$2:$D$75,$B59,Rates_data!$E$2:$E$75,$C59,Rates_data!$G$2:$G$75,$E59,Rates_data!$Y$2:$Y$75,1)) | O59: =IF(K59<>"",K59,H59) -> 261.075 | P59: =IF(K59<>"","median allowed","median negotiated") -> median negotiated
A60: Beth Israel Deaconess Medical Center | B60: 95923 | C60: Harvard Pilgrim Healthcare | D60: Harvard Pilgrim / Point32Health | E60: Commercial | F60: =COUNTIFS(Rates_data!$B$2:$B$75,$A60,Rates_data!$D$2:$D$75,$B60,Rates_data!$E$2:$E$75,$C60,Rates_data!$G$2:$G$75,$E60,Rates_data!$Y$2:$Y$75,1) -> 1 | G60: =_xlfn.MINIFS(Rates_data!$P$2:$P$75,Rates_data!$B$2:$B$75,$A60,Rates_data!$D$2:$D$75,$B60,Rates_data!$E$2:$E$75,$C60,Rates_data!$G$2:$G$75,$E60,Rates_data!$Y$2:$Y$75,1) -> 310.92 | H60: {=MEDIAN(IF((Rates_data!$B$2:$B$75=$A60)*(Rates_data!$D$2:$D$75=$B60)*(Rates_data!$G$2:$G$75=$E60)*(Rates_data!$E$2:$E$75=$C60)*(Rates_data!$Y$2:$Y$75=1)*(Rates_data!$P$2:$P$75<>""),Rates_data!$P$2:$P$75))} -> 310.92 | I60: =_xlfn.MAXIFS(Rates_data!$P$2:$P$75,Rates_data!$B$2:$B$75,$A60,Rates_data!$D$2:$D$75,$B60,Rates_data!$E$2:$E$75,$C60,Rates_data!$G$2:$G$75,$E60,Rates_data!$Y$2:$Y$75,1) -> 310.92 | J60: =IF(F60=0,"",SUMIFS(Rates_data!$R$2:$R$75,Rates_data!$B$2:$B$75,$A60,Rates_data!$D$2:$D$75,$B60,Rates_data!$E$2:$E$75,$C60,Rates_data!$G$2:$G$75,$E60,Rates_data!$Y$2:$Y$75,1)/F60) -> 0 | K60: {=IF(COUNTIFS(Rates_data!$B$2:$B$75,$A60,Rates_data!$D$2:$D$75,$B60,Rates_data!$E$2:$E$75,$C60,Rates_data!$G$2:$G$75,$E60,Rates_data!$Y$2:$Y$75,1,Rates_data!$S$2:$S$75,"<>")=0,"",MEDIAN(IF((Rates_data!$B$2:$B$75=$A60)*(Rates_data!$D$2:$D$75=$B60)*(Rates_data!$G$2:$G$75=$E60)*(Rates_data!$E$2:$E$75=$C60)*(Rates_data!$Y$2:$Y$75=1)*(Rates_data!$S$2:$S$75<>""),Rates_data!$S$2:$S$75)))} | L60: =IF(COUNTIFS(Rates_data!$B$2:$B$75,$A60,Rates_data!$D$2:$D$75,$B60,Rates_data!$E$2:$E$75,$C60,Rates_data!$G$2:$G$75,$E60,Rates_data!$Y$2:$Y$75,1,Rates_data!$T$2:$T$75,"<>")=0,"",_xlfn.MINIFS(Rates_data!$T$2:$T$75,Rates_data!$B$2:$B$75,$A60,Rates_data!$D$2:$D$75,$B60,Rates_data!$E$2:$E$75,$C60,Rates_data!$G$2:$G$75,$E60,Rates_data!$Y$2:$Y$75,1)) | M60: =IF(COUNTIFS(Rates_data!$B$2:$B$75,$A60,Rates_data!$D$2:$D$75,$B60,Rates_data!$E$2:$E$75,$C60,Rates_data!$G$2:$G$75,$E60,Rates_data!$Y$2:$Y$75,1,Rates_data!$U$2:$U$75,"<>")=0,"",_xlfn.MAXIFS(Rates_data!$U$2:$U$75,Rates_data!$B$2:$B$75,$A60,Rates_data!$D$2:$D$75,$B60,Rates_data!$E$2:$E$75,$C60,Rates_data!$G$2:$G$75,$E60,Rates_data!$Y$2:$Y$75,1)) | O60: =IF(K60<>"",K60,H60) -> 310.92 | P60: =IF(K60<>"","median allowed","median negotiated") -> median negotiated
A61: Beth Israel Deaconess Medical Center | B61: 95924 | C61: BCBS | D61: Blue Cross Blue Shield of MA | E61: Commercial | F61: =COUNTIFS(Rates_data!$B$2:$B$75,$A61,Rates_data!$D$2:$D$75,$B61,Rates_data!$E$2:$E$75,$C61,Rates_data!$G$2:$G$75,$E61,Rates_data!$Y$2:$Y$75,1) -> 2 | G61: =_xlfn.MINIFS(Rates_data!$P$2:$P$75,Rates_data!$B$2:$B$75,$A61,Rates_data!$D$2:$D$75,$B61,Rates_data!$E$2:$E$75,$C61,Rates_data!$G$2:$G$75,$E61,Rates_data!$Y$2:$Y$75,1) -> 325.87 | H61: {=MEDIAN(IF((Rates_data!$B$2:$B$75=$A61)*(Rates_data!$D$2:$D$75=$B61)*(Rates_data!$G$2:$G$75=$E61)*(Rates_data!$E$2:$E$75=$C61)*(Rates_data!$Y$2:$Y$75=1)*(Rates_data!$P$2:$P$75<>""),Rates_data!$P$2:$P$75))} -> 333.33 | I61: =_xlfn.MAXIFS(Rates_data!$P$2:$P$75,Rates_data!$B$2:$B$75,$A61,Rates_data!$D$2:$D$75,$B61,Rates_data!$E$2:$E$75,$C61,Rates_data!$G$2:$G$75,$E61,Rates_data!$Y$2:$Y$75,1) -> 340.79 | J61: =IF(F61=0,"",SUMIFS(Rates_data!$R$2:$R$75,Rates_data!$B$2:$B$75,$A61,Rates_data!$D$2:$D$75,$B61,Rates_data!$E$2:$E$75,$C61,Rates_data!$G$2:$G$75,$E61,Rates_data!$Y$2:$Y$75,1)/F61) -> 0 | K61: {=IF(COUNTIFS(Rates_data!$B$2:$B$75,$A61,Rates_data!$D$2:$D$75,$B61,Rates_data!$E$2:$E$75,$C61,Rates_data!$G$2:$G$75,$E61,Rates_data!$Y$2:$Y$75,1,Rates_data!$S$2:$S$75,"<>")=0,"",MEDIAN(IF((Rates_data!$B$2:$B$75=$A61)*(Rates_data!$D$2:$D$75=$B61)*(Rates_data!$G$2:$G$75=$E61)*(Rates_data!$E$2:$E$75=$C61)*(Rates_data!$Y$2:$Y$75=1)*(Rates_data!$S$2:$S$75<>""),Rates_data!$S$2:$S$75)))} | L61: =IF(COUNTIFS(Rates_data!$B$2:$B$75,$A61,Rates_data!$D$2:$D$75,$B61,Rates_data!$E$2:$E$75,$C61,Rates_data!$G$2:$G$75,$E61,Rates_data!$Y$2:$Y$75,1,Rates_data!$T$2:$T$75,"<>")=0,"",_xlfn.MINIFS(Rates_data!$T$2:$T$75,Rates_data!$B$2:$B$75,$A61,Rates_data!$D$2:$D$75,$B61,Rates_data!$E$2:$E$75,$C61,Rates_data!$G$2:$G$75,$E61,Rates_data!$Y$2:$Y$75,1)) | M61: =IF(COUNTIFS(Rates_data!$B$2:$B$75,$A61,Rates_data!$D$2:$D$75,$B61,Rates_data!$E$2:$E$75,$C61,Rates_data!$G$2:$G$75,$E61,Rates_data!$Y$2:$Y$75,1,Rates_data!$U$2:$U$75,"<>")=0,"",_xlfn.MAXIFS(Rates_data!$U$2:$U$75,Rates_data!$B$2:$B$75,$A61,Rates_data!$D$2:$D$75,$B61,Rates_data!$E$2:$E$75,$C61,Rates_data!$G$2:$G$75,$E61,Rates_data!$Y$2:$Y$75,1)) | O61: =IF(K61<>"",K61,H61) -> 333.33 | P61: =IF(K61<>"","median allowed","median negotiated") -> median negotiated
A62: Beth Israel Deaconess Medical Center | B62: 95924 | C62: Harvard Pilgrim Healthcare | D62: Harvard Pilgrim / Point32Health | E62: Commercial | F62: =COUNTIFS(Rates_data!$B$2:$B$75,$A62,Rates_data!$D$2:$D$75,$B62,Rates_data!$E$2:$E$75,$C62,Rates_data!$G$2:$G$75,$E62,Rates_data!$Y$2:$Y$75,1) -> 1 | G62: =_xlfn.MINIFS(Rates_data!$P$2:$P$75,Rates_data!$B$2:$B$75,$A62,Rates_data!$D$2:$D$75,$B62,Rates_data!$E$2:$E$75,$C62,Rates_data!$G$2:$G$75,$E62,Rates_data!$Y$2:$Y$75,1) -> 396.97 | H62: {=MEDIAN(IF((Rates_data!$B$2:$B$75=$A62)*(Rates_data!$D$2:$D$75=$B62)*(Rates_data!$G$2:$G$75=$E62)*(Rates_data!$E$2:$E$75=$C62)*(Rates_data!$Y$2:$Y$75=1)*(Rates_data!$P$2:$P$75<>""),Rates_data!$P$2:$P$75))} -> 396.97 | I62: =_xlfn.MAXIFS(Rates_data!$P$2:$P$75,Rates_data!$B$2:$B$75,$A62,Rates_data!$D$2:$D$75,$B62,Rates_data!$E$2:$E$75,$C62,Rates_data!$G$2:$G$75,$E62,Rates_data!$Y$2:$Y$75,1) -> 396.97 | J62: =IF(F62=0,"",SUMIFS(Rates_data!$R$2:$R$75,Rates_data!$B$2:$B$75,$A62,Rates_data!$D$2:$D$75,$B62,Rates_data!$E$2:$E$75,$C62,Rates_data!$G$2:$G$75,$E62,Rates_data!$Y$2:$Y$75,1)/F62) -> 0 | K62: {=IF(COUNTIFS(Rates_data!$B$2:$B$75,$A62,Rates_data!$D$2:$D$75,$B62,Rates_data!$E$2:$E$75,$C62,Rates_data!$G$2:$G$75,$E62,Rates_data!$Y$2:$Y$75,1,Rates_data!$S$2:$S$75,"<>")=0,"",MEDIAN(IF((Rates_data!$B$2:$B$75=$A62)*(Rates_data!$D$2:$D$75=$B62)*(Rates_data!$G$2:$G$75=$E62)*(Rates_data!$E$2:$E$75=$C62)*(Rates_data!$Y$2:$Y$75=1)*(Rates_data!$S$2:$S$75<>""),Rates_data!$S$2:$S$75)))} | L62: =IF(COUNTIFS(Rates_data!$B$2:$B$75,$A62,Rates_data!$D$2:$D$75,$B62,Rates_data!$E$2:$E$75,$C62,Rates_data!$G$2:$G$75,$E62,Rates_data!$Y$2:$Y$75,1,Rates_data!$T$2:$T$75,"<>")=0,"",_xlfn.MINIFS(Rates_data!$T$2:$T$75,Rates_data!$B$2:$B$75,$A62,Rates_data!$D$2:$D$75,$B62,Rates_data!$E$2:$E$75,$C62,Rates_data!$G$2:$G$75,$E62,Rates_data!$Y$2:$Y$75,1)) | M62: =IF(COUNTIFS(Rates_data!$B$2:$B$75,$A62,Rates_data!$D$2:$D$75,$B62,Rates_data!$E$2:$E$75,$C62,Rates_data!$G$2:$G$75,$E62,Rates_data!$Y$2:$Y$75,1,Rates_data!$U$2:$U$75,"<>")=0,"",_xlfn.MAXIFS(Rates_data!$U$2:$U$75,Rates_data!$B$2:$B$75,$A62,Rates_data!$D$2:$D$75,$B62,Rates_data!$E$2:$E$75,$C62,Rates_data!$G$2:$G$75,$E62,Rates_data!$Y$2:$Y$75,1)) | O62: =IF(K62<>"",K62,H62) -> 396.97 | P62: =IF(K62<>"","median allowed","median negotiated") -> median negotiated

Sheet Battery
A1: Full autonomic battery: 95924 + 95923 facility rate, same payer/plan, plus approximate physician fee
A2: Physician fee = Medicare PC 142.57 (Reference). It is an APPROXIMATION: the physician group's negotiated rate is not published in hospital MRFs.
A4: Hospital | B4: Segment | C4: Payer | D4: Plan | E4: Pricing basis | F4: 95924 negotiated | G4: 95923 negotiated | H4: Facility battery (negotiated) | I4: 95924 median allowed | J4: 95923 median allowed | K4: Facility battery (allowed) | L4: Headline facility battery | M4: Headline basis | N4: Approx. physician fee (Medicare PC, approximation) | O4: Approx. total battery cost | P4: Note
A5: Massachusetts General Hospital | B5: Medicare FFS | C5: Medicare | E5: Hospital Medicare FFS row, OPPS packaging applied (95923 = 0) | F5: =Rates_data!P27 -> 369.77 | G5: =0 -> 0 | H5: =F5+G5 -> 369.77 | I5: =IF(Rates_data!S27="","",Rates_data!S27) -> 369.81 | J5: =0 -> 0 | K5: =IF(AND(I5<>"",J5<>""),I5+J5,"") -> 369.81 | L5: =IF(K5<>"",K5,H5) -> 369.81 | M5: =IF(K5<>"","median allowed","APC price") -> median allowed | N5: =Reference!$C$10 -> 142.57 | O5: =L5+N5 -> 512.38 | P5: 95923 is SI Q1: packaged with 95924 (SI S) on the same claim, no separate payment. Faulkner's own 95923 row says it is only paid if highest rate.
A6: Massachusetts General Hospital | B6: Medicare FFS | C6: Medicare | E6: Hospital 95924 row + OPPS national 95923 (not listed in file) | F6: =Rates_data!P27 -> 369.77 | G6: =Reference!$E$20 -> 135.93 | H6: =F6+G6 -> 505.7 | I6: =IF(Rates_data!S27="","",Rates_data!S27) -> 369.81 | K6: =IF(AND(I6<>"",J6<>""),I6+J6,"") | L6: =IF(K6<>"",K6,H6) -> 505.7 | M6: =IF(K6<>"","median allowed","APC price") -> APC price | N6: =Reference!$C$10 -> 142.57 | O6: =L6+N6 -> 648.27 | P6: File lists no Medicare row for 95923; national unadjusted Addendum B rate substituted and flagged.
A7: Massachusetts General Hospital | B7: Medicare FFS | C7: Medicare (reference) | E7: OPPS national (Addendum B), packaging applied (95923 = 0) | F7: =Reference!$E$21 -> 220.6 | G7: =0 -> 0 | H7: =F7+G7 -> 220.6 | L7: =IF(K7<>"",K7,H7) -> 220.6 | M7: =IF(K7<>"","median allowed","APC price") -> APC price | N7: =Reference!$C$10 -> 142.57 | O7: =L7+N7 -> 363.17 | P7: National, unadjusted for MA wage index.
A8: Massachusetts General Hospital | B8: Medicare FFS | C8: Medicare (reference) | E8: OPPS national (Addendum B), as listed | F8: =Reference!$E$21 -> 220.6 | G8: =Reference!$E$20 -> 135.93 | H8: =F8+G8 -> 356.53 | L8: =IF(K8<>"",K8,H8) -> 356.53 | M8: =IF(K8<>"","median allowed","APC price") -> APC price | N8: =Reference!$C$10 -> 142.57 | O8: =L8+N8 -> 499.1 | P8: National, unadjusted for MA wage index; no packaging.
A9: Massachusetts General Hospital | B9: Commercial | C9: AETNA [1001] | D9: HB AMC AETNA HMO | E9: Hospital file, same payer/plan | F9: =Rates_data!P12 -> 801.3 | G9: =Rates_data!P3 -> 686.13 | H9: =F9+G9 -> 1487.43 | I9: =IF(Rates_data!S12="","",Rates_data!S12) -> 1444.72 | J9: =IF(Rates_data!S3="","",Rates_data!S3) -> 1212.81 | K9: =IF(AND(I9<>"",J9<>""),I9+J9,"") -> 2657.53 | L9: =IF(K9<>"",K9,H9) -> 2657.53 | M9: =IF(K9<>"","median allowed","negotiated") -> median allowed | N9: =Reference!$C$10 -> 142.57 | O9: =L9+N9 -> 2800.1
A10: Massachusetts General Hospital | B10: Commercial | C10: CIGNA ALTERNATE [1018] | D10: HB AMC CIGNA NEW BUSINESS DISCOUNT | E10: Hospital file, same payer/plan | F10: =Rates_data!P13 -> 611.88 | G10: =Rates_data!P4 -> 523.94 | H10: =F10+G10 -> 1135.82 | I10: =IF(Rates_data!S13="","",Rates_data!S13) -> 587.66 | J10: =IF(Rates_data!S4="","",Rates_data!S4) -> 503.18 | K10: =IF(AND(I10<>"",J10<>""),I10+J10,"") -> 1090.84 | L10: =IF(K10<>"",K10,H10) -> 1090.84 | M10: =IF(K10<>"","median allowed","negotiated") -> median allowed | N10: =Reference!$C$10 -> 142.57 | O10: =L10+N10 -> 1233.41
A11: Massachusetts General Hospital | B11: Commercial | C11: CIGNA [1006] | D11: HB AMC CIGNA HMO / PPO | E11: Hospital file, same payer/plan | F11: =Rates_data!P14 -> 912.66 | G11: =Rates_data!P5 -> 781.49 | H11: =F11+G11 -> 1694.15 | I11: =IF(Rates_data!S14="","",Rates_data!S14) -> 875.93 | J11: =IF(Rates_data!S5="","",Rates_data!S5) -> 750.01 | K11: =IF(AND(I11<>"",J11<>""),I11+J11,"") -> 1625.94 | L11: =IF(K11<>"",K11,H11) -> 1625.94 | M11: =IF(K11<>"","median allowed","negotiated") -> median allowed | N11: =Reference!$C$10 -> 142.57 | O11: =L11+N11 -> 1768.51
A12: Massachusetts General Hospital | B12: Commercial | C12: INTERNATIONAL COMMERCIAL [140001] | D12: HB AMC / MEE / PCC / ONE TEAM HEALTH INTERNATIONAL | E12: Hospital file, same payer/plan | F12: =Rates_data!P15 -> 746.2 | G12: =Rates_data!P6 -> 638.95 | H12: =F12+G12 -> 1385.15 | I12: =IF(Rates_data!S15="","",Rates_data!S15) -> 723.45 | J12: =IF(Rates_data!S6="","",Rates_data!S6) -> 619.45 | K12: =IF(AND(I12<>"",J12<>""),I12+J12,"") -> 1342.9 | L12: =IF(K12<>"",K12,H12) -> 1342.9 | M12: =IF(K12<>"","median allowed","negotiated") -> median allowed | N12: =Reference!$C$10 -> 142.57 | O12: =L12+N12 -> 1485.47
A13: Massachusetts General Hospital | B13: Commercial | C13: MGB HEALTH PLAN [150001] | D13: HB AMC MGBHP COMMERCIAL HMO | E13: Hospital file, same payer/plan | F13: =Rates_data!P16 -> 419.02 | G13: =Rates_data!P7 -> 358.8 | H13: =F13+G13 -> 777.82 | I13: =IF(Rates_data!S16="","",Rates_data!S16) -> 415.15 | J13: =IF(Rates_data!S7="","",Rates_data!S7) -> 355.47 | K13: =IF(AND(I13<>"",J13<>""),I13+J13,"") -> 770.62 | L13: =IF(K13<>"",K13,H13) -> 770.62 | M13: =IF(K13<>"","median allowed","negotiated") -> median allowed | N13: =Reference!$C$10 -> 142.57 | O13: =L13+N13 -> 913.19
A14: Massachusetts General Hospital | B14: Commercial | C14: MGB HEALTH PLAN [150001] | D14: HB AMC MGBHP COMMERCIAL PPO | E14: Hospital file, same payer/plan | F14: =Rates_data!P17 -> 439.68 | G14: =Rates_data!P8 -> 376.49 | H14: =F14+G14 -> 816.17 | I14: =IF(Rates_data!S17="","",Rates_data!S17) -> 435.18 | J14: =IF(Rates_data!S8="","",Rates_data!S8) -> 372.62 | K14: =IF(AND(I14<>"",J14<>""),I14+J14,"") -> 807.8 | L14: =IF(K14<>"",K14,H14) -> 807.8 | M14: =IF(K14<>"","median allowed","negotiated") -> median allowed | N14: =Reference!$C$10 -> 142.57 | O14: =L14+N14 -> 950.37
A15: Massachusetts General Hospital | B15: Commercial | C15: UNITED HEALTHCARE [1016] | D15: HB AMC CH UNITED NEW BUSINESS DISCOUNT | E15: Hospital file, same payer/plan | F15: =Rates_data!P18 -> 492.49 | G15: =Rates_data!P9 -> 421.71 | H15: =F15+G15 -> 914.2 | I15: =IF(Rates_data!S18="","",Rates_data!S18) -> 889.73 | J15: =IF(Rates_data!S9="","",Rates_data!S9) -> 761.83 | K15: =IF(AND(I15<>"",J15<>""),I15+J15,"") -> 1651.56 | L15: =IF(K15<>"",K15,H15) -> 1651.56 | M15: =IF(K15<>"","median allowed","negotiated") -> median allowed | N15: =Reference!$C$10 -> 142.57 | O15: =L15+N15 -> 1794.13
A16: Massachusetts General Hospital | B16: Commercial | C16: UNITED HEALTHCARE [1016] | D16: HB AMC UNITED PPO / POS | E16: Hospital file, same payer/plan | F16: =Rates_data!P19 -> 938.15 | G16: =Rates_data!P10 -> 803.31 | H16: =F16+G16 -> 1741.46 | I16: =IF(Rates_data!S19="","",Rates_data!S19) -> 889.73 | J16: =IF(Rates_data!S10="","",Rates_data!S10) -> 761.83 | K16: =IF(AND(I16<>"",J16<>""),I16+J16,"") -> 1651.56 | L16: =IF(K16<>"",K16,H16) -> 1651.56 | M16: =IF(K16<>"","median allowed","negotiated") -> median allowed | N16: =Reference!$C$10 -> 142.57 | O16: =L16+N16 -> 1794.13
A17: Massachusetts General Hospital | B17: Commercial | C17: WELLPOINT [1015] | D17: HB AMC WELLPOINT | E17: Hospital file, same payer/plan | F17: =Rates_data!P20 -> 846.99 | G17: =Rates_data!P11 -> 725.26 | H17: =F17+G17 -> 1572.25 | I17: =IF(Rates_data!S20="","",Rates_data!S20) -> 828.63 | J17: =IF(Rates_data!S11="","",Rates_data!S11) -> 709.51 | K17: =IF(AND(I17<>"",J17<>""),I17+J17,"") -> 1538.14 | L17: =IF(K17<>"",K17,H17) -> 1538.14 | M17: =IF(K17<>"","median allowed","negotiated") -> median allowed | N17: =Reference!$C$10 -> 142.57 | O17: =L17+N17 -> 1680.71
A18: Brigham and Women's Faulkner Hospital | B18: Medicare FFS | C18: Medicare | E18: Hospital Medicare FFS row, OPPS packaging applied (95923 = 0) | F18: =Rates_data!P53 -> 369.81 | G18: =0 -> 0 | H18: =F18+G18 -> 369.81 | I18: =IF(Rates_data!S53="","",Rates_data!S53) -> 369.81 | J18: =0 -> 0 | K18: =IF(AND(I18<>"",J18<>""),I18+J18,"") -> 369.81 | L18: =IF(K18<>"",K18,H18) -> 369.81 | M18: =IF(K18<>"","median allowed","APC price") -> median allowed | N18: =Reference!$C$10 -> 142.57 | O18: =L18+N18 -> 512.38 | P18: 95923 is SI Q1: packaged with 95924 (SI S) on the same claim, no separate payment. Faulkner's own 95923 row says it is only paid if highest rate.
A19: Brigham and Women's Faulkner Hospital | B19: Medicare FFS | C19: Medicare | E19: Hospital Medicare FFS rows, as listed (no packaging) | F19: =Rates_data!P53 -> 369.81 | G19: =Rates_data!P40 -> 153.08 | H19: =F19+G19 -> 522.89 | I19: =IF(Rates_data!S53="","",Rates_data!S53) -> 369.81 | J19: =IF(Rates_data!S40="","",Rates_data!S40) -> 306.16 | K19: =IF(AND(I19<>"",J19<>""),I19+J19,"") -> 675.97 | L19: =IF(K19<>"",K19,H19) -> 675.97 | M19: =IF(K19<>"","median allowed","APC price") -> median allowed | N19: =Reference!$C$10 -> 142.57 | O19: =L19+N19 -> 818.54 | P19: Sum of listed APC prices; overstates Medicare payment when billed together.
A20: Brigham and Women's Faulkner Hospital | B20: Medicare FFS | C20: Medicare (reference) | E20: OPPS national (Addendum B), packaging applied (95923 = 0) | F20: =Reference!$E$21 -> 220.6 | G20: =0 -> 0 | H20: =F20+G20 -> 220.6 | L20: =IF(K20<>"",K20,H20) -> 220.6 | M20: =IF(K20<>"","median allowed","APC price") -> APC price | N20: =Reference!$C$10 -> 142.57 | O20: =L20+N20 -> 363.17 | P20: National, unadjusted for MA wage index.
A21: Brigham and Women's Faulkner Hospital | B21: Medicare FFS | C21: Medicare (reference) | E21: OPPS national (Addendum B), as listed | F21: =Reference!$E$21 -> 220.6 | G21: =Reference!$E$20 -> 135.93 | H21: =F21+G21 -> 356.53 | L21: =IF(K21<>"",K21,H21) -> 356.53 | M21: =IF(K21<>"","median allowed","APC price") -> APC price | N21: =Reference!$C$10 -> 142.57 | O21: =L21+N21 -> 499.1 | P21: National, unadjusted for MA wage index; no packaging.
A22: Brigham and Women's Faulkner Hospital | B22: Commercial | C22: CIGNA [1006] | D22: HB CH CIGNA HMO / PPO | E22: Hospital file, same payer/plan | F22: =Rates_data!P41 -> 479.74 | G22: =Rates_data!P33 -> 412.73 | H22: =F22+G22 -> 892.47 | I22: =IF(Rates_data!S41="","",Rates_data!S41) -> 461.18 | J22: =IF(Rates_data!S33="","",Rates_data!S33) -> 396.72 | K22: =IF(AND(I22<>"",J22<>""),I22+J22,"") -> 857.9 | L22: =IF(K22<>"",K22,H22) -> 857.9 | M22: =IF(K22<>"","median allowed","negotiated") -> median allowed | N22: =Reference!$C$10 -> 142.57 | O22: =L22+N22 -> 1000.47
A23: Brigham and Women's Faulkner Hospital | B23: Commercial | C23: HEALTH NEW ENGLAND [1034] | D23: HB CH CLARITEV (PRIMARY PPO) | E23: Hospital file, same payer/plan | F23: =Rates_data!P42 -> 590.57 | G23: =Rates_data!P34 -> 508.08 | H23: =F23+G23 -> 1098.65 | I23: =IF(Rates_data!S42="","",Rates_data!S42) -> 574.51 | J23: =IF(Rates_data!S34="","",Rates_data!S34) -> 494.21 | K23: =IF(AND(I23<>"",J23<>""),I23+J23,"") -> 1068.72 | L23: =IF(K23<>"",K23,H23) -> 1068.72 | M23: =IF(K23<>"","median allowed","negotiated") -> median allowed | N23: =Reference!$C$10 -> 142.57 | O23: =L23+N23 -> 1211.29
A24: Brigham and Women's Faulkner Hospital | B24: Commercial | C24: UNITED HEALTHCARE [1016] | D24: HB AMC CH UNITED NEW BUSINESS DISCOUNT | E24: Hospital file, same payer/plan | F24: =Rates_data!P43 -> 359.6 | G24: =Rates_data!P35 -> 309.37 | H24: =F24+G24 -> 668.97 | I24: =IF(Rates_data!S43="","",Rates_data!S43) -> 358.56 | J24: =IF(Rates_data!S35="","",Rates_data!S35) -> 308.44 | K24: =IF(AND(I24<>"",J24<>""),I24+J24,"") -> 667 | L24: =IF(K24<>"",K24,H24) -> 667 | M24: =IF(K24<>"","median allowed","negotiated") -> median allowed | N24: =Reference!$C$10 -> 142.57 | O24: =L24+N24 -> 809.57
A25: Brigham and Women's Faulkner Hospital | B25: Commercial | C25: UNITED HEALTHCARE [1016] | D25: HB CH UNITED HMO / PPO / INDEMNITY | E25: Hospital file, same payer/plan | F25: =Rates_data!P44 -> 634.66 | G25: =Rates_data!P36 -> 546.01 | H25: =F25+G25 -> 1180.67 | I25: =IF(Rates_data!S44="","",Rates_data!S44) -> 605.05 | J25: =IF(Rates_data!S36="","",Rates_data!S36) -> 520.48 | K25: =IF(AND(I25<>"",J25<>""),I25+J25,"") -> 1125.53 | L25: =IF(K25<>"",K25,H25) -> 1125.53 | M25: =IF(K25<>"","median allowed","negotiated") -> median allowed | N25: =Reference!$C$10 -> 142.57 | O25: =L25+N25 -> 1268.1
A26: Brigham and Women's Faulkner Hospital | B26: Commercial | C26: WELLPOINT [1015] | D26: HB CH WELLPOINT | E26: Hospital file, same payer/plan | F26: =Rates_data!P45 -> 630.29 | G26: =Rates_data!P37 -> 542.25 | H26: =F26+G26 -> 1172.54 | I26: =IF(Rates_data!S45="","",Rates_data!S45) -> 787 | J26: =IF(Rates_data!S37="","",Rates_data!S37) -> 677 | K26: =IF(AND(I26<>"",J26<>""),I26+J26,"") -> 1464 | L26: =IF(K26<>"",K26,H26) -> 1464 | M26: =IF(K26<>"","median allowed","negotiated") -> median allowed | N26: =Reference!$C$10 -> 142.57 | O26: =L26+N26 -> 1606.57
A27: Brigham and Women's Faulkner Hospital | B27: Medicare Advantage | C27: BLUE CROSS BLUE SHIELD [110001] | D27: HB BWF MEDICARE | E27: Hospital file, same payer/plan | F27: =Rates_data!P46 -> 369.81 | G27: =Rates_data!P38 -> 153.08 | H27: =F27+G27 -> 522.89 | I27: =IF(Rates_data!S46="","",Rates_data!S46) -> 363.89 | J27: =IF(Rates_data!S38="","",Rates_data!S38) -> 171.01 | K27: =IF(AND(I27<>"",J27<>""),I27+J27,"") -> 534.9 | L27: =IF(K27<>"",K27,H27) -> 534.9 | M27: =IF(K27<>"","median allowed","negotiated") -> median allowed | N27: =Reference!$C$10 -> 142.57 | O27: =L27+N27 -> 677.47 | P27: APC-priced MA plan; 95923 likely packaged in practice (Q1).
A28: Brigham and Women's Faulkner Hospital | B28: Medicare Advantage | C28: CENTERS OF EXCELLENCE [1026] | D28: HB BWF MEDICARE | E28: Hospital file, same payer/plan | F28: =Rates_data!P47 -> 369.81 | G28: =Rates_data!P39 -> 153.08 | H28: =F28+G28 -> 522.89 | I28: =IF(Rates_data!S47="","",Rates_data!S47) -> 366.63 | J28: =IF(Rates_data!S39="","",Rates_data!S39) -> 168.27 | K28: =IF(AND(I28<>"",J28<>""),I28+J28,"") -> 534.9 | L28: =IF(K28<>"",K28,H28) -> 534.9 | M28: =IF(K28<>"","median allowed","negotiated") -> median allowed | N28: =Reference!$C$10 -> 142.57 | O28: =L28+N28 -> 677.47 | P28: APC-priced MA plan; 95923 likely packaged in practice (Q1).
A29: Beth Israel Deaconess Medical Center | B29: Medicare FFS | C29: Medicare (reference) | E29: OPPS national (Addendum B), packaging applied (95923 = 0) | F29: =Reference!$E$21 -> 220.6 | G29: =0 -> 0 | H29: =F29+G29 -> 220.6 | L29: =IF(K29<>"",K29,H29) -> 220.6 | M29: =IF(K29<>"","median allowed","APC price") -> APC price | N29: =Reference!$C$10 -> 142.57 | O29: =L29+N29 -> 363.17 | P29: National, unadjusted for MA wage index.
A30: Beth Israel Deaconess Medical Center | B30: Medicare FFS | C30: Medicare (reference) | E30: OPPS national (Addendum B), as listed | F30: =Reference!$E$21 -> 220.6 | G30: =Reference!$E$20 -> 135.93 | H30: =F30+G30 -> 356.53 | L30: =IF(K30<>"",K30,H30) -> 356.53 | M30: =IF(K30<>"","median allowed","APC price") -> APC price | N30: =Reference!$C$10 -> 142.57 | O30: =L30+N30 -> 499.1 | P30: National, unadjusted for MA wage index; no packaging.
A31: Beth Israel Deaconess Medical Center | B31: Commercial | C31: BCBS | D31: HMO | E31: Hospital file, same payer/plan | F31: =Rates_data!P73 -> 325.87 | G31: =Rates_data!P69 -> 255.23 | H31: =F31+G31 -> 581.1 | I31: =IF(Rates_data!S73="","",Rates_data!S73) | J31: =IF(Rates_data!S69="","",Rates_data!S69) | K31: =IF(AND(I31<>"",J31<>""),I31+J31,"") | L31: =IF(K31<>"",K31,H31) -> 581.1 | M31: =IF(K31<>"","median allowed","negotiated") -> negotiated | N31: =Reference!$C$10 -> 142.57 | O31: =L31+N31 -> 723.67
A32: Beth Israel Deaconess Medical Center | B32: Commercial | C32: BCBS | D32: PPO | E32: Hospital file, same payer/plan | F32: =Rates_data!P74 -> 340.79 | G32: =Rates_data!P70 -> 266.92 | H32: =F32+G32 -> 607.71 | I32: =IF(Rates_data!S74="","",Rates_data!S74) | J32: =IF(Rates_data!S70="","",Rates_data!S70) | K32: =IF(AND(I32<>"",J32<>""),I32+J32,"") | L32: =IF(K32<>"",K32,H32) -> 607.71 | M32: =IF(K32<>"","median allowed","negotiated") -> negotiated | N32: =Reference!$C$10 -> 142.57 | O32: =L32+N32 -> 750.28
A33: Beth Israel Deaconess Medical Center | B33: Commercial | C33: Harvard Pilgrim Healthcare | D33: Self Insured Non LCU All Commercial Plans | E33: Hospital file, same payer/plan | F33: =Rates_data!P75 -> 396.97 | G33: =Rates_data!P71 -> 310.92 | H33: =F33+G33 -> 707.89 | I33: =IF(Rates_data!S75="","",Rates_data!S75) | J33: =IF(Rates_data!S71="","",Rates_data!S71) | K33: =IF(AND(I33<>"",J33<>""),I33+J33,"") | L33: =IF(K33<>"",K33,H33) -> 707.89 | M33: =IF(K33<>"","median allowed","negotiated") -> negotiated | N33: =Reference!$C$10 -> 142.57 | O33: =L33+N33 -> 850.46
A36: Commercial summary by hospital (medians across commercial payer/plan pairs)
A37: Hospital | B37: Commercial pairs | C37: Median headline facility battery | D37: Median negotiated facility battery | E37: Median approx. total battery cost | F37: Min headline | G37: Max headline
A38: Massachusetts General Hospital | B38: =COUNTIFS($A$5:$A$33,$A38,$B$5:$B$33,"Commercial") -> 9 | C38: {=IF($B38=0,"none listed",MEDIAN(IF(($A$5:$A$33=$A38)*($B$5:$B$33="Commercial"),$L$5:$L$33)))} -> 1538.14 | D38: {=IF($B38=0,"none listed",MEDIAN(IF(($A$5:$A$33=$A38)*($B$5:$B$33="Commercial"),$H$5:$H$33)))} -> 1385.15 | E38: {=IF($B38=0,"none listed",MEDIAN(IF(($A$5:$A$33=$A38)*($B$5:$B$33="Commercial"),$O$5:$O$33)))} -> 1680.71 | F38: =IF($B38=0,"",_xlfn.MINIFS($L$5:$L$33,$A$5:$A$33,$A38,$B$5:$B$33,"Commercial")) -> 770.62 | G38: =IF($B38=0,"",_xlfn.MAXIFS($L$5:$L$33,$A$5:$A$33,$A38,$B$5:$B$33,"Commercial")) -> 2657.53
A39: Brigham and Women's Hospital | B39: =COUNTIFS($A$5:$A$33,$A39,$B$5:$B$33,"Commercial") -> 0 | C39: {=IF($B39=0,"none listed",MEDIAN(IF(($A$5:$A$33=$A39)*($B$5:$B$33="Commercial"),$L$5:$L$33)))} -> none listed | D39: {=IF($B39=0,"none listed",MEDIAN(IF(($A$5:$A$33=$A39)*($B$5:$B$33="Commercial"),$H$5:$H$33)))} -> none listed | E39: {=IF($B39=0,"none listed",MEDIAN(IF(($A$5:$A$33=$A39)*($B$5:$B$33="Commercial"),$O$5:$O$33)))} -> none listed | F39: =IF($B39=0,"",_xlfn.MINIFS($L$5:$L$33,$A$5:$A$33,$A39,$B$5:$B$33,"Commercial")) | G39: =IF($B39=0,"",_xlfn.MAXIFS($L$5:$L$33,$A$5:$A$33,$A39,$B$5:$B$33,"Commercial"))
A40: Brigham and Women's Faulkner Hospital | B40: =COUNTIFS($A$5:$A$33,$A40,$B$5:$B$33,"Commercial") -> 5 | C40: {=IF($B40=0,"none listed",MEDIAN(IF(($A$5:$A$33=$A40)*($B$5:$B$33="Commercial"),$L$5:$L$33)))} -> 1068.72 | D40: {=IF($B40=0,"none listed",MEDIAN(IF(($A$5:$A$33=$A40)*($B$5:$B$33="Commercial"),$H$5:$H$33)))} -> 1098.65 | E40: {=IF($B40=0,"none listed",MEDIAN(IF(($A$5:$A$33=$A40)*($B$5:$B$33="Commercial"),$O$5:$O$33)))} -> 1211.29 | F40: =IF($B40=0,"",_xlfn.MINIFS($L$5:$L$33,$A$5:$A$33,$A40,$B$5:$B$33,"Commercial")) -> 667 | G40: =IF($B40=0,"",_xlfn.MAXIFS($L$5:$L$33,$A$5:$A$33,$A40,$B$5:$B$33,"Commercial")) -> 1464
A41: Wentworth-Douglass Hospital | B41: =COUNTIFS($A$5:$A$33,$A41,$B$5:$B$33,"Commercial") -> 0 | C41: {=IF($B41=0,"none listed",MEDIAN(IF(($A$5:$A$33=$A41)*($B$5:$B$33="Commercial"),$L$5:$L$33)))} -> none listed | D41: {=IF($B41=0,"none listed",MEDIAN(IF(($A$5:$A$33=$A41)*($B$5:$B$33="Commercial"),$H$5:$H$33)))} -> none listed | E41: {=IF($B41=0,"none listed",MEDIAN(IF(($A$5:$A$33=$A41)*($B$5:$B$33="Commercial"),$O$5:$O$33)))} -> none listed | F41: =IF($B41=0,"",_xlfn.MINIFS($L$5:$L$33,$A$5:$A$33,$A41,$B$5:$B$33,"Commercial")) | G41: =IF($B41=0,"",_xlfn.MAXIFS($L$5:$L$33,$A$5:$A$33,$A41,$B$5:$B$33,"Commercial"))
A42: Beth Israel Deaconess Medical Center | B42: =COUNTIFS($A$5:$A$33,$A42,$B$5:$B$33,"Commercial") -> 3 | C42: {=IF($B42=0,"none listed",MEDIAN(IF(($A$5:$A$33=$A42)*($B$5:$B$33="Commercial"),$L$5:$L$33)))} -> 607.71 | D42: {=IF($B42=0,"none listed",MEDIAN(IF(($A$5:$A$33=$A42)*($B$5:$B$33="Commercial"),$H$5:$H$33)))} -> 607.71 | E42: {=IF($B42=0,"none listed",MEDIAN(IF(($A$5:$A$33=$A42)*($B$5:$B$33="Commercial"),$O$5:$O$33)))} -> 750.28 | F42: =IF($B42=0,"",_xlfn.MINIFS($L$5:$L$33,$A$5:$A$33,$A42,$B$5:$B$33,"Commercial")) -> 581.1 | G42: =IF($B42=0,"",_xlfn.MAXIFS($L$5:$L$33,$A$5:$A$33,$A42,$B$5:$B$33,"Commercial")) -> 707.89

Sheet Multiples
A1: Multiples of Medicare
A2: A: each included facility rate / OPPS national (Addendum B, unadjusted for MA wage index) and / the hospital's own Medicare FFS row. B: approximate total battery cost / 316.15 (independent-site MPFS global).
A4: A. Facility rate multiples
A5: Hospital | B5: Code | C5: Segment | D5: Payer | E5: Plan | F5: Implied facility rate | G5: OPPS national rate | H5: Multiple of OPPS national | I5: Hospital Medicare FFS row (same code) | J5: Multiple of hospital Medicare row | K5: Headline rate | L5: Headline basis
A6: Massachusetts General Hospital | B6: 95921 | C6: Commercial | D6: UNITED HEALTHCARE [1016] | E6: HB AMC UNITED PPO / POS | F6: =Rates_data!P2 -> 500.13 | G6: =Rates_data!AE2 -> 131.46 | H6: =IF(G6>0,F6/G6,"") -> 3.8044272 | I6: not listed | K6: =Rates_data!W2 -> 474.04 | L6: =Rates_data!X2 -> median allowed
A7: Massachusetts General Hospital | B7: 95923 | C7: Commercial | D7: AETNA [1001] | E7: HB AMC AETNA HMO | F7: =Rates_data!P3 -> 686.13 | G7: =Rates_data!AE3 -> 135.93 | H7: =IF(G7>0,F7/G7,"") -> 5.0476716 | I7: not listed | K7: =Rates_data!W3 -> 1212.81 | L7: =Rates_data!X3 -> median allowed
A8: Massachusetts General Hospital | B8: 95923 | C8: Commercial | D8: CIGNA ALTERNATE [1018] | E8: HB AMC CIGNA NEW BUSINESS DISCOUNT | F8: =Rates_data!P4 -> 523.94 | G8: =Rates_data!AE4 -> 135.93 | H8: =IF(G8>0,F8/G8,"") -> 3.8544839 | I8: not listed | K8: =Rates_data!W4 -> 503.18 | L8: =Rates_data!X4 -> median allowed
A9: Massachusetts General Hospital | B9: 95923 | C9: Commercial | D9: CIGNA [1006] | E9: HB AMC CIGNA HMO / PPO | F9: =Rates_data!P5 -> 781.49 | G9: =Rates_data!AE5 -> 135.93 | H9: =IF(G9>0,F9/G9,"") -> 5.7492092 | I9: not listed | K9: =Rates_data!W5 -> 750.01 | L9: =Rates_data!X5 -> median allowed
A10: Massachusetts General Hospital | B10: 95923 | C10: Commercial | D10: INTERNATIONAL COMMERCIAL [140001] | E10: HB AMC / MEE / PCC / ONE TEAM HEALTH INTERNATIONAL | F10: =Rates_data!P6 -> 638.95 | G10: =Rates_data!AE6 -> 135.93 | H10: =IF(G10>0,F10/G10,"") -> 4.7005812 | I10: not listed | K10: =Rates_data!W6 -> 619.45 | L10: =Rates_data!X6 -> median allowed
A11: Massachusetts General Hospital | B11: 95923 | C11: Commercial | D11: MGB HEALTH PLAN [150001] | E11: HB AMC MGBHP COMMERCIAL HMO | F11: =Rates_data!P7 -> 358.8 | G11: =Rates_data!AE7 -> 135.93 | H11: =IF(G11>0,F11/G11,"") -> 2.6395939 | I11: not listed | K11: =Rates_data!W7 -> 355.47 | L11: =Rates_data!X7 -> median allowed
A12: Massachusetts General Hospital | B12: 95923 | C12: Commercial | D12: MGB HEALTH PLAN [150001] | E12: HB AMC MGBHP COMMERCIAL PPO | F12: =Rates_data!P8 -> 376.49 | G12: =Rates_data!AE8 -> 135.93 | H12: =IF(G12>0,F12/G12,"") -> 2.7697344 | I12: not listed | K12: =Rates_data!W8 -> 372.62 | L12: =Rates_data!X8 -> median allowed
A13: Massachusetts General Hospital | B13: 95923 | C13: Commercial | D13: UNITED HEALTHCARE [1016] | E13: HB AMC CH UNITED NEW BUSINESS DISCOUNT | F13: =Rates_data!P9 -> 421.71 | G13: =Rates_data!AE9 -> 135.93 | H13: =IF(G13>0,F13/G13,"") -> 3.1024056 | I13: not listed | K13: =Rates_data!W9 -> 761.83 | L13: =Rates_data!X9 -> median allowed
A14: Massachusetts General Hospital | B14: 95923 | C14: Commercial | D14: UNITED HEALTHCARE [1016] | E14: HB AMC UNITED PPO / POS | F14: =Rates_data!P10 -> 803.31 | G14: =Rates_data!AE10 -> 135.93 | H14: =IF(G14>0,F14/G14,"") -> 5.909733 | I14: not listed | K14: =Rates_data!W10 -> 761.83 | L14: =Rates_data!X10 -> median allowed
A15: Massachusetts General Hospital | B15: 95923 | C15: Commercial | D15: WELLPOINT [1015] | E15: HB AMC WELLPOINT | F15: =Rates_data!P11 -> 725.26 | G15: =Rates_data!AE11 -> 135.93 | H15: =IF(G15>0,F15/G15,"") -> 5.3355404 | I15: not listed | K15: =Rates_data!W11 -> 709.51 | L15: =Rates_data!X11 -> median allowed
A16: Massachusetts General Hospital | B16: 95924 | C16: Commercial | D16: AETNA [1001] | E16: HB AMC AETNA HMO | F16: =Rates_data!P12 -> 801.3 | G16: =Rates_data!AE12 -> 220.6 | H16: =IF(G16>0,F16/G16,"") -> 3.6323663 | I16: =Rates_data!P27 -> 369.77 | J16: =IF(I16>0,F16/I16,"") -> 2.1670227 | K16: =Rates_data!W12 -> 1444.72 | L16: =Rates_data!X12 -> median allowed
A17: Massachusetts General Hospital | B17: 95924 | C17: Commercial | D17: CIGNA ALTERNATE [1018] | E17: HB AMC CIGNA NEW BUSINESS DISCOUNT | F17: =Rates_data!P13 -> 611.88 | G17: =Rates_data!AE13 -> 220.6 | H17: =IF(G17>0,F17/G17,"") -> 2.7737081 | I17: =Rates_data!P27 -> 369.77 | J17: =IF(I17>0,F17/I17,"") -> 1.6547584 | K17: =Rates_data!W13 -> 587.66 | L17: =Rates_data!X13 -> median allowed
A18: Massachusetts General Hospital | B18: 95924 | C18: Commercial | D18: CIGNA [1006] | E18: HB AMC CIGNA HMO / PPO | F18: =Rates_data!P14 -> 912.66 | G18: =Rates_data!AE14 -> 220.6 | H18: =IF(G18>0,F18/G18,"") -> 4.1371714 | I18: =Rates_data!P27 -> 369.77 | J18: =IF(I18>0,F18/I18,"") -> 2.4681829 | K18: =Rates_data!W14 -> 875.93 | L18: =Rates_data!X14 -> median allowed
A19: Massachusetts General Hospital | B19: 95924 | C19: Commercial | D19: INTERNATIONAL COMMERCIAL [140001] | E19: HB AMC / MEE / PCC / ONE TEAM HEALTH INTERNATIONAL | F19: =Rates_data!P15 -> 746.2 | G19: =Rates_data!AE15 -> 220.6 | H19: =IF(G19>0,F19/G19,"") -> 3.3825929 | I19: =Rates_data!P27 -> 369.77 | J19: =IF(I19>0,F19/I19,"") -> 2.0180112 | K19: =Rates_data!W15 -> 723.45 | L19: =Rates_data!X15 -> median allowed
A20: Massachusetts General Hospital | B20: 95924 | C20: Commercial | D20: MGB HEALTH PLAN [150001] | E20: HB AMC MGBHP COMMERCIAL HMO | F20: =Rates_data!P16 -> 419.02 | G20: =Rates_data!AE16 -> 220.6 | H20: =IF(G20>0,F20/G20,"") -> 1.899456 | I20: =Rates_data!P27 -> 369.77 | J20: =IF(I20>0,F20/I20,"") -> 1.1331909 | K20: =Rates_data!W16 -> 415.15 | L20: =Rates_data!X16 -> median allowed
A21: Massachusetts General Hospital | B21: 95924 | C21: Commercial | D21: MGB HEALTH PLAN [150001] | E21: HB AMC MGBHP COMMERCIAL PPO | F21: =Rates_data!P17 -> 439.68 | G21: =Rates_data!AE17 -> 220.6 | H21: =IF(G21>0,F21/G21,"") -> 1.9931097 | I21: =Rates_data!P27 -> 369.77 | J21: =IF(I21>0,F21/I21,"") -> 1.1890635 | K21: =Rates_data!W17 -> 435.18 | L21: =Rates_data!X17 -> median allowed
A22: Massachusetts General Hospital | B22: 95924 | C22: Commercial | D22: UNITED HEALTHCARE [1016] | E22: HB AMC CH UNITED NEW BUSINESS DISCOUNT | F22: =Rates_data!P18 -> 492.49 | G22: =Rates_data!AE18 -> 220.6 | H22: =IF(G22>0,F22/G22,"") -> 2.2325023 | I22: =Rates_data!P27 -> 369.77 | J22: =IF(I22>0,F22/I22,"") -> 1.331882 | K22: =Rates_data!W18 -> 889.73 | L22: =Rates_data!X18 -> median allowed
A23: Massachusetts General Hospital | B23: 95924 | C23: Commercial | D23: UNITED HEALTHCARE [1016] | E23: HB AMC UNITED PPO / POS | F23: =Rates_data!P19 -> 938.15 | G23: =Rates_data!AE19 -> 220.6 | H23: =IF(G23>0,F23/G23,"") -> 4.2527199 | I23: =Rates_data!P27 -> 369.77 | J23: =IF(I23>0,F23/I23,"") -> 2.5371177 | K23: =Rates_data!W19 -> 889.73 | L23: =Rates_data!X19 -> median allowed
A24: Massachusetts General Hospital | B24: 95924 | C24: Commercial | D24: WELLPOINT [1015] | E24: HB AMC WELLPOINT | F24: =Rates_data!P20 -> 846.99 | G24: =Rates_data!AE20 -> 220.6 | H24: =IF(G24>0,F24/G24,"") -> 3.8394832 | I24: =Rates_data!P27 -> 369.77 | J24: =IF(I24>0,F24/I24,"") -> 2.290586 | K24: =Rates_data!W20 -> 828.63 | L24: =Rates_data!X20 -> median allowed
A25: Massachusetts General Hospital | B25: 95924 | C25: MassHealth / dual managed care | D25: COMMONWEALTH CARE ALLIANCE [1007] | E25: HB MGH COMMONWEALTH CARE ALLIANCE | F25: =Rates_data!P21 -> 369.77 | G25: =Rates_data!AE21 -> 220.6 | H25: =IF(G25>0,F25/G25,"") -> 1.6762013 | I25: =Rates_data!P27 -> 369.77 | J25: =IF(I25>0,F25/I25,"") -> 1 | K25: =Rates_data!W21 -> 365.12 | L25: =Rates_data!X21 -> median allowed
A26: Massachusetts General Hospital | B26: 95924 | C26: Medicare Advantage | D26: BLUE CROSS BLUE SHIELD [110001] | E26: HB MGH MEDICARE | F26: =Rates_data!P22 -> 369.77 | G26: =Rates_data!AE22 -> 220.6 | H26: =IF(G26>0,F26/G26,"") -> 1.6762013 | I26: =Rates_data!P27 -> 369.77 | J26: =IF(I26>0,F26/I26,"") -> 1 | K26: =Rates_data!W22 -> 363.89 | L26: =Rates_data!X22 -> median allowed
A27: Massachusetts General Hospital | B27: 95924 | C27: Medicare Advantage | D27: HUMANA [1012] | E27: HB MGH MEDICARE | F27: =Rates_data!P23 -> 369.77 | G27: =Rates_data!AE23 -> 220.6 | H27: =IF(G27>0,F27/G27,"") -> 1.6762013 | I27: =Rates_data!P27 -> 369.77 | J27: =IF(I27>0,F27/I27,"") -> 1 | K27: =Rates_data!W23 -> 365.37 | L27: =Rates_data!X23 -> median allowed
A28: Massachusetts General Hospital | B28: 95924 | C28: Medicare Advantage | D28: MGB HEALTH PLAN [150001] | E28: HB MGH MEDICARE | F28: =Rates_data!P24 -> 369.77 | G28: =Rates_data!AE24 -> 220.6 | H28: =IF(G28>0,F28/G28,"") -> 1.6762013 | I28: =Rates_data!P27 -> 369.77 | J28: =IF(I28>0,F28/I28,"") -> 1 | K28: =Rates_data!W24 -> 336.12 | L28: =Rates_data!X24 -> median allowed
A29: Massachusetts General Hospital | B29: 95924 | C29: Medicare Advantage | D29: TUFTS HEALTH PLAN [170001] | E29: HB MGH TUFTS MEDICARE REPLACEMENT | F29: =Rates_data!P25 -> 362.37 | G29: =Rates_data!AE25 -> 220.6 | H29: =IF(G29>0,F29/G29,"") -> 1.6426564 | I29: =Rates_data!P27 -> 369.77 | J29: =IF(I29>0,F29/I29,"") -> 0.97998756 | K29: =Rates_data!W25 -> 362.81 | L29: =Rates_data!X25 -> median allowed
A30: Massachusetts General Hospital | B30: 95924 | C30: Medicare Advantage | D30: UNITED HEALTHCARE [1016] | E30: HB MGH UNITED MEDICARE REPLACEMENT | F30: =Rates_data!P26 -> 362.37 | G30: =Rates_data!AE26 -> 220.6 | H30: =IF(G30>0,F30/G30,"") -> 1.6426564 | I30: =Rates_data!P27 -> 369.77 | J30: =IF(I30>0,F30/I30,"") -> 0.97998756 | K30: =Rates_data!W26 -> 362.92 | L30: =Rates_data!X26 -> median allowed
A31: Massachusetts General Hospital | B31: 95924 | C31: Medicare FFS | D31: MEDICARE [2001] | E31: HB MGH MEDICARE | F31: =Rates_data!P27 -> 369.77 | G31: =Rates_data!AE27 -> 220.6 | H31: =IF(G31>0,F31/G31,"") -> 1.6762013 | I31: =Rates_data!P27 -> 369.77 | J31: =IF(I31>0,F31/I31,"") -> 1 | K31: =Rates_data!W27 -> 369.81 | L31: =Rates_data!X27 -> median allowed
A32: Massachusetts General Hospital | B32: 95924 | C32: TRICARE | D32: TRICARE [160005] | E32: HB MGH TRICARE | F32: =Rates_data!P28 -> 351.32 | G32: =Rates_data!AE28 -> 220.6 | H32: =IF(G32>0,F32/G32,"") -> 1.5925657 | I32: =Rates_data!P27 -> 369.77 | J32: =IF(I32>0,F32/I32,"") -> 0.95010412 | K32: =Rates_data!W28 -> 351.32 | L32: =Rates_data!X28 -> median allowed
A33: Brigham and Women's Faulkner Hospital | B33: 95921 | C33: Commercial | D33: CIGNA [1006] | E33: HB CH CIGNA HMO / PPO | F33: =Rates_data!P29 -> 255.58 | G33: =Rates_data!AE29 -> 131.46 | H33: =IF(G33>0,F33/G33,"") -> 1.9441655 | I33: =Rates_data!P32 -> 185.81 | J33: =IF(I33>0,F33/I33,"") -> 1.3754911 | K33: =Rates_data!W29 -> 245.53 | L33: =Rates_data!X29 -> median allowed
A34: Brigham and Women's Faulkner Hospital | B34: 95921 | C34: Commercial | D34: UNITED HEALTHCARE [1016] | E34: HB CH UNITED HMO / PPO / INDEMNITY | F34: =Rates_data!P30 -> 338.12 | G34: =Rates_data!AE30 -> 131.46 | H34: =IF(G34>0,F34/G34,"") -> 2.5720371 | I34: =Rates_data!P32 -> 185.81 | J34: =IF(I34>0,F34/I34,"") -> 1.8197083 | K34: =Rates_data!W30 -> 322.13 | L34: =Rates_data!X30 -> median allowed
A35: Brigham and Women's Faulkner Hospital | B35: 95921 | C35: Medicare Advantage | D35: UNITED HEALTHCARE [1016] | E35: HB BWF UNITED MEDICARE REPLACEMENT | F35: =Rates_data!P31 -> 182.09 | G35: =Rates_data!AE31 -> 131.46 | H35: =IF(G35>0,F35/G35,"") -> 1.3851362 | I35: =Rates_data!P32 -> 185.81 | J35: =IF(I35>0,F35/I35,"") -> 0.97997955 | K35: =Rates_data!W31 -> 182.84 | L35: =Rates_data!X31 -> median allowed
A36: Brigham and Women's Faulkner Hospital | B36: 95921 | C36: Medicare FFS | D36: MEDICARE [2001] | E36: HB BWF MEDICARE | F36: =Rates_data!P32 -> 185.81 | G36: =Rates_data!AE32 -> 131.46 | H36: =IF(G36>0,F36/G36,"") -> 1.4134337 | I36: =Rates_data!P32 -> 185.81 | J36: =IF(I36>0,F36/I36,"") -> 1 | K36: =Rates_data!W32 -> 185.81 | L36: =Rates_data!X32 -> median allowed
A37: Brigham and Women's Faulkner Hospital | B37: 95923 | C37: Commercial | D37: CIGNA [1006] | E37: HB CH CIGNA HMO / PPO | F37: =Rates_data!P33 -> 412.73 | G37: =Rates_data!AE33 -> 135.93 | H37: =IF(G37>0,F37/G37,"") -> 3.0363422 | I37: =Rates_data!P40 -> 153.08 | J37: =IF(I37>0,F37/I37,"") -> 2.6961719 | K37: =Rates_data!W33 -> 396.72 | L37: =Rates_data!X33 -> median allowed
A38: Brigham and Women's Faulkner Hospital | B38: 95923 | C38: Commercial | D38: HEALTH NEW ENGLAND [1034] | E38: HB CH CLARITEV (PRIMARY PPO) | F38: =Rates_data!P34 -> 508.08 | G38: =Rates_data!AE34 -> 135.93 | H38: =IF(G38>0,F38/G38,"") -> 3.7378062 | I38: =Rates_data!P40 -> 153.08 | J38: =IF(I38>0,F38/I38,"") -> 3.3190489 | K38: =Rates_data!W34 -> 494.21 | L38: =Rates_data!X34 -> median allowed
A39: Brigham and Women's Faulkner Hospital | B39: 95923 | C39: Commercial | D39: UNITED HEALTHCARE [1016] | E39: HB AMC CH UNITED NEW BUSINESS DISCOUNT | F39: =Rates_data!P35 -> 309.37 | G39: =Rates_data!AE35 -> 135.93 | H39: =IF(G39>0,F39/G39,"") -> 2.2759509 | I39: =Rates_data!P40 -> 153.08 | J39: =IF(I39>0,F39/I39,"") -> 2.0209694 | K39: =Rates_data!W35 -> 308.44 | L39: =Rates_data!X35 -> median allowed
A40: Brigham and Women's Faulkner Hospital | B40: 95923 | C40: Commercial | D40: UNITED HEALTHCARE [1016] | E40: HB CH UNITED HMO / PPO / INDEMNITY | F40: =Rates_data!P36 -> 546.01 | G40: =Rates_data!AE36 -> 135.93 | H40: =IF(G40>0,F40/G40,"") -> 4.0168469 | I40: =Rates_data!P40 -> 153.08 | J40: =IF(I40>0,F40/I40,"") -> 3.5668278 | K40: =Rates_data!W36 -> 520.48 | L40: =Rates_data!X36 -> median allowed
A41: Brigham and Women's Faulkner Hospital | B41: 95923 | C41: Commercial | D41: WELLPOINT [1015] | E41: HB CH WELLPOINT | F41: =Rates_data!P37 -> 542.25 | G41: =Rates_data!AE37 -> 135.93 | H41: =IF(G41>0,F41/G41,"") -> 3.9891856 | I41: =Rates_data!P40 -> 153.08 | J41: =IF(I41>0,F41/I41,"") -> 3.5422655 | K41: =Rates_data!W37 -> 677 | L41: =Rates_data!X37 -> median allowed
A42: Brigham and Women's Faulkner Hospital | B42: 95923 | C42: Medicare Advantage | D42: BLUE CROSS BLUE SHIELD [110001] | E42: HB BWF MEDICARE | F42: =Rates_data!P38 -> 153.08 | G42: =Rates_data!AE38 -> 135.93 | H42: =IF(G42>0,F42/G42,"") -> 1.1261679 | I42: =Rates_data!P40 -> 153.08 | J42: =IF(I42>0,F42/I42,"") -> 1 | K42: =Rates_data!W38 -> 171.01 | L42: =Rates_data!X38 -> median allowed
A43: Brigham and Women's Faulkner Hospital | B43: 95923 | C43: Medicare Advantage | D43: CENTERS OF EXCELLENCE [1026] | E43: HB BWF MEDICARE | F43: =Rates_data!P39 -> 153.08 | G43: =Rates_data!AE39 -> 135.93 | H43: =IF(G43>0,F43/G43,"") -> 1.1261679 | I43: =Rates_data!P40 -> 153.08 | J43: =IF(I43>0,F43/I43,"") -> 1 | K43: =Rates_data!W39 -> 168.27 | L43: =Rates_data!X39 -> median allowed
A44: Brigham and Women's Faulkner Hospital | B44: 95923 | C44: Medicare FFS | D44: MEDICARE [2001] | E44: HB BWF MEDICARE | F44: =Rates_data!P40 -> 153.08 | G44: =Rates_data!AE40 -> 135.93 | H44: =IF(G44>0,F44/G44,"") -> 1.1261679 | I44: =Rates_data!P40 -> 153.08 | J44: =IF(I44>0,F44/I44,"") -> 1 | K44: =Rates_data!W40 -> 306.16 | L44: =Rates_data!X40 -> median allowed
A45: Brigham and Women's Faulkner Hospital | B45: 95924 | C45: Commercial | D45: CIGNA [1006] | E45: HB CH CIGNA HMO / PPO | F45: =Rates_data!P41 -> 479.74 | G45: =Rates_data!AE41 -> 220.6 | H45: =IF(G45>0,F45/G45,"") -> 2.1747053 | I45: =Rates_data!P53 -> 369.81 | J45: =IF(I45>0,F45/I45,"") -> 1.2972608 | K45: =Rates_data!W41 -> 461.18 | L45: =Rates_data!X41 -> median allowed
A46: Brigham and Women's Faulkner Hospital | B46: 95924 | C46: Commercial | D46: HEALTH NEW ENGLAND [1034] | E46: HB CH CLARITEV (PRIMARY PPO) | F46: =Rates_data!P42 -> 590.57 | G46: =Rates_data!AE42 -> 220.6 | H46: =IF(G46>0,F46/G46,"") -> 2.6771079 | I46: =Rates_data!P53 -> 369.81 | J46: =IF(I46>0,F46/I46,"") -> 1.5969552 | K46: =Rates_data!W42 -> 574.51 | L46: =Rates_data!X42 -> median allowed
A47: Brigham and Women's Faulkner Hospital | B47: 95924 | C47: Commercial | D47: UNITED HEALTHCARE [1016] | E47: HB AMC CH UNITED NEW BUSINESS DISCOUNT | F47: =Rates_data!P43 -> 359.6 | G47: =Rates_data!AE43 -> 220.6 | H47: =IF(G47>0,F47/G47,"") -> 1.6300997 | I47: =Rates_data!P53 -> 369.81 | J47: =IF(I47>0,F47/I47,"") -> 0.97239123 | K47: =Rates_data!W43 -> 358.56 | L47: =Rates_data!X43 -> median allowed
A48: Brigham and Women's Faulkner Hospital | B48: 95924 | C48: Commercial | D48: UNITED HEALTHCARE [1016] | E48: HB CH UNITED HMO / PPO / INDEMNITY | F48: =Rates_data!P44 -> 634.66 | G48: =Rates_data!AE44 -> 220.6 | H48: =IF(G48>0,F48/G48,"") -> 2.8769719 | I48: =Rates_data!P53 -> 369.81 | J48: =IF(I48>0,F48/I48,"") -> 1.7161786 | K48: =Rates_data!W44 -> 605.05 | L48: =Rates_data!X44 -> median allowed
A49: Brigham and Women's Faulkner Hospital | B49: 95924 | C49: Commercial | D49: WELLPOINT [1015] | E49: HB CH WELLPOINT | F49: =Rates_data!P45 -> 630.29 | G49: =Rates_data!AE45 -> 220.6 | H49: =IF(G49>0,F49/G49,"") -> 2.8571623 | I49: =Rates_data!P53 -> 369.81 | J49: =IF(I49>0,F49/I49,"") -> 1.7043617 | K49: =Rates_data!W45 -> 787 | L49: =Rates_data!X45 -> median allowed
A50: Brigham and Women's Faulkner Hospital | B50: 95924 | C50: Medicare Advantage | D50: BLUE CROSS BLUE SHIELD [110001] | E50: HB BWF MEDICARE | F50: =Rates_data!P46 -> 369.81 | G50: =Rates_data!AE46 -> 220.6 | H50: =IF(G50>0,F50/G50,"") -> 1.6763826 | I50: =Rates_data!P53 -> 369.81 | J50: =IF(I50>0,F50/I50,"") -> 1 | K50: =Rates_data!W46 -> 363.89 | L50: =Rates_data!X46 -> median allowed
A51: Brigham and Women's Faulkner Hospital | B51: 95924 | C51: Medicare Advantage | D51: CENTERS OF EXCELLENCE [1026] | E51: HB BWF MEDICARE | F51: =Rates_data!P47 -> 369.81 | G51: =Rates_data!AE47 -> 220.6 | H51: =IF(G51>0,F51/G51,"") -> 1.6763826 | I51: =Rates_data!P53 -> 369.81 | J51: =IF(I51>0,F51/I51,"") -> 1 | K51: =Rates_data!W47 -> 366.63 | L51: =Rates_data!X47 -> median allowed
A52: Brigham and Women's Faulkner Hospital | B52: 95924 | C52: Medicare Advantage | D52: COMMONWEALTH CARE ALLIANCE [1007] | E52: HB BWF TUFTS + COMM CARE ALLIANCE MCARE | F52: =Rates_data!P48 -> 362.41 | G52: =Rates_data!AE48 -> 220.6 | H52: =IF(G52>0,F52/G52,"") -> 1.6428377 | I52: =Rates_data!P53 -> 369.81 | J52: =IF(I52>0,F52/I52,"") -> 0.97998972 | K52: =Rates_data!W48 -> 363.89 | L52: =Rates_data!X48 -> median allowed
A53: Brigham and Women's Faulkner Hospital | B53: 95924 | C53: Medicare Advantage | D53: HUMANA [1012] | E53: HB BWF MEDICARE | F53: =Rates_data!P49 -> 369.81 | G53: =Rates_data!AE49 -> 220.6 | H53: =IF(G53>0,F53/G53,"") -> 1.6763826 | I53: =Rates_data!P53 -> 369.81 | J53: =IF(I53>0,F53/I53,"") -> 1 | K53: =Rates_data!W49 -> 362.41 | L53: =Rates_data!X49 -> median allowed
A54: Brigham and Women's Faulkner Hospital | B54: 95924 | C54: Medicare Advantage | D54: MARTIN'S POINT [160007] | E54: HB BWF MEDICARE | F54: =Rates_data!P50 -> 369.81 | G54: =Rates_data!AE50 -> 220.6 | H54: =IF(G54>0,F54/G54,"") -> 1.6763826 | I54: =Rates_data!P53 -> 369.81 | J54: =IF(I54>0,F54/I54,"") -> 1 | K54: =Rates_data!W50 -> 363.89 | L54: =Rates_data!X50 -> median allowed
A55: Brigham and Women's Faulkner Hospital | B55: 95924 | C55: Medicare Advantage | D55: TUFTS HEALTH PLAN [170001] | E55: HB BWF TUFTS + COMM CARE ALLIANCE MCARE | F55: =Rates_data!P51 -> 362.41 | G55: =Rates_data!AE51 -> 220.6 | H55: =IF(G55>0,F55/G55,"") -> 1.6428377 | I55: =Rates_data!P53 -> 369.81 | J55: =IF(I55>0,F55/I55,"") -> 0.97998972 | K55: =Rates_data!W51 -> 362.81 | L55: =Rates_data!X51 -> median allowed
A56: Brigham and Women's Faulkner Hospital | B56: 95924 | C56: Medicare Advantage | D56: UNITED HEALTHCARE [1016] | E56: HB BWF UNITED MEDICARE REPLACEMENT | F56: =Rates_data!P52 -> 362.41 | G56: =Rates_data!AE52 -> 220.6 | H56: =IF(G56>0,F56/G56,"") -> 1.6428377 | I56: =Rates_data!P53 -> 369.81 | J56: =IF(I56>0,F56/I56,"") -> 0.97998972 | K56: =Rates_data!W52 -> 362.92 | L56: =Rates_data!X52 -> median allowed
A57: Brigham and Women's Faulkner Hospital | B57: 95924 | C57: Medicare FFS | D57: MEDICARE [2001] | E57: HB BWF MEDICARE | F57: =Rates_data!P53 -> 369.81 | G57: =Rates_data!AE53 -> 220.6 | H57: =IF(G57>0,F57/G57,"") -> 1.6763826 | I57: =Rates_data!P53 -> 369.81 | J57: =IF(I57>0,F57/I57,"") -> 1 | K57: =Rates_data!W53 -> 369.81 | L57: =Rates_data!X53 -> median allowed
A58: Brigham and Women's Faulkner Hospital | B58: 95924 | C58: TRICARE | D58: TRICARE [160005] | E58: HB BWF TRICARE | F58: =Rates_data!P54 -> 351.32 | G58: =Rates_data!AE54 -> 220.6 | H58: =IF(G58>0,F58/G58,"") -> 1.5925657 | I58: =Rates_data!P53 -> 369.81 | J58: =IF(I58>0,F58/I58,"") -> 0.95000135 | K58: =Rates_data!W54 -> 351.32 | L58: =Rates_data!X54 -> median allowed
A59: Beth Israel Deaconess Medical Center | B59: 93660 | C59: Commercial | D59: BCBS | E59: HMO | F59: =Rates_data!P56 -> 1091.24 | G59: =Rates_data!AE56 -> 381.24 | H59: =IF(G59>0,F59/G59,"") -> 2.8623439 | I59: not listed | K59: =Rates_data!W56 -> 1091.24 | L59: =Rates_data!X56 -> negotiated
A60: Beth Israel Deaconess Medical Center | B60: 93660 | C60: Commercial | D60: BCBS | E60: PPO | F60: =Rates_data!P57 -> 1141.22 | G60: =Rates_data!AE57 -> 381.24 | H60: =IF(G60>0,F60/G60,"") -> 2.9934425 | I60: not listed | K60: =Rates_data!W57 -> 1141.22 | L60: =Rates_data!X57 -> negotiated
A61: Beth Israel Deaconess Medical Center | B61: 93660 | C61: Commercial | D61: Harvard Pilgrim Healthcare | E61: Self Insured Non LCU All Commercial Plans | F61: =Rates_data!P58 -> 1329.39 | G61: =Rates_data!AE58 -> 381.24 | H61: =IF(G61>0,F61/G61,"") -> 3.4870161 | I61: not listed | K61: =Rates_data!W58 -> 1329.39 | L61: =Rates_data!X58 -> negotiated
A62: Beth Israel Deaconess Medical Center | B62: 93660 | C62: Commercial | D62: Unicare | E62: GIC Wellpoint All Commercial Plans | F62: =Rates_data!P59 -> 502.78 | G62: =Rates_data!AE59 -> 381.24 | H62: =IF(G62>0,F62/G62,"") -> 1.3188018 | I62: not listed | K62: =Rates_data!W59 -> 502.78 | L62: =Rates_data!X59 -> negotiated
A63: Beth Israel Deaconess Medical Center | B63: 95921 | C63: Commercial | D63: BCBS | E63: HMO | F63: =Rates_data!P61 -> 325.87 | G63: =Rates_data!AE61 -> 131.46 | H63: =IF(G63>0,F63/G63,"") -> 2.4788529 | I63: not listed | K63: =Rates_data!W61 -> 325.87 | L63: =Rates_data!X61 -> negotiated
A64: Beth Israel Deaconess Medical Center | B64: 95921 | C64: Commercial | D64: BCBS | E64: PPO | F64: =Rates_data!P62 -> 340.79 | G64: =Rates_data!AE62 -> 131.46 | H64: =IF(G64>0,F64/G64,"") -> 2.5923475 | I64: not listed | K64: =Rates_data!W62 -> 340.79 | L64: =Rates_data!X62 -> negotiated
A65: Beth Israel Deaconess Medical Center | B65: 95921 | C65: Commercial | D65: Harvard Pilgrim Healthcare | E65: Self Insured Non LCU All Commercial Plans | F65: =Rates_data!P63 -> 396.97 | G65: =Rates_data!AE63 -> 131.46 | H65: =IF(G65>0,F65/G65,"") -> 3.0197018 | I65: not listed | K65: =Rates_data!W63 -> 396.97 | L65: =Rates_data!X63 -> negotiated
A66: Beth Israel Deaconess Medical Center | B66: 95922 | C66: Commercial | D66: BCBS | E66: HMO | F66: =Rates_data!P65 -> 255.23 | G66: =Rates_data!AE65 -> 135.93 | H66: =IF(G66>0,F66/G66,"") -> 1.8776576 | I66: not listed | K66: =Rates_data!W65 -> 255.23 | L66: =Rates_data!X65 -> negotiated
A67: Beth Israel Deaconess Medical Center | B67: 95922 | C67: Commercial | D67: BCBS | E67: PPO | F67: =Rates_data!P66 -> 266.92 | G67: =Rates_data!AE66 -> 135.93 | H67: =IF(G67>0,F67/G67,"") -> 1.9636578 | I67: not listed | K67: =Rates_data!W66 -> 266.92 | L67: =Rates_data!X66 -> negotiated
A68: Beth Israel Deaconess Medical Center | B68: 95922 | C68: Commercial | D68: Harvard Pilgrim Healthcare | E68: Self Insured Non LCU All Commercial Plans | F68: =Rates_data!P67 -> 310.92 | G68: =Rates_data!AE67 -> 135.93 | H68: =IF(G68>0,F68/G68,"") -> 2.2873538 | I68: not listed | K68: =Rates_data!W67 -> 310.92 | L68: =Rates_data!X67 -> negotiated
A69: Beth Israel Deaconess Medical Center | B69: 95923 | C69: Commercial | D69: BCBS | E69: HMO | F69: =Rates_data!P69 -> 255.23 | G69: =Rates_data!AE69 -> 135.93 | H69: =IF(G69>0,F69/G69,"") -> 1.8776576 | I69: not listed | K69: =Rates_data!W69 -> 255.23 | L69: =Rates_data!X69 -> negotiated
A70: Beth Israel Deaconess Medical Center | B70: 95923 | C70: Commercial | D70: BCBS | E70: PPO | F70: =Rates_data!P70 -> 266.92 | G70: =Rates_data!AE70 -> 135.93 | H70: =IF(G70>0,F70/G70,"") -> 1.9636578 | I70: not listed | K70: =Rates_data!W70 -> 266.92 | L70: =Rates_data!X70 -> negotiated
A71: Beth Israel Deaconess Medical Center | B71: 95923 | C71: Commercial | D71: Harvard Pilgrim Healthcare | E71: Self Insured Non LCU All Commercial Plans | F71: =Rates_data!P71 -> 310.92 | G71: =Rates_data!AE71 -> 135.93 | H71: =IF(G71>0,F71/G71,"") -> 2.2873538 | I71: not listed | K71: =Rates_data!W71 -> 310.92 | L71: =Rates_data!X71 -> negotiated
A72: Beth Israel Deaconess Medical Center | B72: 95924 | C72: Commercial | D72: BCBS | E72: HMO | F72: =Rates_data!P73 -> 325.87 | G72: =Rates_data!AE73 -> 220.6 | H72: =IF(G72>0,F72/G72,"") -> 1.4771985 | I72: not listed | K72: =Rates_data!W73 -> 325.87 | L72: =Rates_data!X73 -> negotiated
A73: Beth Israel Deaconess Medical Center | B73: 95924 | C73: Commercial | D73: BCBS | E73: PPO | F73: =Rates_data!P74 -> 340.79 | G73: =Rates_data!AE74 -> 220.6 | H73: =IF(G73>0,F73/G73,"") -> 1.5448323 | I73: not listed | K73: =Rates_data!W74 -> 340.79 | L73: =Rates_data!X74 -> negotiated
A74: Beth Israel Deaconess Medical Center | B74: 95924 | C74: Commercial | D74: Harvard Pilgrim Healthcare | E74: Self Insured Non LCU All Commercial Plans | F74: =Rates_data!P75 -> 396.97 | G74: =Rates_data!AE75 -> 220.6 | H74: =IF(G74>0,F74/G74,"") -> 1.7995014 | I74: not listed | K74: =Rates_data!W75 -> 396.97 | L74: =Rates_data!X75 -> negotiated
A77: B. Battery: approximate total cost (hospital facility + 142.57 physician approximation) / 316.15 independent-site Medicare global
A78: Hospital | B78: Segment | C78: Payer | D78: Plan | E78: Pricing basis | F78: Approx. total battery cost | G78: MPFS global (independent site) | H78: Site-of-service multiple
A79: =IF(Battery!A5="","",Battery!A5) -> Massachusetts General Hospital | B79: =IF(Battery!B5="","",Battery!B5) -> Medicare FFS | C79: =IF(Battery!C5="","",Battery!C5) -> Medicare | D79: =IF(Battery!D5="","",Battery!D5) | E79: =IF(Battery!E5="","",Battery!E5) -> Hospital Medicare FFS row, OPPS packaging applied (95923 = 0) | F79: =Battery!O5 -> 512.38 | G79: =Reference!$D$10 -> 316.15 | H79: =F79/G79 -> 1.6206864
A80: =IF(Battery!A6="","",Battery!A6) -> Massachusetts General Hospital | B80: =IF(Battery!B6="","",Battery!B6) -> Medicare FFS | C80: =IF(Battery!C6="","",Battery!C6) -> Medicare | D80: =IF(Battery!D6="","",Battery!D6) | E80: =IF(Battery!E6="","",Battery!E6) -> Hospital 95924 row + OPPS national 95923 (not listed in file) | F80: =Battery!O6 -> 648.27 | G80: =Reference!$D$10 -> 316.15 | H80: =F80/G80 -> 2.050514
A81: =IF(Battery!A7="","",Battery!A7) -> Massachusetts General Hospital | B81: =IF(Battery!B7="","",Battery!B7) -> Medicare FFS | C81: =IF(Battery!C7="","",Battery!C7) -> Medicare (reference) | D81: =IF(Battery!D7="","",Battery!D7) | E81: =IF(Battery!E7="","",Battery!E7) -> OPPS national (Addendum B), packaging applied (95923 = 0) | F81: =Battery!O7 -> 363.17 | G81: =Reference!$D$10 -> 316.15 | H81: =F81/G81 -> 1.1487269
A82: =IF(Battery!A8="","",Battery!A8) -> Massachusetts General Hospital | B82: =IF(Battery!B8="","",Battery!B8) -> Medicare FFS | C82: =IF(Battery!C8="","",Battery!C8) -> Medicare (reference) | D82: =IF(Battery!D8="","",Battery!D8) | E82: =IF(Battery!E8="","",Battery!E8) -> OPPS national (Addendum B), as listed | F82: =Battery!O8 -> 499.1 | G82: =Reference!$D$10 -> 316.15 | H82: =F82/G82 -> 1.578681
A83: =IF(Battery!A9="","",Battery!A9) -> Massachusetts General Hospital | B83: =IF(Battery!B9="","",Battery!B9) -> Commercial | C83: =IF(Battery!C9="","",Battery!C9) -> AETNA [1001] | D83: =IF(Battery!D9="","",Battery!D9) -> HB AMC AETNA HMO | E83: =IF(Battery!E9="","",Battery!E9) -> Hospital file, same payer/plan | F83: =Battery!O9 -> 2800.1 | G83: =Reference!$D$10 -> 316.15 | H83: =F83/G83 -> 8.8568717
A84: =IF(Battery!A10="","",Battery!A10) -> Massachusetts General Hospital | B84: =IF(Battery!B10="","",Battery!B10) -> Commercial | C84: =IF(Battery!C10="","",Battery!C10) -> CIGNA ALTERNATE [1018] | D84: =IF(Battery!D10="","",Battery!D10) -> HB AMC CIGNA NEW BUSINESS DISCOUNT | E84: =IF(Battery!E10="","",Battery!E10) -> Hospital file, same payer/plan | F84: =Battery!O10 -> 1233.41 | G84: =Reference!$D$10 -> 316.15 | H84: =F84/G84 -> 3.9013443
A85: =IF(Battery!A11="","",Battery!A11) -> Massachusetts General Hospital | B85: =IF(Battery!B11="","",Battery!B11) -> Commercial | C85: =IF(Battery!C11="","",Battery!C11) -> CIGNA [1006] | D85: =IF(Battery!D11="","",Battery!D11) -> HB AMC CIGNA HMO / PPO | E85: =IF(Battery!E11="","",Battery!E11) -> Hospital file, same payer/plan | F85: =Battery!O11 -> 1768.51 | G85: =Reference!$D$10 -> 316.15 | H85: =F85/G85 -> 5.5938953
A86: =IF(Battery!A12="","",Battery!A12) -> Massachusetts General Hospital | B86: =IF(Battery!B12="","",Battery!B12) -> Commercial | C86: =IF(Battery!C12="","",Battery!C12) -> INTERNATIONAL COMMERCIAL [140001] | D86: =IF(Battery!D12="","",Battery!D12) -> HB AMC / MEE / PCC / ONE TEAM HEALTH INTERNATIONAL | E86: =IF(Battery!E12="","",Battery!E12) -> Hospital file, same payer/plan | F86: =Battery!O12 -> 1485.47 | G86: =Reference!$D$10 -> 316.15 | H86: =F86/G86 -> 4.6986241
A87: =IF(Battery!A13="","",Battery!A13) -> Massachusetts General Hospital | B87: =IF(Battery!B13="","",Battery!B13) -> Commercial | C87: =IF(Battery!C13="","",Battery!C13) -> MGB HEALTH PLAN [150001] | D87: =IF(Battery!D13="","",Battery!D13) -> HB AMC MGBHP COMMERCIAL HMO | E87: =IF(Battery!E13="","",Battery!E13) -> Hospital file, same payer/plan | F87: =Battery!O13 -> 913.19 | G87: =Reference!$D$10 -> 316.15 | H87: =F87/G87 -> 2.8884707
A88: =IF(Battery!A14="","",Battery!A14) -> Massachusetts General Hospital | B88: =IF(Battery!B14="","",Battery!B14) -> Commercial | C88: =IF(Battery!C14="","",Battery!C14) -> MGB HEALTH PLAN [150001] | D88: =IF(Battery!D14="","",Battery!D14) -> HB AMC MGBHP COMMERCIAL PPO | E88: =IF(Battery!E14="","",Battery!E14) -> Hospital file, same payer/plan | F88: =Battery!O14 -> 950.37 | G88: =Reference!$D$10 -> 316.15 | H88: =F88/G88 -> 3.0060731
A89: =IF(Battery!A15="","",Battery!A15) -> Massachusetts General Hospital | B89: =IF(Battery!B15="","",Battery!B15) -> Commercial | C89: =IF(Battery!C15="","",Battery!C15) -> UNITED HEALTHCARE [1016] | D89: =IF(Battery!D15="","",Battery!D15) -> HB AMC CH UNITED NEW BUSINESS DISCOUNT | E89: =IF(Battery!E15="","",Battery!E15) -> Hospital file, same payer/plan | F89: =Battery!O15 -> 1794.13 | G89: =Reference!$D$10 -> 316.15 | H89: =F89/G89 -> 5.6749328
A90: =IF(Battery!A16="","",Battery!A16) -> Massachusetts General Hospital | B90: =IF(Battery!B16="","",Battery!B16) -> Commercial | C90: =IF(Battery!C16="","",Battery!C16) -> UNITED HEALTHCARE [1016] | D90: =IF(Battery!D16="","",Battery!D16) -> HB AMC UNITED PPO / POS | E90: =IF(Battery!E16="","",Battery!E16) -> Hospital file, same payer/plan | F90: =Battery!O16 -> 1794.13 | G90: =Reference!$D$10 -> 316.15 | H90: =F90/G90 -> 5.6749328
... A107: =IF(Battery!A33="","",Battery!A33) -> Beth Israel Deaconess Medical Center | B107: =IF(Battery!B33="","",Battery!B33) -> Commercial | C107: =IF(Battery!C33="","",Battery!C33) -> Harvard Pilgrim Healthcare | D107: =IF(Battery!D33="","",Battery!D33) -> Self Insured Non LCU All Commercial Plans | E107: =IF(Battery!E33="","",Battery!E33) -> Hospital file, same payer/plan | F107: =Battery!O33 -> 850.46 | G107: =Reference!$D$10 -> 316.15 | H107: =F107/G107 -> 2.6900522

Sheet Focus_payers
A1: Focus payers — all included rows
A2: MassHealth managed care: only Commonwealth Care Alliance (One Care / SCO dual plans) appears; no MassHealth ACO or WellSense rows exist for these codes in any file.
A4: Focus group | B4: Hospital | C4: Code | D4: Segment | E4: Payer | F4: Plan | G4: Setting | H4: Methodology | I4: Negotiated / implied $ | J4: Percentage of charges | K4: Median allowed | L4: 10th pct allowed | M4: 90th pct allowed | N4: Allowed count | O4: Headline rate | P4: Headline basis | Q4: Medicare comparator | R4: Multiple of comparator
A5: Blue Cross Blue Shield of Massachusetts | B5: Beth Israel Deaconess Medical Center | C5: 93660 | D5: Commercial | E5: BCBS | F5: HMO | G5: outpatient | H5: fee schedule | I5: =IF(Rates_data!P56="","",Rates_data!P56) -> 1091.24 | J5: =IF(Rates_data!O56="","",Rates_data!O56) | K5: =IF(Rates_data!S56="","",Rates_data!S56) | L5: =IF(Rates_data!T56="","",Rates_data!T56) | M5: =IF(Rates_data!U56="","",Rates_data!U56) | N5: =IF(Rates_data!V56="","",Rates_data!V56) | O5: =IF(Rates_data!W56="","",Rates_data!W56) -> 1091.24 | P5: =IF(Rates_data!X56="","",Rates_data!X56) -> negotiated | Q5: =IF(Rates_data!AA56="","",Rates_data!AA56) -> 381.24 | R5: =IF(Rates_data!AC56="","",Rates_data!AC56) -> 2.8623439
A6: Blue Cross Blue Shield of Massachusetts | B6: Beth Israel Deaconess Medical Center | C6: 93660 | D6: Commercial | E6: BCBS | F6: PPO | G6: outpatient | H6: fee schedule | I6: =IF(Rates_data!P57="","",Rates_data!P57) -> 1141.22 | J6: =IF(Rates_data!O57="","",Rates_data!O57) | K6: =IF(Rates_data!S57="","",Rates_data!S57) | L6: =IF(Rates_data!T57="","",Rates_data!T57) | M6: =IF(Rates_data!U57="","",Rates_data!U57) | N6: =IF(Rates_data!V57="","",Rates_data!V57) | O6: =IF(Rates_data!W57="","",Rates_data!W57) -> 1141.22 | P6: =IF(Rates_data!X57="","",Rates_data!X57) -> negotiated | Q6: =IF(Rates_data!AA57="","",Rates_data!AA57) -> 381.24 | R6: =IF(Rates_data!AC57="","",Rates_data!AC57) -> 2.9934425
A7: Blue Cross Blue Shield of Massachusetts | B7: Beth Israel Deaconess Medical Center | C7: 95921 | D7: Commercial | E7: BCBS | F7: HMO | G7: outpatient | H7: fee schedule | I7: =IF(Rates_data!P61="","",Rates_data!P61) -> 325.87 | J7: =IF(Rates_data!O61="","",Rates_data!O61) | K7: =IF(Rates_data!S61="","",Rates_data!S61) | L7: =IF(Rates_data!T61="","",Rates_data!T61) | M7: =IF(Rates_data!U61="","",Rates_data!U61) | N7: =IF(Rates_data!V61="","",Rates_data!V61) | O7: =IF(Rates_data!W61="","",Rates_data!W61) -> 325.87 | P7: =IF(Rates_data!X61="","",Rates_data!X61) -> negotiated | Q7: =IF(Rates_data!AA61="","",Rates_data!AA61) -> 131.46 | R7: =IF(Rates_data!AC61="","",Rates_data!AC61) -> 2.4788529
A8: Blue Cross Blue Shield of Massachusetts | B8: Beth Israel Deaconess Medical Center | C8: 95921 | D8: Commercial | E8: BCBS | F8: PPO | G8: outpatient | H8: fee schedule | I8: =IF(Rates_data!P62="","",Rates_data!P62) -> 340.79 | J8: =IF(Rates_data!O62="","",Rates_data!O62) | K8: =IF(Rates_data!S62="","",Rates_data!S62) | L8: =IF(Rates_data!T62="","",Rates_data!T62) | M8: =IF(Rates_data!U62="","",Rates_data!U62) | N8: =IF(Rates_data!V62="","",Rates_data!V62) | O8: =IF(Rates_data!W62="","",Rates_data!W62) -> 340.79 | P8: =IF(Rates_data!X62="","",Rates_data!X62) -> negotiated | Q8: =IF(Rates_data!AA62="","",Rates_data!AA62) -> 131.46 | R8: =IF(Rates_data!AC62="","",Rates_data!AC62) -> 2.5923475
A9: Blue Cross Blue Shield of Massachusetts | B9: Beth Israel Deaconess Medical Center | C9: 95922 | D9: Commercial | E9: BCBS | F9: HMO | G9: outpatient | H9: fee schedule | I9: =IF(Rates_data!P65="","",Rates_data!P65) -> 255.23 | J9: =IF(Rates_data!O65="","",Rates_data!O65) | K9: =IF(Rates_data!S65="","",Rates_data!S65) | L9: =IF(Rates_data!T65="","",Rates_data!T65) | M9: =IF(Rates_data!U65="","",Rates_data!U65) | N9: =IF(Rates_data!V65="","",Rates_data!V65) | O9: =IF(Rates_data!W65="","",Rates_data!W65) -> 255.23 | P9: =IF(Rates_data!X65="","",Rates_data!X65) -> negotiated | Q9: =IF(Rates_data!AA65="","",Rates_data!AA65) -> 135.93 | R9: =IF(Rates_data!AC65="","",Rates_data!AC65) -> 1.8776576
A10: Blue Cross Blue Shield of Massachusetts | B10: Beth Israel Deaconess Medical Center | C10: 95922 | D10: Commercial | E10: BCBS | F10: PPO | G10: outpatient | H10: fee schedule | I10: =IF(Rates_data!P66="","",Rates_data!P66) -> 266.92 | J10: =IF(Rates_data!O66="","",Rates_data!O66) | K10: =IF(Rates_data!S66="","",Rates_data!S66) | L10: =IF(Rates_data!T66="","",Rates_data!T66) | M10: =IF(Rates_data!U66="","",Rates_data!U66) | N10: =IF(Rates_data!V66="","",Rates_data!V66) | O10: =IF(Rates_data!W66="","",Rates_data!W66) -> 266.92 | P10: =IF(Rates_data!X66="","",Rates_data!X66) -> negotiated | Q10: =IF(Rates_data!AA66="","",Rates_data!AA66) -> 135.93 | R10: =IF(Rates_data!AC66="","",Rates_data!AC66) -> 1.9636578
A11: Blue Cross Blue Shield of Massachusetts | B11: Beth Israel Deaconess Medical Center | C11: 95923 | D11: Commercial | E11: BCBS | F11: HMO | G11: outpatient | H11: fee schedule | I11: =IF(Rates_data!P69="","",Rates_data!P69) -> 255.23 | J11: =IF(Rates_data!O69="","",Rates_data!O69) | K11: =IF(Rates_data!S69="","",Rates_data!S69) | L11: =IF(Rates_data!T69="","",Rates_data!T69) | M11: =IF(Rates_data!U69="","",Rates_data!U69) | N11: =IF(Rates_data!V69="","",Rates_data!V69) | O11: =IF(Rates_data!W69="","",Rates_data!W69) -> 255.23 | P11: =IF(Rates_data!X69="","",Rates_data!X69) -> negotiated | Q11: =IF(Rates_data!AA69="","",Rates_data!AA69) -> 135.93 | R11: =IF(Rates_data!AC69="","",Rates_data!AC69) -> 1.8776576
A12: Blue Cross Blue Shield of Massachusetts | B12: Beth Israel Deaconess Medical Center | C12: 95923 | D12: Commercial | E12: BCBS | F12: PPO | G12: outpatient | H12: fee schedule | I12: =IF(Rates_data!P70="","",Rates_data!P70) -> 266.92 | J12: =IF(Rates_data!O70="","",Rates_data!O70) | K12: =IF(Rates_data!S70="","",Rates_data!S70) | L12: =IF(Rates_data!T70="","",Rates_data!T70) | M12: =IF(Rates_data!U70="","",Rates_data!U70) | N12: =IF(Rates_data!V70="","",Rates_data!V70) | O12: =IF(Rates_data!W70="","",Rates_data!W70) -> 266.92 | P12: =IF(Rates_data!X70="","",Rates_data!X70) -> negotiated | Q12: =IF(Rates_data!AA70="","",Rates_data!AA70) -> 135.93 | R12: =IF(Rates_data!AC70="","",Rates_data!AC70) -> 1.9636578
A13: Blue Cross Blue Shield of Massachusetts | B13: Beth Israel Deaconess Medical Center | C13: 95924 | D13: Commercial | E13: BCBS | F13: HMO | G13: outpatient | H13: fee schedule | I13: =IF(Rates_data!P73="","",Rates_data!P73) -> 325.87 | J13: =IF(Rates_data!O73="","",Rates_data!O73) | K13: =IF(Rates_data!S73="","",Rates_data!S73) | L13: =IF(Rates_data!T73="","",Rates_data!T73) | M13: =IF(Rates_data!U73="","",Rates_data!U73) | N13: =IF(Rates_data!V73="","",Rates_data!V73) | O13: =IF(Rates_data!W73="","",Rates_data!W73) -> 325.87 | P13: =IF(Rates_data!X73="","",Rates_data!X73) -> negotiated | Q13: =IF(Rates_data!AA73="","",Rates_data!AA73) -> 220.6 | R13: =IF(Rates_data!AC73="","",Rates_data!AC73) -> 1.4771985
A14: Blue Cross Blue Shield of Massachusetts | B14: Beth Israel Deaconess Medical Center | C14: 95924 | D14: Commercial | E14: BCBS | F14: PPO | G14: outpatient | H14: fee schedule | I14: =IF(Rates_data!P74="","",Rates_data!P74) -> 340.79 | J14: =IF(Rates_data!O74="","",Rates_data!O74) | K14: =IF(Rates_data!S74="","",Rates_data!S74) | L14: =IF(Rates_data!T74="","",Rates_data!T74) | M14: =IF(Rates_data!U74="","",Rates_data!U74) | N14: =IF(Rates_data!V74="","",Rates_data!V74) | O14: =IF(Rates_data!W74="","",Rates_data!W74) -> 340.79 | P14: =IF(Rates_data!X74="","",Rates_data!X74) -> negotiated | Q14: =IF(Rates_data!AA74="","",Rates_data!AA74) -> 220.6 | R14: =IF(Rates_data!AC74="","",Rates_data!AC74) -> 1.5448323
A15: Harvard Pilgrim / Point32Health | B15: Beth Israel Deaconess Medical Center | C15: 93660 | D15: Commercial | E15: Harvard Pilgrim Healthcare | F15: Self Insured Non LCU All Commercial Plans | G15: outpatient | H15: fee schedule | I15: =IF(Rates_data!P58="","",Rates_data!P58) -> 1329.39 | J15: =IF(Rates_data!O58="","",Rates_data!O58) | K15: =IF(Rates_data!S58="","",Rates_data!S58) | L15: =IF(Rates_data!T58="","",Rates_data!T58) | M15: =IF(Rates_data!U58="","",Rates_data!U58) | N15: =IF(Rates_data!V58="","",Rates_data!V58) | O15: =IF(Rates_data!W58="","",Rates_data!W58) -> 1329.39 | P15: =IF(Rates_data!X58="","",Rates_data!X58) -> negotiated | Q15: =IF(Rates_data!AA58="","",Rates_data!AA58) -> 381.24 | R15: =IF(Rates_data!AC58="","",Rates_data!AC58) -> 3.4870161
A16: Harvard Pilgrim / Point32Health | B16: Beth Israel Deaconess Medical Center | C16: 95921 | D16: Commercial | E16: Harvard Pilgrim Healthcare | F16: Self Insured Non LCU All Commercial Plans | G16: outpatient | H16: fee schedule | I16: =IF(Rates_data!P63="","",Rates_data!P63) -> 396.97 | J16: =IF(Rates_data!O63="","",Rates_data!O63) | K16: =IF(Rates_data!S63="","",Rates_data!S63) | L16: =IF(Rates_data!T63="","",Rates_data!T63) | M16: =IF(Rates_data!U63="","",Rates_data!U63) | N16: =IF(Rates_data!V63="","",Rates_data!V63) | O16: =IF(Rates_data!W63="","",Rates_data!W63) -> 396.97 | P16: =IF(Rates_data!X63="","",Rates_data!X63) -> negotiated | Q16: =IF(Rates_data!AA63="","",Rates_data!AA63) -> 131.46 | R16: =IF(Rates_data!AC63="","",Rates_data!AC63) -> 3.0197018
A17: Harvard Pilgrim / Point32Health | B17: Beth Israel Deaconess Medical Center | C17: 95922 | D17: Commercial | E17: Harvard Pilgrim Healthcare | F17: Self Insured Non LCU All Commercial Plans | G17: outpatient | H17: fee schedule | I17: =IF(Rates_data!P67="","",Rates_data!P67) -> 310.92 | J17: =IF(Rates_data!O67="","",Rates_data!O67) | K17: =IF(Rates_data!S67="","",Rates_data!S67) | L17: =IF(Rates_data!T67="","",Rates_data!T67) | M17: =IF(Rates_data!U67="","",Rates_data!U67) | N17: =IF(Rates_data!V67="","",Rates_data!V67) | O17: =IF(Rates_data!W67="","",Rates_data!W67) -> 310.92 | P17: =IF(Rates_data!X67="","",Rates_data!X67) -> negotiated | Q17: =IF(Rates_data!AA67="","",Rates_data!AA67) -> 135.93 | R17: =IF(Rates_data!AC67="","",Rates_data!AC67) -> 2.2873538
A18: Harvard Pilgrim / Point32Health | B18: Beth Israel Deaconess Medical Center | C18: 95923 | D18: Commercial | E18: Harvard Pilgrim Healthcare | F18: Self Insured Non LCU All Commercial Plans | G18: outpatient | H18: fee schedule | I18: =IF(Rates_data!P71="","",Rates_data!P71) -> 310.92 | J18: =IF(Rates_data!O71="","",Rates_data!O71) | K18: =IF(Rates_data!S71="","",Rates_data!S71) | L18: =IF(Rates_data!T71="","",Rates_data!T71) | M18: =IF(Rates_data!U71="","",Rates_data!U71) | N18: =IF(Rates_data!V71="","",Rates_data!V71) | O18: =IF(Rates_data!W71="","",Rates_data!W71) -> 310.92 | P18: =IF(Rates_data!X71="","",Rates_data!X71) -> negotiated | Q18: =IF(Rates_data!AA71="","",Rates_data!AA71) -> 135.93 | R18: =IF(Rates_data!AC71="","",Rates_data!AC71) -> 2.2873538
A19: Harvard Pilgrim / Point32Health | B19: Beth Israel Deaconess Medical Center | C19: 95924 | D19: Commercial | E19: Harvard Pilgrim Healthcare | F19: Self Insured Non LCU All Commercial Plans | G19: outpatient | H19: fee schedule | I19: =IF(Rates_data!P75="","",Rates_data!P75) -> 396.97 | J19: =IF(Rates_data!O75="","",Rates_data!O75) | K19: =IF(Rates_data!S75="","",Rates_data!S75) | L19: =IF(Rates_data!T75="","",Rates_data!T75) | M19: =IF(Rates_data!U75="","",Rates_data!U75) | N19: =IF(Rates_data!V75="","",Rates_data!V75) | O19: =IF(Rates_data!W75="","",Rates_data!W75) -> 396.97 | P19: =IF(Rates_data!X75="","",Rates_data!X75) -> negotiated | Q19: =IF(Rates_data!AA75="","",Rates_data!AA75) -> 220.6 | R19: =IF(Rates_data!AC75="","",Rates_data!AC75) -> 1.7995014
A20: Tufts Health Plan | B20: not listed at any hospital for these codes
A21: Mass General Brigham Health Plan | B21: Massachusetts General Hospital | C21: 95923 | D21: Commercial | E21: MGB HEALTH PLAN [150001] | F21: HB AMC MGBHP COMMERCIAL HMO | G21: both | H21: percent of total billed charges | I21: =IF(Rates_data!P7="","",Rates_data!P7) -> 358.8 | J21: =IF(Rates_data!O7="","",Rates_data!O7) -> 36.5 | K21: =IF(Rates_data!S7="","",Rates_data!S7) -> 355.47 | L21: =IF(Rates_data!T7="","",Rates_data!T7) -> 302.1 | M21: =IF(Rates_data!U7="","",Rates_data!U7) -> 355.47 | N21: =IF(Rates_data!V7="","",Rates_data!V7) -> 13 | O21: =IF(Rates_data!W7="","",Rates_data!W7) -> 355.47 | P21: =IF(Rates_data!X7="","",Rates_data!X7) -> median allowed | Q21: =IF(Rates_data!AA7="","",Rates_data!AA7) -> 135.93 | R21: =IF(Rates_data!AC7="","",Rates_data!AC7) -> 2.6395939
A22: Mass General Brigham Health Plan | B22: Massachusetts General Hospital | C22: 95923 | D22: Commercial | E22: MGB HEALTH PLAN [150001] | F22: HB AMC MGBHP COMMERCIAL PPO | G22: both | H22: percent of total billed charges | I22: =IF(Rates_data!P8="","",Rates_data!P8) -> 376.49 | J22: =IF(Rates_data!O8="","",Rates_data!O8) -> 38.3 | K22: =IF(Rates_data!S8="","",Rates_data!S8) -> 372.62 | L22: =IF(Rates_data!T8="","",Rates_data!T8) -> 372.62 | M22: =IF(Rates_data!U8="","",Rates_data!U8) -> 372.62 | N22: =IF(Rates_data!V8="","",Rates_data!V8) -> 36 | O22: =IF(Rates_data!W8="","",Rates_data!W8) -> 372.62 | P22: =IF(Rates_data!X8="","",Rates_data!X8) -> median allowed | Q22: =IF(Rates_data!AA8="","",Rates_data!AA8) -> 135.93 | R22: =IF(Rates_data!AC8="","",Rates_data!AC8) -> 2.7697344
A23: Mass General Brigham Health Plan | B23: Massachusetts General Hospital | C23: 95924 | D23: Commercial | E23: MGB HEALTH PLAN [150001] | F23: HB AMC MGBHP COMMERCIAL HMO | G23: both | H23: percent of total billed charges | I23: =IF(Rates_data!P16="","",Rates_data!P16) -> 419.02 | J23: =IF(Rates_data!O16="","",Rates_data!O16) -> 36.5 | K23: =IF(Rates_data!S16="","",Rates_data!S16) -> 415.15 | L23: =IF(Rates_data!T16="","",Rates_data!T16) -> 352.82 | M23: =IF(Rates_data!U16="","",Rates_data!U16) -> 415.15 | N23: =IF(Rates_data!V16="","",Rates_data!V16) -> 13 | O23: =IF(Rates_data!W16="","",Rates_data!W16) -> 415.15 | P23: =IF(Rates_data!X16="","",Rates_data!X16) -> median allowed | Q23: =IF(Rates_data!AA16="","",Rates_data!AA16) -> 369.77 | R23: =IF(Rates_data!AC16="","",Rates_data!AC16) -> 1.1331909
A24: Mass General Brigham Health Plan | B24: Massachusetts General Hospital | C24: 95924 | D24: Commercial | E24: MGB HEALTH PLAN [150001] | F24: HB AMC MGBHP COMMERCIAL PPO | G24: both | H24: percent of total billed charges | I24: =IF(Rates_data!P17="","",Rates_data!P17) -> 439.68 | J24: =IF(Rates_data!O17="","",Rates_data!O17) -> 38.3 | K24: =IF(Rates_data!S17="","",Rates_data!S17) -> 435.18 | L24: =IF(Rates_data!T17="","",Rates_data!T17) -> 435.18 | M24: =IF(Rates_data!U17="","",Rates_data!U17) -> 435.18 | N24: =IF(Rates_data!V17="","",Rates_data!V17) -> 36 | O24: =IF(Rates_data!W17="","",Rates_data!W17) -> 435.18 | P24: =IF(Rates_data!X17="","",Rates_data!X17) -> median allowed | Q24: =IF(Rates_data!AA17="","",Rates_data!AA17) -> 369.77 | R24: =IF(Rates_data!AC17="","",Rates_data!AC17) -> 1.1890635
A25: UnitedHealthcare | B25: Massachusetts General Hospital | C25: 95921 | D25: Commercial | E25: UNITED HEALTHCARE [1016] | F25: HB AMC UNITED PPO / POS | G25: outpatient | H25: percent of total billed charges | I25: =IF(Rates_data!P2="","",Rates_data!P2) -> 500.13 | J25: =IF(Rates_data!O2="","",Rates_data!O2) -> 81.72 | K25: =IF(Rates_data!S2="","",Rates_data!S2) -> 474.04 | L25: =IF(Rates_data!T2="","",Rates_data!T2) -> 474.04 | M25: =IF(Rates_data!U2="","",Rates_data!U2) -> 474.04 | N25: =IF(Rates_data!V2="","",Rates_data!V2) -> 1 through 10 | O25: =IF(Rates_data!W2="","",Rates_data!W2) -> 474.04 | P25: =IF(Rates_data!X2="","",Rates_data!X2) -> median allowed | Q25: =IF(Rates_data!AA2="","",Rates_data!AA2) -> 131.46 | R25: =IF(Rates_data!AC2="","",Rates_data!AC2) -> 3.8044272
A26: UnitedHealthcare | B26: Massachusetts General Hospital | C26: 95923 | D26: Commercial | E26: UNITED HEALTHCARE [1016] | F26: HB AMC CH UNITED NEW BUSINESS DISCOUNT | G26: both | H26: percent of total billed charges | I26: =IF(Rates_data!P9="","",Rates_data!P9) -> 421.71 | J26: =IF(Rates_data!O9="","",Rates_data!O9) -> 42.9 | K26: =IF(Rates_data!S9="","",Rates_data!S9) -> 761.83 | L26: =IF(Rates_data!T9="","",Rates_data!T9) -> 761.83 | M26: =IF(Rates_data!U9="","",Rates_data!U9) -> 761.83 | N26: =IF(Rates_data!V9="","",Rates_data!V9) -> 1 through 10 | O26: =IF(Rates_data!W9="","",Rates_data!W9) -> 761.83 | P26: =IF(Rates_data!X9="","",Rates_data!X9) -> median allowed | Q26: =IF(Rates_data!AA9="","",Rates_data!AA9) -> 135.93 | R26: =IF(Rates_data!AC9="","",Rates_data!AC9) -> 3.1024056
A27: UnitedHealthcare | B27: Massachusetts General Hospital | C27: 95923 | D27: Commercial | E27: UNITED HEALTHCARE [1016] | F27: HB AMC UNITED PPO / POS | G27: outpatient | H27: percent of total billed charges | I27: =IF(Rates_data!P10="","",Rates_data!P10) -> 803.31 | J27: =IF(Rates_data!O10="","",Rates_data!O10) -> 81.72 | K27: =IF(Rates_data!S10="","",Rates_data!S10) -> 761.83 | L27: =IF(Rates_data!T10="","",Rates_data!T10) -> 761.83 | M27: =IF(Rates_data!U10="","",Rates_data!U10) -> 1212.81 | N27: =IF(Rates_data!V10="","",Rates_data!V10) -> 18 | O27: =IF(Rates_data!W10="","",Rates_data!W10) -> 761.83 | P27: =IF(Rates_data!X10="","",Rates_data!X10) -> median allowed | Q27: =IF(Rates_data!AA10="","",Rates_data!AA10) -> 135.93 | R27: =IF(Rates_data!AC10="","",Rates_data!AC10) -> 5.909733
A28: UnitedHealthcare | B28: Massachusetts General Hospital | C28: 95924 | D28: Commercial | E28: UNITED HEALTHCARE [1016] | F28: HB AMC CH UNITED NEW BUSINESS DISCOUNT | G28: both | H28: percent of total billed charges | I28: =IF(Rates_data!P18="","",Rates_data!P18) -> 492.49 | J28: =IF(Rates_data!O18="","",Rates_data!O18) -> 42.9 | K28: =IF(Rates_data!S18="","",Rates_data!S18) -> 889.73 | L28: =IF(Rates_data!T18="","",Rates_data!T18) -> 889.73 | M28: =IF(Rates_data!U18="","",Rates_data!U18) -> 889.73 | N28: =IF(Rates_data!V18="","",Rates_data!V18) -> 1 through 10 | O28: =IF(Rates_data!W18="","",Rates_data!W18) -> 889.73 | P28: =IF(Rates_data!X18="","",Rates_data!X18) -> median allowed | Q28: =IF(Rates_data!AA18="","",Rates_data!AA18) -> 369.77 | R28: =IF(Rates_data!AC18="","",Rates_data!AC18) -> 1.331882
A29: UnitedHealthcare | B29: Massachusetts General Hospital | C29: 95924 | D29: Commercial | E29: UNITED HEALTHCARE [1016] | F29: HB AMC UNITED PPO / POS | G29: outpatient | H29: percent of total billed charges | I29: =IF(Rates_data!P19="","",Rates_data!P19) -> 938.15 | J29: =IF(Rates_data!O19="","",Rates_data!O19) -> 81.72 | K29: =IF(Rates_data!S19="","",Rates_data!S19) -> 889.73 | L29: =IF(Rates_data!T19="","",Rates_data!T19) -> 889.73 | M29: =IF(Rates_data!U19="","",Rates_data!U19) -> 1444.72 | N29: =IF(Rates_data!V19="","",Rates_data!V19) -> 17 | O29: =IF(Rates_data!W19="","",Rates_data!W19) -> 889.73 | P29: =IF(Rates_data!X19="","",Rates_data!X19) -> median allowed | Q29: =IF(Rates_data!AA19="","",Rates_data!AA19) -> 369.77 | R29: =IF(Rates_data!AC19="","",Rates_data!AC19) -> 2.5371177
A30: UnitedHealthcare | B30: Brigham and Women's Faulkner Hospital | C30: 95921 | D30: Commercial | E30: UNITED HEALTHCARE [1016] | F30: HB CH UNITED HMO / PPO / INDEMNITY | G30: outpatient | H30: percent of total billed charges | I30: =IF(Rates_data!P30="","",Rates_data!P30) -> 338.12 | J30: =IF(Rates_data!O30="","",Rates_data!O30) -> 78.45 | K30: =IF(Rates_data!S30="","",Rates_data!S30) -> 322.13 | L30: =IF(Rates_data!T30="","",Rates_data!T30) -> 322.13 | M30: =IF(Rates_data!U30="","",Rates_data!U30) -> 322.13 | N30: =IF(Rates_data!V30="","",Rates_data!V30) -> 1 through 10 | O30: =IF(Rates_data!W30="","",Rates_data!W30) -> 322.13 | P30: =IF(Rates_data!X30="","",Rates_data!X30) -> median allowed | Q30: =IF(Rates_data!AA30="","",Rates_data!AA30) -> 185.81 | R30: =IF(Rates_data!AC30="","",Rates_data!AC30) -> 1.8197083
A31: UnitedHealthcare | B31: Brigham and Women's Faulkner Hospital | C31: 95923 | D31: Commercial | E31: UNITED HEALTHCARE [1016] | F31: HB AMC CH UNITED NEW BUSINESS DISCOUNT | G31: outpatient | H31: percent of total billed charges | I31: =IF(Rates_data!P35="","",Rates_data!P35) -> 309.37 | J31: =IF(Rates_data!O35="","",Rates_data!O35) -> 44.45 | K31: =IF(Rates_data!S35="","",Rates_data!S35) -> 308.44 | L31: =IF(Rates_data!T35="","",Rates_data!T35) -> 308.44 | M31: =IF(Rates_data!U35="","",Rates_data!U35) -> 308.44 | N31: =IF(Rates_data!V35="","",Rates_data!V35) -> 1 through 10 | O31: =IF(Rates_data!W35="","",Rates_data!W35) -> 308.44 | P31: =IF(Rates_data!X35="","",Rates_data!X35) -> median allowed | Q31: =IF(Rates_data!AA35="","",Rates_data!AA35) -> 153.08 | R31: =IF(Rates_data!AC35="","",Rates_data!AC35) -> 2.0209694
A32: UnitedHealthcare | B32: Brigham and Women's Faulkner Hospital | C32: 95923 | D32: Commercial | E32: UNITED HEALTHCARE [1016] | F32: HB CH UNITED HMO / PPO / INDEMNITY | G32: outpatient | H32: percent of total billed charges | I32: =IF(Rates_data!P36="","",Rates_data!P36) -> 546.01 | J32: =IF(Rates_data!O36="","",Rates_data!O36) -> 78.45 | K32: =IF(Rates_data!S36="","",Rates_data!S36) -> 520.48 | L32: =IF(Rates_data!T36="","",Rates_data!T36) -> 308.44 | M32: =IF(Rates_data!U36="","",Rates_data!U36) -> 520.48 | N32: =IF(Rates_data!V36="","",Rates_data!V36) -> 22 | O32: =IF(Rates_data!W36="","",Rates_data!W36) -> 520.48 | P32: =IF(Rates_data!X36="","",Rates_data!X36) -> median allowed | Q32: =IF(Rates_data!AA36="","",Rates_data!AA36) -> 153.08 | R32: =IF(Rates_data!AC36="","",Rates_data!AC36) -> 3.5668278
A33: UnitedHealthcare | B33: Brigham and Women's Faulkner Hospital | C33: 95924 | D33: Commercial | E33: UNITED HEALTHCARE [1016] | F33: HB AMC CH UNITED NEW BUSINESS DISCOUNT | G33: outpatient | H33: percent of total billed charges | I33: =IF(Rates_data!P43="","",Rates_data!P43) -> 359.6 | J33: =IF(Rates_data!O43="","",Rates_data!O43) -> 44.45 | K33: =IF(Rates_data!S43="","",Rates_data!S43) -> 358.56 | L33: =IF(Rates_data!T43="","",Rates_data!T43) -> 358.56 | M33: =IF(Rates_data!U43="","",Rates_data!U43) -> 358.56 | N33: =IF(Rates_data!V43="","",Rates_data!V43) -> 1 through 10 | O33: =IF(Rates_data!W43="","",Rates_data!W43) -> 358.56 | P33: =IF(Rates_data!X43="","",Rates_data!X43) -> median allowed | Q33: =IF(Rates_data!AA43="","",Rates_data!AA43) -> 369.81 | R33: =IF(Rates_data!AC43="","",Rates_data!AC43) -> 0.97239123
A34: UnitedHealthcare | B34: Brigham and Women's Faulkner Hospital | C34: 95924 | D34: Commercial | E34: UNITED HEALTHCARE [1016] | F34: HB CH UNITED HMO / PPO / INDEMNITY | G34: outpatient | H34: percent of total billed charges | I34: =IF(Rates_data!P44="","",Rates_data!P44) -> 634.66 | J34: =IF(Rates_data!O44="","",Rates_data!O44) -> 78.45 | K34: =IF(Rates_data!S44="","",Rates_data!S44) -> 605.05 | L34: =IF(Rates_data!T44="","",Rates_data!T44) -> 358.56 | M34: =IF(Rates_data!U44="","",Rates_data!U44) -> 605.05 | N34: =IF(Rates_data!V44="","",Rates_data!V44) -> 21 | O34: =IF(Rates_data!W44="","",Rates_data!W44) -> 605.05 | P34: =IF(Rates_data!X44="","",Rates_data!X44) -> median allowed | Q34: =IF(Rates_data!AA44="","",Rates_data!AA44) -> 369.81 | R34: =IF(Rates_data!AC44="","",Rates_data!AC44) -> 1.7161786
A35: Aetna | B35: Massachusetts General Hospital | C35: 95923 | D35: Commercial | E35: AETNA [1001] | F35: HB AMC AETNA HMO | G35: outpatient | H35: percent of total billed charges | I35: =IF(Rates_data!P3="","",Rates_data!P3) -> 686.13 | J35: =IF(Rates_data!O3="","",Rates_data!O3) -> 69.8 | K35: =IF(Rates_data!S3="","",Rates_data!S3) -> 1212.81 | L35: =IF(Rates_data!T3="","",Rates_data!T3) -> 645.18 | M35: =IF(Rates_data!U3="","",Rates_data!U3) -> 1212.81 | N35: =IF(Rates_data!V3="","",Rates_data!V3) -> 1 through 10 | O35: =IF(Rates_data!W3="","",Rates_data!W3) -> 1212.81 | P35: =IF(Rates_data!X3="","",Rates_data!X3) -> median allowed | Q35: =IF(Rates_data!AA3="","",Rates_data!AA3) -> 135.93 | R35: =IF(Rates_data!AC3="","",Rates_data!AC3) -> 5.0476716
A36: Aetna | B36: Massachusetts General Hospital | C36: 95924 | D36: Commercial | E36: AETNA [1001] | F36: HB AMC AETNA HMO | G36: outpatient | H36: percent of total billed charges | I36: =IF(Rates_data!P12="","",Rates_data!P12) -> 801.3 | J36: =IF(Rates_data!O12="","",Rates_data!O12) -> 69.8 | K36: =IF(Rates_data!S12="","",Rates_data!S12) -> 1444.72 | L36: =IF(Rates_data!T12="","",Rates_data!T12) -> 753.5 | M36: =IF(Rates_data!U12="","",Rates_data!U12) -> 1444.72 | N36: =IF(Rates_data!V12="","",Rates_data!V12) -> 1 through 10 | O36: =IF(Rates_data!W12="","",Rates_data!W12) -> 1444.72 | P36: =IF(Rates_data!X12="","",Rates_data!X12) -> median allowed | Q36: =IF(Rates_data!AA12="","",Rates_data!AA12) -> 369.77 | R36: =IF(Rates_data!AC12="","",Rates_data!AC12) -> 2.1670227
A37: Cigna | B37: Massachusetts General Hospital | C37: 95923 | D37: Commercial | E37: CIGNA ALTERNATE [1018] | F37: HB AMC CIGNA NEW BUSINESS DISCOUNT | G37: both | H37: percent of total billed charges | I37: =IF(Rates_data!P4="","",Rates_data!P4) -> 523.94 | J37: =IF(Rates_data!O4="","",Rates_data!O4) -> 53.3 | K37: =IF(Rates_data!S4="","",Rates_data!S4) -> 503.18 | L37: =IF(Rates_data!T4="","",Rates_data!T4) -> 503.18 | M37: =IF(Rates_data!U4="","",Rates_data!U4) -> 503.18 | N37: =IF(Rates_data!V4="","",Rates_data!V4) -> 1 through 10 | O37: =IF(Rates_data!W4="","",Rates_data!W4) -> 503.18 | P37: =IF(Rates_data!X4="","",Rates_data!X4) -> median allowed | Q37: =IF(Rates_data!AA4="","",Rates_data!AA4) -> 135.93 | R37: =IF(Rates_data!AC4="","",Rates_data!AC4) -> 3.8544839
A38: Cigna | B38: Massachusetts General Hospital | C38: 95923 | D38: Commercial | E38: CIGNA [1006] | F38: HB AMC CIGNA HMO / PPO | G38: both | H38: percent of total billed charges | I38: =IF(Rates_data!P5="","",Rates_data!P5) -> 781.49 | J38: =IF(Rates_data!O5="","",Rates_data!O5) -> 79.5 | K38: =IF(Rates_data!S5="","",Rates_data!S5) -> 750.01 | L38: =IF(Rates_data!T5="","",Rates_data!T5) -> 503.18 | M38: =IF(Rates_data!U5="","",Rates_data!U5) -> 750.01 | N38: =IF(Rates_data!V5="","",Rates_data!V5) -> 17 | O38: =IF(Rates_data!W5="","",Rates_data!W5) -> 750.01 | P38: =IF(Rates_data!X5="","",Rates_data!X5) -> median allowed | Q38: =IF(Rates_data!AA5="","",Rates_data!AA5) -> 135.93 | R38: =IF(Rates_data!AC5="","",Rates_data!AC5) -> 5.7492092
A39: Cigna | B39: Massachusetts General Hospital | C39: 95924 | D39: Commercial | E39: CIGNA ALTERNATE [1018] | F39: HB AMC CIGNA NEW BUSINESS DISCOUNT | G39: both | H39: percent of total billed charges | I39: =IF(Rates_data!P13="","",Rates_data!P13) -> 611.88 | J39: =IF(Rates_data!O13="","",Rates_data!O13) -> 53.3 | K39: =IF(Rates_data!S13="","",Rates_data!S13) -> 587.66 | L39: =IF(Rates_data!T13="","",Rates_data!T13) -> 587.66 | M39: =IF(Rates_data!U13="","",Rates_data!U13) -> 587.66 | N39: =IF(Rates_data!V13="","",Rates_data!V13) -> 1 through 10 | O39: =IF(Rates_data!W13="","",Rates_data!W13) -> 587.66 | P39: =IF(Rates_data!X13="","",Rates_data!X13) -> median allowed | Q39: =IF(Rates_data!AA13="","",Rates_data!AA13) -> 369.77 | R39: =IF(Rates_data!AC13="","",Rates_data!AC13) -> 1.6547584
A40: Cigna | B40: Massachusetts General Hospital | C40: 95924 | D40: Commercial | E40: CIGNA [1006] | F40: HB AMC CIGNA HMO / PPO | G40: both | H40: percent of total billed charges | I40: =IF(Rates_data!P14="","",Rates_data!P14) -> 912.66 | J40: =IF(Rates_data!O14="","",Rates_data!O14) -> 79.5 | K40: =IF(Rates_data!S14="","",Rates_data!S14) -> 875.93 | L40: =IF(Rates_data!T14="","",Rates_data!T14) -> 587.66 | M40: =IF(Rates_data!U14="","",Rates_data!U14) -> 875.93 | N40: =IF(Rates_data!V14="","",Rates_data!V14) -> 18 | O40: =IF(Rates_data!W14="","",Rates_data!W14) -> 875.93 | P40: =IF(Rates_data!X14="","",Rates_data!X14) -> median allowed | Q40: =IF(Rates_data!AA14="","",Rates_data!AA14) -> 369.77 | R40: =IF(Rates_data!AC14="","",Rates_data!AC14) -> 2.4681829
A41: Cigna | B41: Brigham and Women's Faulkner Hospital | C41: 95921 | D41: Commercial | E41: CIGNA [1006] | F41: HB CH CIGNA HMO / PPO | G41: outpatient | H41: percent of total billed charges | I41: =IF(Rates_data!P29="","",Rates_data!P29) -> 255.58 | J41: =IF(Rates_data!O29="","",Rates_data!O29) -> 59.3 | K41: =IF(Rates_data!S29="","",Rates_data!S29) -> 245.53 | L41: =IF(Rates_data!T29="","",Rates_data!T29) -> 245.53 | M41: =IF(Rates_data!U29="","",Rates_data!U29) -> 245.53 | N41: =IF(Rates_data!V29="","",Rates_data!V29) -> 1 through 10 | O41: =IF(Rates_data!W29="","",Rates_data!W29) -> 245.53 | P41: =IF(Rates_data!X29="","",Rates_data!X29) -> median allowed | Q41: =IF(Rates_data!AA29="","",Rates_data!AA29) -> 185.81 | R41: =IF(Rates_data!AC29="","",Rates_data!AC29) -> 1.3754911
A42: Cigna | B42: Brigham and Women's Faulkner Hospital | C42: 95923 | D42: Commercial | E42: CIGNA [1006] | F42: HB CH CIGNA HMO / PPO | G42: outpatient | H42: percent of total billed charges | I42: =IF(Rates_data!P33="","",Rates_data!P33) -> 412.73 | J42: =IF(Rates_data!O33="","",Rates_data!O33) -> 59.3 | K42: =IF(Rates_data!S33="","",Rates_data!S33) -> 396.72 | L42: =IF(Rates_data!T33="","",Rates_data!T33) -> 396.72 | M42: =IF(Rates_data!U33="","",Rates_data!U33) -> 396.72 | N42: =IF(Rates_data!V33="","",Rates_data!V33) -> 15 | O42: =IF(Rates_data!W33="","",Rates_data!W33) -> 396.72 | P42: =IF(Rates_data!X33="","",Rates_data!X33) -> median allowed | Q42: =IF(Rates_data!AA33="","",Rates_data!AA33) -> 153.08 | R42: =IF(Rates_data!AC33="","",Rates_data!AC33) -> 2.6961719
A43: Cigna | B43: Brigham and Women's Faulkner Hospital | C43: 95924 | D43: Commercial | E43: CIGNA [1006] | F43: HB CH CIGNA HMO / PPO | G43: outpatient | H43: percent of total billed charges | I43: =IF(Rates_data!P41="","",Rates_data!P41) -> 479.74 | J43: =IF(Rates_data!O41="","",Rates_data!O41) -> 59.3 | K43: =IF(Rates_data!S41="","",Rates_data!S41) -> 461.18 | L43: =IF(Rates_data!T41="","",Rates_data!T41) -> 461.18 | M43: =IF(Rates_data!U41="","",Rates_data!U41) -> 461.18 | N43: =IF(Rates_data!V41="","",Rates_data!V41) -> 15 | O43: =IF(Rates_data!W41="","",Rates_data!W41) -> 461.18 | P43: =IF(Rates_data!X41="","",Rates_data!X41) -> median allowed | Q43: =IF(Rates_data!AA41="","",Rates_data!AA41) -> 369.81 | R43: =IF(Rates_data!AC41="","",Rates_data!AC41) -> 1.2972608
A44: MassHealth managed-care plans | B44: Massachusetts General Hospital | C44: 95924 | D44: MassHealth / dual managed care | E44: COMMONWEALTH CARE ALLIANCE [1007] | F44: HB MGH COMMONWEALTH CARE ALLIANCE | G44: both | H44: other | I44: =IF(Rates_data!P21="","",Rates_data!P21) -> 369.77 | J44: =IF(Rates_data!O21="","",Rates_data!O21) | K44: =IF(Rates_data!S21="","",Rates_data!S21) -> 365.12 | L44: =IF(Rates_data!T21="","",Rates_data!T21) -> 363.89 | M44: =IF(Rates_data!U21="","",Rates_data!U21) -> 365.12 | N44: =IF(Rates_data!V21="","",Rates_data!V21) -> 1 through 10 | O44: =IF(Rates_data!W21="","",Rates_data!W21) -> 365.12 | P44: =IF(Rates_data!X21="","",Rates_data!X21) -> median allowed | Q44: =IF(Rates_data!AA21="","",Rates_data!AA21) -> 369.77 | R44: =IF(Rates_data!AC21="","",Rates_data!AC21) -> 1
A45: Medicare Advantage plans | B45: Massachusetts General Hospital | C45: 95924 | D45: Medicare Advantage | E45: BLUE CROSS BLUE SHIELD [110001] | F45: HB MGH MEDICARE | G45: both | H45: other | I45: =IF(Rates_data!P22="","",Rates_data!P22) -> 369.77 | J45: =IF(Rates_data!O22="","",Rates_data!O22) | K45: =IF(Rates_data!S22="","",Rates_data!S22) -> 363.89 | L45: =IF(Rates_data!T22="","",Rates_data!T22) -> 363.89 | M45: =IF(Rates_data!U22="","",Rates_data!U22) -> 369.81 | N45: =IF(Rates_data!V22="","",Rates_data!V22) -> 1 through 10 | O45: =IF(Rates_data!W22="","",Rates_data!W22) -> 363.89 | P45: =IF(Rates_data!X22="","",Rates_data!X22) -> median allowed | Q45: =IF(Rates_data!AA22="","",Rates_data!AA22) -> 369.77 | R45: =IF(Rates_data!AC22="","",Rates_data!AC22) -> 1
A46: Medicare Advantage plans | B46: Massachusetts General Hospital | C46: 95924 | D46: Medicare Advantage | E46: HUMANA [1012] | F46: HB MGH MEDICARE | G46: both | H46: other | I46: =IF(Rates_data!P23="","",Rates_data!P23) -> 369.77 | J46: =IF(Rates_data!O23="","",Rates_data!O23) | K46: =IF(Rates_data!S23="","",Rates_data!S23) -> 365.37 | L46: =IF(Rates_data!T23="","",Rates_data!T23) -> 365.37 | M46: =IF(Rates_data!U23="","",Rates_data!U23) -> 365.37 | N46: =IF(Rates_data!V23="","",Rates_data!V23) -> 1 through 10 | O46: =IF(Rates_data!W23="","",Rates_data!W23) -> 365.37 | P46: =IF(Rates_data!X23="","",Rates_data!X23) -> median allowed | Q46: =IF(Rates_data!AA23="","",Rates_data!AA23) -> 369.77 | R46: =IF(Rates_data!AC23="","",Rates_data!AC23) -> 1
A47: Medicare Advantage plans | B47: Massachusetts General Hospital | C47: 95924 | D47: Medicare Advantage | E47: MGB HEALTH PLAN [150001] | F47: HB MGH MEDICARE | G47: both | H47: other | I47: =IF(Rates_data!P24="","",Rates_data!P24) -> 369.77 | J47: =IF(Rates_data!O24="","",Rates_data!O24) | K47: =IF(Rates_data!S24="","",Rates_data!S24) -> 336.12 | L47: =IF(Rates_data!T24="","",Rates_data!T24) -> 336.12 | M47: =IF(Rates_data!U24="","",Rates_data!U24) -> 336.12 | N47: =IF(Rates_data!V24="","",Rates_data!V24) -> 1 through 10 | O47: =IF(Rates_data!W24="","",Rates_data!W24) -> 336.12 | P47: =IF(Rates_data!X24="","",Rates_data!X24) -> median allowed | Q47: =IF(Rates_data!AA24="","",Rates_data!AA24) -> 369.77 | R47: =IF(Rates_data!AC24="","",Rates_data!AC24) -> 1
A48: Medicare Advantage plans | B48: Massachusetts General Hospital | C48: 95924 | D48: Medicare Advantage | E48: TUFTS HEALTH PLAN [170001] | F48: HB MGH TUFTS MEDICARE REPLACEMENT | G48: both | H48: other | I48: =IF(Rates_data!P25="","",Rates_data!P25) -> 362.37 | J48: =IF(Rates_data!O25="","",Rates_data!O25) | K48: =IF(Rates_data!S25="","",Rates_data!S25) -> 362.81 | L48: =IF(Rates_data!T25="","",Rates_data!T25) -> 335.92 | M48: =IF(Rates_data!U25="","",Rates_data!U25) -> 362.81 | N48: =IF(Rates_data!V25="","",Rates_data!V25) -> 1 through 10 | O48: =IF(Rates_data!W25="","",Rates_data!W25) -> 362.81 | P48: =IF(Rates_data!X25="","",Rates_data!X25) -> median allowed | Q48: =IF(Rates_data!AA25="","",Rates_data!AA25) -> 369.77 | R48: =IF(Rates_data!AC25="","",Rates_data!AC25) -> 0.97998756
A49: Medicare Advantage plans | B49: Massachusetts General Hospital | C49: 95924 | D49: Medicare Advantage | E49: UNITED HEALTHCARE [1016] | F49: HB MGH UNITED MEDICARE REPLACEMENT | G49: both | H49: other | I49: =IF(Rates_data!P26="","",Rates_data!P26) -> 362.37 | J49: =IF(Rates_data!O26="","",Rates_data!O26) | K49: =IF(Rates_data!S26="","",Rates_data!S26) -> 362.92 | L49: =IF(Rates_data!T26="","",Rates_data!T26) -> 362.41 | M49: =IF(Rates_data!U26="","",Rates_data!U26) -> 369.81 | N49: =IF(Rates_data!V26="","",Rates_data!V26) -> 1 through 10 | O49: =IF(Rates_data!W26="","",Rates_data!W26) -> 362.92 | P49: =IF(Rates_data!X26="","",Rates_data!X26) -> median allowed | Q49: =IF(Rates_data!AA26="","",Rates_data!AA26) -> 369.77 | R49: =IF(Rates_data!AC26="","",Rates_data!AC26) -> 0.97998756
A50: Medicare Advantage plans | B50: Brigham and Women's Faulkner Hospital | C50: 95921 | D50: Medicare Advantage | E50: UNITED HEALTHCARE [1016] | F50: HB BWF UNITED MEDICARE REPLACEMENT | G50: both | H50: other | I50: =IF(Rates_data!P31="","",Rates_data!P31) -> 182.09 | J50: =IF(Rates_data!O31="","",Rates_data!O31) | K50: =IF(Rates_data!S31="","",Rates_data!S31) -> 182.84 | L50: =IF(Rates_data!T31="","",Rates_data!T31) -> 182.1 | M50: =IF(Rates_data!U31="","",Rates_data!U31) -> 183.1 | N50: =IF(Rates_data!V31="","",Rates_data!V31) -> 1 through 10 | O50: =IF(Rates_data!W31="","",Rates_data!W31) -> 182.84 | P50: =IF(Rates_data!X31="","",Rates_data!X31) -> median allowed | Q50: =IF(Rates_data!AA31="","",Rates_data!AA31) -> 185.81 | R50: =IF(Rates_data!AC31="","",Rates_data!AC31) -> 0.97997955
A51: Medicare Advantage plans | B51: Brigham and Women's Faulkner Hospital | C51: 95923 | D51: Medicare Advantage | E51: BLUE CROSS BLUE SHIELD [110001] | F51: HB BWF MEDICARE | G51: both | H51: other | I51: =IF(Rates_data!P38="","",Rates_data!P38) -> 153.08 | J51: =IF(Rates_data!O38="","",Rates_data!O38) | K51: =IF(Rates_data!S38="","",Rates_data!S38) -> 171.01 | L51: =IF(Rates_data!T38="","",Rates_data!T38) -> 132.59 | M51: =IF(Rates_data!U38="","",Rates_data!U38) -> 171.01 | N51: =IF(Rates_data!V38="","",Rates_data!V38) -> 1 through 10 | O51: =IF(Rates_data!W38="","",Rates_data!W38) -> 171.01 | P51: =IF(Rates_data!X38="","",Rates_data!X38) -> median allowed | Q51: =IF(Rates_data!AA38="","",Rates_data!AA38) -> 153.08 | R51: =IF(Rates_data!AC38="","",Rates_data!AC38) -> 1
A52: Medicare Advantage plans | B52: Brigham and Women's Faulkner Hospital | C52: 95923 | D52: Medicare Advantage | E52: CENTERS OF EXCELLENCE [1026] | F52: HB BWF MEDICARE | G52: both | H52: other | I52: =IF(Rates_data!P39="","",Rates_data!P39) -> 153.08 | J52: =IF(Rates_data!O39="","",Rates_data!O39) | K52: =IF(Rates_data!S39="","",Rates_data!S39) -> 168.27 | L52: =IF(Rates_data!T39="","",Rates_data!T39) -> 168.27 | M52: =IF(Rates_data!U39="","",Rates_data!U39) -> 168.27 | N52: =IF(Rates_data!V39="","",Rates_data!V39) -> 1 through 10 | O52: =IF(Rates_data!W39="","",Rates_data!W39) -> 168.27 | P52: =IF(Rates_data!X39="","",Rates_data!X39) -> median allowed | Q52: =IF(Rates_data!AA39="","",Rates_data!AA39) -> 153.08 | R52: =IF(Rates_data!AC39="","",Rates_data!AC39) -> 1
A53: Medicare Advantage plans | B53: Brigham and Women's Faulkner Hospital | C53: 95924 | D53: Medicare Advantage | E53: BLUE CROSS BLUE SHIELD [110001] | F53: HB BWF MEDICARE | G53: both | H53: other | I53: =IF(Rates_data!P46="","",Rates_data!P46) -> 369.81 | J53: =IF(Rates_data!O46="","",Rates_data!O46) | K53: =IF(Rates_data!S46="","",Rates_data!S46) -> 363.89 | L53: =IF(Rates_data!T46="","",Rates_data!T46) -> 154.13 | M53: =IF(Rates_data!U46="","",Rates_data!U46) -> 363.89 | N53: =IF(Rates_data!V46="","",Rates_data!V46) -> 1 through 10 | O53: =IF(Rates_data!W46="","",Rates_data!W46) -> 363.89 | P53: =IF(Rates_data!X46="","",Rates_data!X46) -> median allowed | Q53: =IF(Rates_data!AA46="","",Rates_data!AA46) -> 369.81 | R53: =IF(Rates_data!AC46="","",Rates_data!AC46) -> 1
A54: Medicare Advantage plans | B54: Brigham and Women's Faulkner Hospital | C54: 95924 | D54: Medicare Advantage | E54: CENTERS OF EXCELLENCE [1026] | F54: HB BWF MEDICARE | G54: both | H54: other | I54: =IF(Rates_data!P47="","",Rates_data!P47) -> 369.81 | J54: =IF(Rates_data!O47="","",Rates_data!O47) | K54: =IF(Rates_data!S47="","",Rates_data!S47) -> 366.63 | L54: =IF(Rates_data!T47="","",Rates_data!T47) -> 366.63 | M54: =IF(Rates_data!U47="","",Rates_data!U47) -> 366.63 | N54: =IF(Rates_data!V47="","",Rates_data!V47) -> 1 through 10 | O54: =IF(Rates_data!W47="","",Rates_data!W47) -> 366.63 | P54: =IF(Rates_data!X47="","",Rates_data!X47) -> median allowed | Q54: =IF(Rates_data!AA47="","",Rates_data!AA47) -> 369.81 | R54: =IF(Rates_data!AC47="","",Rates_data!AC47) -> 1
A55: Medicare Advantage plans | B55: Brigham and Women's Faulkner Hospital | C55: 95924 | D55: Medicare Advantage | E55: COMMONWEALTH CARE ALLIANCE [1007] | F55: HB BWF TUFTS + COMM CARE ALLIANCE MCARE | G55: both | H55: other | I55: =IF(Rates_data!P48="","",Rates_data!P48) -> 362.41 | J55: =IF(Rates_data!O48="","",Rates_data!O48) | K55: =IF(Rates_data!S48="","",Rates_data!S48) -> 363.89 | L55: =IF(Rates_data!T48="","",Rates_data!T48) -> 363.89 | M55: =IF(Rates_data!U48="","",Rates_data!U48) -> 363.89 | N55: =IF(Rates_data!V48="","",Rates_data!V48) -> 1 through 10 | O55: =IF(Rates_data!W48="","",Rates_data!W48) -> 363.89 | P55: =IF(Rates_data!X48="","",Rates_data!X48) -> median allowed | Q55: =IF(Rates_data!AA48="","",Rates_data!AA48) -> 369.81 | R55: =IF(Rates_data!AC48="","",Rates_data!AC48) -> 0.97998972
A56: Medicare Advantage plans | B56: Brigham and Women's Faulkner Hospital | C56: 95924 | D56: Medicare Advantage | E56: HUMANA [1012] | F56: HB BWF MEDICARE | G56: both | H56: other | I56: =IF(Rates_data!P49="","",Rates_data!P49) -> 369.81 | J56: =IF(Rates_data!O49="","",Rates_data!O49) | K56: =IF(Rates_data!S49="","",Rates_data!S49) -> 362.41 | L56: =IF(Rates_data!T49="","",Rates_data!T49) -> 362.41 | M56: =IF(Rates_data!U49="","",Rates_data!U49) -> 362.41 | N56: =IF(Rates_data!V49="","",Rates_data!V49) -> 1 through 10 | O56: =IF(Rates_data!W49="","",Rates_data!W49) -> 362.41 | P56: =IF(Rates_data!X49="","",Rates_data!X49) -> median allowed | Q56: =IF(Rates_data!AA49="","",Rates_data!AA49) -> 369.81 | R56: =IF(Rates_data!AC49="","",Rates_data!AC49) -> 1
A57: Medicare Advantage plans | B57: Brigham and Women's Faulkner Hospital | C57: 95924 | D57: Medicare Advantage | E57: MARTIN'S POINT [160007] | F57: HB BWF MEDICARE | G57: both | H57: other | I57: =IF(Rates_data!P50="","",Rates_data!P50) -> 369.81 | J57: =IF(Rates_data!O50="","",Rates_data!O50) | K57: =IF(Rates_data!S50="","",Rates_data!S50) -> 363.89 | L57: =IF(Rates_data!T50="","",Rates_data!T50) -> 363.89 | M57: =IF(Rates_data!U50="","",Rates_data!U50) -> 363.89 | N57: =IF(Rates_data!V50="","",Rates_data!V50) -> 1 through 10 | O57: =IF(Rates_data!W50="","",Rates_data!W50) -> 363.89 | P57: =IF(Rates_data!X50="","",Rates_data!X50) -> median allowed | Q57: =IF(Rates_data!AA50="","",Rates_data!AA50) -> 369.81 | R57: =IF(Rates_data!AC50="","",Rates_data!AC50) -> 1
A58: Medicare Advantage plans | B58: Brigham and Women's Faulkner Hospital | C58: 95924 | D58: Medicare Advantage | E58: TUFTS HEALTH PLAN [170001] | F58: HB BWF TUFTS + COMM CARE ALLIANCE MCARE | G58: both | H58: other | I58: =IF(Rates_data!P51="","",Rates_data!P51) -> 362.41 | J58: =IF(Rates_data!O51="","",Rates_data!O51) | K58: =IF(Rates_data!S51="","",Rates_data!S51) -> 362.81 | L58: =IF(Rates_data!T51="","",Rates_data!T51) -> 362.61 | M58: =IF(Rates_data!U51="","",Rates_data!U51) -> 363.01 | N58: =IF(Rates_data!V51="","",Rates_data!V51) -> 1 through 10 | O58: =IF(Rates_data!W51="","",Rates_data!W51) -> 362.81 | P58: =IF(Rates_data!X51="","",Rates_data!X51) -> median allowed | Q58: =IF(Rates_data!AA51="","",Rates_data!AA51) -> 369.81 | R58: =IF(Rates_data!AC51="","",Rates_data!AC51) -> 0.97998972
A59: Medicare Advantage plans | B59: Brigham and Women's Faulkner Hospital | C59: 95924 | D59: Medicare Advantage | E59: UNITED HEALTHCARE [1016] | F59: HB BWF UNITED MEDICARE REPLACEMENT | G59: both | H59: other | I59: =IF(Rates_data!P52="","",Rates_data!P52) -> 362.41 | J59: =IF(Rates_data!O52="","",Rates_data!O52) | K59: =IF(Rates_data!S52="","",Rates_data!S52) -> 362.92 | L59: =IF(Rates_data!T52="","",Rates_data!T52) -> 337.09 | M59: =IF(Rates_data!U52="","",Rates_data!U52) -> 363.42 | N59: =IF(Rates_data!V52="","",Rates_data!V52) -> 12 | O59: =IF(Rates_data!W52="","",Rates_data!W52) -> 362.92 | P59: =IF(Rates_data!X52="","",Rates_data!X52) -> median allowed | Q59: =IF(Rates_data!AA52="","",Rates_data!AA52) -> 369.81 | R59: =IF(Rates_data!AC52="","",Rates_data!AC52) -> 0.97998972

Sheet Coverage
A1: Coverage: does the hospital file list rows for 95923 / 95924?
A2: Commercial rows for the seven commercial focus payers; any rows for MassHealth managed care, Medicare Advantage and Medicare FFS. 'not listed' = no row in the hospital's MRF.
A4: Focus payer | B4: Rows counted | C4: MGH 95923 | D4: MGH 95924 | E4: BWH 95923 | F4: BWH 95924 | G4: BWFH 95923 | H4: BWFH 95924 | I4: WDH 95923 | J4: WDH 95924 | K4: BIDMC 95923 | L4: BIDMC 95924
A5: Blue Cross Blue Shield of Massachusetts | B5: Commercial rows | C5: =IF(COUNTIFS(Rates_data!$B$2:$B$75,"Massachusetts General Hospital",Rates_data!$D$2:$D$75,"95923",Rates_data!$Y$2:$Y$75,1,Rates_data!$F$2:$F$75,"Blue Cross Blue Shield of MA",Rates_data!$G$2:$G$75,"Commercial")=0,"not listed",COUNTIFS(Rates_data!$B$2:$B$75,"Massachusetts General Hospital",Rates_data!$D$2:$D$75,"95923",Rates_data!$Y$2:$Y$75,1,Rates_data!$F$2:$F$75,"Blue Cross Blue Shield of MA",Rates_data!$G$2:$G$75,"Commercial")&" row(s)") -> not listed | D5: =IF(COUNTIFS(Rates_data!$B$2:$B$75,"Massachusetts General Hospital",Rates_data!$D$2:$D$75,"95924",Rates_data!$Y$2:$Y$75,1,Rates_data!$F$2:$F$75,"Blue Cross Blue Shield of MA",Rates_data!$G$2:$G$75,"Commercial")=0,"not listed",COUNTIFS(Rates_data!$B$2:$B$75,"Massachusetts General Hospital",Rates_data!$D$2:$D$75,"95924",Rates_data!$Y$2:$Y$75,1,Rates_data!$F$2:$F$75,"Blue Cross Blue Shield of MA",Rates_data!$G$2:$G$75,"Commercial")&" row(s)") -> not listed | E5: =IF(COUNTIFS(Rates_data!$B$2:$B$75,"Brigham and Women's Hospital",Rates_data!$D$2:$D$75,"95923",Rates_data!$Y$2:$Y$75,1,Rates_data!$F$2:$F$75,"Blue Cross Blue Shield of MA",Rates_data!$G$2:$G$75,"Commercial")=0,"not listed",COUNTIFS(Rates_data!$B$2:$B$75,"Brigham and Women's Hospital",Rates_data!$D$2:$D$75,"95923",Rates_data!$Y$2:$Y$75,1,Rates_data!$F$2:$F$75,"Blue Cross Blue Shield of MA",Rates_data!$G$2:$G$75,"Commercial")&" row(s)") -> not listed | F5: =IF(COUNTIFS(Rates_data!$B$2:$B$75,"Brigham and Women's Hospital",Rates_data!$D$2:$D$75,"95924",Rates_data!$Y$2:$Y$75,1,Rates_data!$F$2:$F$75,"Blue Cross Blue Shield of MA",Rates_data!$G$2:$G$75,"Commercial")=0,"not listed",COUNTIFS(Rates_data!$B$2:$B$75,"Brigham and Women's Hospital",Rates_data!$D$2:$D$75,"95924",Rates_data!$Y$2:$Y$75,1,Rates_data!$F$2:$F$75,"Blue Cross Blue Shield of MA",Rates_data!$G$2:$G$75,"Commercial")&" row(s)") -> not listed | G5: =IF(COUNTIFS(Rates_data!$B$2:$B$75,"Brigham and Women's Faulkner Hospital",Rates_data!$D$2:$D$75,"95923",Rates_data!$Y$2:$Y$75,1,Rates_data!$F$2:$F$75,"Blue Cross Blue Shield of MA",Rates_data!$G$2:$G$75,"Commercial")=0,"not listed",COUNTIFS(Rates_data!$B$2:$B$75,"Brigham and Women's Faulkner Hospital",Rates_data!$D$2:$D$75,"95923",Rates_data!$Y$2:$Y$75,1,Rates_data!$F$2:$F$75,"Blue Cross Blue Shield of MA",Rates_data!$G$2:$G$75,"Commercial")&" row(s)") -> not listed | H5: =IF(COUNTIFS(Rates_data!$B$2:$B$75,"Brigham and Women's Faulkner Hospital",Rates_data!$D$2:$D$75,"95924",Rates_data!$Y$2:$Y$75,1,Rates_data!$F$2:$F$75,"Blue Cross Blue Shield of MA",Rates_data!$G$2:$G$75,"Commercial")=0,"not listed",COUNTIFS(Rates_data!$B$2:$B$75,"Brigham and Women's Faulkner Hospital",Rates_data!$D$2:$D$75,"95924",Rates_data!$Y$2:$Y$75,1,Rates_data!$F$2:$F$75,"Blue Cross Blue Shield of MA",Rates_data!$G$2:$G$75,"Commercial")&" row(s)") -> not listed | I5: =IF(COUNTIFS(Rates_data!$B$2:$B$75,"Wentworth-Douglass Hospital",Rates_data!$D$2:$D$75,"95923",Rates_data!$Y$2:$Y$75,1,Rates_data!$F$2:$F$75,"Blue Cross Blue Shield of MA",Rates_data!$G$2:$G$75,"Commercial")=0,"not listed",COUNTIFS(Rates_data!$B$2:$B$75,"Wentworth-Douglass Hospital",Rates_data!$D$2:$D$75,"95923",Rates_data!$Y$2:$Y$75,1,Rates_data!$F$2:$F$75,"Blue Cross Blue Shield of MA",Rates_data!$G$2:$G$75,"Commercial")&" row(s)") -> not listed | J5: =IF(COUNTIFS(Rates_data!$B$2:$B$75,"Wentworth-Douglass Hospital",Rates_data!$D$2:$D$75,"95924",Rates_data!$Y$2:$Y$75,1,Rates_data!$F$2:$F$75,"Blue Cross Blue Shield of MA",Rates_data!$G$2:$G$75,"Commercial")=0,"not listed",COUNTIFS(Rates_data!$B$2:$B$75,"Wentworth-Douglass Hospital",Rates_data!$D$2:$D$75,"95924",Rates_data!$Y$2:$Y$75,1,Rates_data!$F$2:$F$75,"Blue Cross Blue Shield of MA",Rates_data!$G$2:$G$75,"Commercial")&" row(s)") -> not listed | K5: =IF(COUNTIFS(Rates_data!$B$2:$B$75,"Beth Israel Deaconess Medical Center",Rates_data!$D$2:$D$75,"95923",Rates_data!$Y$2:$Y$75,1,Rates_data!$F$2:$F$75,"Blue Cross Blue Shield of MA",Rates_data!$G$2:$G$75,"Commercial")=0,"not listed",COUNTIFS(Rates_data!$B$2:$B$75,"Beth Israel Deaconess Medical Center",Rates_data!$D$2:$D$75,"95923",Rates_data!$Y$2:$Y$75,1,Rates_data!$F$2:$F$75,"Blue Cross Blue Shield of MA",Rates_data!$G$2:$G$75,"Commercial")&" row(s)") -> 2 row(s) | L5: =IF(COUNTIFS(Rates_data!$B$2:$B$75,"Beth Israel Deaconess Medical Center",Rates_data!$D$2:$D$75,"95924",Rates_data!$Y$2:$Y$75,1,Rates_data!$F$2:$F$75,"Blue Cross Blue Shield of MA",Rates_data!$G$2:$G$75,"Commercial")=0,"not listed",COUNTIFS(Rates_data!$B$2:$B$75,"Beth Israel Deaconess Medical Center",Rates_data!$D$2:$D$75,"95924",Rates_data!$Y$2:$Y$75,1,Rates_data!$F$2:$F$75,"Blue Cross Blue Shield of MA",Rates_data!$G$2:$G$75,"Commercial")&" row(s)") -> 2 row(s)
A6: Harvard Pilgrim / Point32Health | B6: Commercial rows | C6: =IF(COUNTIFS(Rates_data!$B$2:$B$75,"Massachusetts General Hospital",Rates_data!$D$2:$D$75,"95923",Rates_data!$Y$2:$Y$75,1,Rates_data!$F$2:$F$75,"Harvard Pilgrim / Point32Health",Rates_data!$G$2:$G$75,"Commercial")=0,"not listed",COUNTIFS(Rates_data!$B$2:$B$75,"Massachusetts General Hospital",Rates_data!$D$2:$D$75,"95923",Rates_data!$Y$2:$Y$75,1,Rates_data!$F$2:$F$75,"Harvard Pilgrim / Point32Health",Rates_data!$G$2:$G$75,"Commercial")&" row(s)") -> not listed | D6: =IF(COUNTIFS(Rates_data!$B$2:$B$75,"Massachusetts General Hospital",Rates_data!$D$2:$D$75,"95924",Rates_data!$Y$2:$Y$75,1,Rates_data!$F$2:$F$75,"Harvard Pilgrim / Point32Health",Rates_data!$G$2:$G$75,"Commercial")=0,"not listed",COUNTIFS(Rates_data!$B$2:$B$75,"Massachusetts General Hospital",Rates_data!$D$2:$D$75,"95924",Rates_data!$Y$2:$Y$75,1,Rates_data!$F$2:$F$75,"Harvard Pilgrim / Point32Health",Rates_data!$G$2:$G$75,"Commercial")&" row(s)") -> not listed | E6: =IF(COUNTIFS(Rates_data!$B$2:$B$75,"Brigham and Women's Hospital",Rates_data!$D$2:$D$75,"95923",Rates_data!$Y$2:$Y$75,1,Rates_data!$F$2:$F$75,"Harvard Pilgrim / Point32Health",Rates_data!$G$2:$G$75,"Commercial")=0,"not listed",COUNTIFS(Rates_data!$B$2:$B$75,"Brigham and Women's Hospital",Rates_data!$D$2:$D$75,"95923",Rates_data!$Y$2:$Y$75,1,Rates_data!$F$2:$F$75,"Harvard Pilgrim / Point32Health",Rates_data!$G$2:$G$75,"Commercial")&" row(s)") -> not listed | F6: =IF(COUNTIFS(Rates_data!$B$2:$B$75,"Brigham and Women's Hospital",Rates_data!$D$2:$D$75,"95924",Rates_data!$Y$2:$Y$75,1,Rates_data!$F$2:$F$75,"Harvard Pilgrim / Point32Health",Rates_data!$G$2:$G$75,"Commercial")=0,"not listed",COUNTIFS(Rates_data!$B$2:$B$75,"Brigham and Women's Hospital",Rates_data!$D$2:$D$75,"95924",Rates_data!$Y$2:$Y$75,1,Rates_data!$F$2:$F$75,"Harvard Pilgrim / Point32Health",Rates_data!$G$2:$G$75,"Commercial")&" row(s)") -> not listed | G6: =IF(COUNTIFS(Rates_data!$B$2:$B$75,"Brigham and Women's Faulkner Hospital",Rates_data!$D$2:$D$75,"95923",Rates_data!$Y$2:$Y$75,1,Rates_data!$F$2:$F$75,"Harvard Pilgrim / Point32Health",Rates_data!$G$2:$G$75,"Commercial")=0,"not listed",COUNTIFS(Rates_data!$B$2:$B$75,"Brigham and Women's Faulkner Hospital",Rates_data!$D$2:$D$75,"95923",Rates_data!$Y$2:$Y$75,1,Rates_data!$F$2:$F$75,"Harvard Pilgrim / Point32Health",Rates_data!$G$2:$G$75,"Commercial")&" row(s)") -> not listed | H6: =IF(COUNTIFS(Rates_data!$B$2:$B$75,"Brigham and Women's Faulkner Hospital",Rates_data!$D$2:$D$75,"95924",Rates_data!$Y$2:$Y$75,1,Rates_data!$F$2:$F$75,"Harvard Pilgrim / Point32Health",Rates_data!$G$2:$G$75,"Commercial")=0,"not listed",COUNTIFS(Rates_data!$B$2:$B$75,"Brigham and Women's Faulkner Hospital",Rates_data!$D$2:$D$75,"95924",Rates_data!$Y$2:$Y$75,1,Rates_data!$F$2:$F$75,"Harvard Pilgrim / Point32Health",Rates_data!$G$2:$G$75,"Commercial")&" row(s)") -> not listed | I6: =IF(COUNTIFS(Rates_data!$B$2:$B$75,"Wentworth-Douglass Hospital",Rates_data!$D$2:$D$75,"95923",Rates_data!$Y$2:$Y$75,1,Rates_data!$F$2:$F$75,"Harvard Pilgrim / Point32Health",Rates_data!$G$2:$G$75,"Commercial")=0,"not listed",COUNTIFS(Rates_data!$B$2:$B$75,"Wentworth-Douglass Hospital",Rates_data!$D$2:$D$75,"95923",Rates_data!$Y$2:$Y$75,1,Rates_data!$F$2:$F$75,"Harvard Pilgrim / Point32Health",Rates_data!$G$2:$G$75,"Commercial")&" row(s)") -> not listed | J6: =IF(COUNTIFS(Rates_data!$B$2:$B$75,"Wentworth-Douglass Hospital",Rates_data!$D$2:$D$75,"95924",Rates_data!$Y$2:$Y$75,1,Rates_data!$F$2:$F$75,"Harvard Pilgrim / Point32Health",Rates_data!$G$2:$G$75,"Commercial")=0,"not listed",COUNTIFS(Rates_data!$B$2:$B$75,"Wentworth-Douglass Hospital",Rates_data!$D$2:$D$75,"95924",Rates_data!$Y$2:$Y$75,1,Rates_data!$F$2:$F$75,"Harvard Pilgrim / Point32Health",Rates_data!$G$2:$G$75,"Commercial")&" row(s)") -> not listed | K6: =IF(COUNTIFS(Rates_data!$B$2:$B$75,"Beth Israel Deaconess Medical Center",Rates_data!$D$2:$D$75,"95923",Rates_data!$Y$2:$Y$75,1,Rates_data!$F$2:$F$75,"Harvard Pilgrim / Point32Health",Rates_data!$G$2:$G$75,"Commercial")=0,"not listed",COUNTIFS(Rates_data!$B$2:$B$75,"Beth Israel Deaconess Medical Center",Rates_data!$D$2:$D$75,"95923",Rates_data!$Y$2:$Y$75,1,Rates_data!$F$2:$F$75,"Harvard Pilgrim / Point32Health",Rates_data!$G$2:$G$75,"Commercial")&" row(s)") -> 1 row(s) | L6: =IF(COUNTIFS(Rates_data!$B$2:$B$75,"Beth Israel Deaconess Medical Center",Rates_data!$D$2:$D$75,"95924",Rates_data!$Y$2:$Y$75,1,Rates_data!$F$2:$F$75,"Harvard Pilgrim / Point32Health",Rates_data!$G$2:$G$75,"Commercial")=0,"not listed",COUNTIFS(Rates_data!$B$2:$B$75,"Beth Israel Deaconess Medical Center",Rates_data!$D$2:$D$75,"95924",Rates_data!$Y$2:$Y$75,1,Rates_data!$F$2:$F$75,"Harvard Pilgrim / Point32Health",Rates_data!$G$2:$G$75,"Commercial")&" row(s)") -> 1 row(s)
A7: Tufts Health Plan | B7: Commercial rows | C7: =IF(COUNTIFS(Rates_data!$B$2:$B$75,"Massachusetts General Hospital",Rates_data!$D$2:$D$75,"95923",Rates_data!$Y$2:$Y$75,1,Rates_data!$F$2:$F$75,"Tufts Health Plan",Rates_data!$G$2:$G$75,"Commercial")=0,"not listed",COUNTIFS(Rates_data!$B$2:$B$75,"Massachusetts General Hospital",Rates_data!$D$2:$D$75,"95923",Rates_data!$Y$2:$Y$75,1,Rates_data!$F$2:$F$75,"Tufts Health Plan",Rates_data!$G$2:$G$75,"Commercial")&" row(s)") -> not listed | D7: =IF(COUNTIFS(Rates_data!$B$2:$B$75,"Massachusetts General Hospital",Rates_data!$D$2:$D$75,"95924",Rates_data!$Y$2:$Y$75,1,Rates_data!$F$2:$F$75,"Tufts Health Plan",Rates_data!$G$2:$G$75,"Commercial")=0,"not listed",COUNTIFS(Rates_data!$B$2:$B$75,"Massachusetts General Hospital",Rates_data!$D$2:$D$75,"95924",Rates_data!$Y$2:$Y$75,1,Rates_data!$F$2:$F$75,"Tufts Health Plan",Rates_data!$G$2:$G$75,"Commercial")&" row(s)") -> not listed | E7: =IF(COUNTIFS(Rates_data!$B$2:$B$75,"Brigham and Women's Hospital",Rates_data!$D$2:$D$75,"95923",Rates_data!$Y$2:$Y$75,1,Rates_data!$F$2:$F$75,"Tufts Health Plan",Rates_data!$G$2:$G$75,"Commercial")=0,"not listed",COUNTIFS(Rates_data!$B$2:$B$75,"Brigham and Women's Hospital",Rates_data!$D$2:$D$75,"95923",Rates_data!$Y$2:$Y$75,1,Rates_data!$F$2:$F$75,"Tufts Health Plan",Rates_data!$G$2:$G$75,"Commercial")&" row(s)") -> not listed | F7: =IF(COUNTIFS(Rates_data!$B$2:$B$75,"Brigham and Women's Hospital",Rates_data!$D$2:$D$75,"95924",Rates_data!$Y$2:$Y$75,1,Rates_data!$F$2:$F$75,"Tufts Health Plan",Rates_data!$G$2:$G$75,"Commercial")=0,"not listed",COUNTIFS(Rates_data!$B$2:$B$75,"Brigham and Women's Hospital",Rates_data!$D$2:$D$75,"95924",Rates_data!$Y$2:$Y$75,1,Rates_data!$F$2:$F$75,"Tufts Health Plan",Rates_data!$G$2:$G$75,"Commercial")&" row(s)") -> not listed | G7: =IF(COUNTIFS(Rates_data!$B$2:$B$75,"Brigham and Women's Faulkner Hospital",Rates_data!$D$2:$D$75,"95923",Rates_data!$Y$2:$Y$75,1,Rates_data!$F$2:$F$75,"Tufts Health Plan",Rates_data!$G$2:$G$75,"Commercial")=0,"not listed",COUNTIFS(Rates_data!$B$2:$B$75,"Brigham and Women's Faulkner Hospital",Rates_data!$D$2:$D$75,"95923",Rates_data!$Y$2:$Y$75,1,Rates_data!$F$2:$F$75,"Tufts Health Plan",Rates_data!$G$2:$G$75,"Commercial")&" row(s)") -> not listed | H7: =IF(COUNTIFS(Rates_data!$B$2:$B$75,"Brigham and Women's Faulkner Hospital",Rates_data!$D$2:$D$75,"95924",Rates_data!$Y$2:$Y$75,1,Rates_data!$F$2:$F$75,"Tufts Health Plan",Rates_data!$G$2:$G$75,"Commercial")=0,"not listed",COUNTIFS(Rates_data!$B$2:$B$75,"Brigham and Women's Faulkner Hospital",Rates_data!$D$2:$D$75,"95924",Rates_data!$Y$2:$Y$75,1,Rates_data!$F$2:$F$75,"Tufts Health Plan",Rates_data!$G$2:$G$75,"Commercial")&" row(s)") -> not listed | I7: =IF(COUNTIFS(Rates_data!$B$2:$B$75,"Wentworth-Douglass Hospital",Rates_data!$D$2:$D$75,"95923",Rates_data!$Y$2:$Y$75,1,Rates_data!$F$2:$F$75,"Tufts Health Plan",Rates_data!$G$2:$G$75,"Commercial")=0,"not listed",COUNTIFS(Rates_data!$B$2:$B$75,"Wentworth-Douglass Hospital",Rates_data!$D$2:$D$75,"95923",Rates_data!$Y$2:$Y$75,1,Rates_data!$F$2:$F$75,"Tufts Health Plan",Rates_data!$G$2:$G$75,"Commercial")&" row(s)") -> not listed | J7: =IF(COUNTIFS(Rates_data!$B$2:$B$75,"Wentworth-Douglass Hospital",Rates_data!$D$2:$D$75,"95924",Rates_data!$Y$2:$Y$75,1,Rates_data!$F$2:$F$75,"Tufts Health Plan",Rates_data!$G$2:$G$75,"Commercial")=0,"not listed",COUNTIFS(Rates_data!$B$2:$B$75,"Wentworth-Douglass Hospital",Rates_data!$D$2:$D$75,"95924",Rates_data!$Y$2:$Y$75,1,Rates_data!$F$2:$F$75,"Tufts Health Plan",Rates_data!$G$2:$G$75,"Commercial")&" row(s)") -> not listed | K7: =IF(COUNTIFS(Rates_data!$B$2:$B$75,"Beth Israel Deaconess Medical Center",Rates_data!$D$2:$D$75,"95923",Rates_data!$Y$2:$Y$75,1,Rates_data!$F$2:$F$75,"Tufts Health Plan",Rates_data!$G$2:$G$75,"Commercial")=0,"not listed",COUNTIFS(Rates_data!$B$2:$B$75,"Beth Israel Deaconess Medical Center",Rates_data!$D$2:$D$75,"95923",Rates_data!$Y$2:$Y$75,1,Rates_data!$F$2:$F$75,"Tufts Health Plan",Rates_data!$G$2:$G$75,"Commercial")&" row(s)") -> not listed | L7: =IF(COUNTIFS(Rates_data!$B$2:$B$75,"Beth Israel Deaconess Medical Center",Rates_data!$D$2:$D$75,"95924",Rates_data!$Y$2:$Y$75,1,Rates_data!$F$2:$F$75,"Tufts Health Plan",Rates_data!$G$2:$G$75,"Commercial")=0,"not listed",COUNTIFS(Rates_data!$B$2:$B$75,"Beth Israel Deaconess Medical Center",Rates_data!$D$2:$D$75,"95924",Rates_data!$Y$2:$Y$75,1,Rates_data!$F$2:$F$75,"Tufts Health Plan",Rates_data!$G$2:$G$75,"Commercial")&" row(s)") -> not listed
A8: Mass General Brigham Health Plan | B8: Commercial rows | C8: =IF(COUNTIFS(Rates_data!$B$2:$B$75,"Massachusetts General Hospital",Rates_data!$D$2:$D$75,"95923",Rates_data!$Y$2:$Y$75,1,Rates_data!$F$2:$F$75,"Mass General Brigham Health Plan",Rates_data!$G$2:$G$75,"Commercial")=0,"not listed",COUNTIFS(Rates_data!$B$2:$B$75,"Massachusetts General Hospital",Rates_data!$D$2:$D$75,"95923",Rates_data!$Y$2:$Y$75,1,Rates_data!$F$2:$F$75,"Mass General Brigham Health Plan",Rates_data!$G$2:$G$75,"Commercial")&" row(s)") -> 2 row(s) | D8: =IF(COUNTIFS(Rates_data!$B$2:$B$75,"Massachusetts General Hospital",Rates_data!$D$2:$D$75,"95924",Rates_data!$Y$2:$Y$75,1,Rates_data!$F$2:$F$75,"Mass General Brigham Health Plan",Rates_data!$G$2:$G$75,"Commercial")=0,"not listed",COUNTIFS(Rates_data!$B$2:$B$75,"Massachusetts General Hospital",Rates_data!$D$2:$D$75,"95924",Rates_data!$Y$2:$Y$75,1,Rates_data!$F$2:$F$75,"Mass General Brigham Health Plan",Rates_data!$G$2:$G$75,"Commercial")&" row(s)") -> 2 row(s) | E8: =IF(COUNTIFS(Rates_data!$B$2:$B$75,"Brigham and Women's Hospital",Rates_data!$D$2:$D$75,"95923",Rates_data!$Y$2:$Y$75,1,Rates_data!$F$2:$F$75,"Mass General Brigham Health Plan",Rates_data!$G$2:$G$75,"Commercial")=0,"not listed",COUNTIFS(Rates_data!$B$2:$B$75,"Brigham and Women's Hospital",Rates_data!$D$2:$D$75,"95923",Rates_data!$Y$2:$Y$75,1,Rates_data!$F$2:$F$75,"Mass General Brigham Health Plan",Rates_data!$G$2:$G$75,"Commercial")&" row(s)") -> not listed | F8: =IF(COUNTIFS(Rates_data!$B$2:$B$75,"Brigham and Women's Hospital",Rates_data!$D$2:$D$75,"95924",Rates_data!$Y$2:$Y$75,1,Rates_data!$F$2:$F$75,"Mass General Brigham Health Plan",Rates_data!$G$2:$G$75,"Commercial")=0,"not listed",COUNTIFS(Rates_data!$B$2:$B$75,"Brigham and Women's Hospital",Rates_data!$D$2:$D$75,"95924",Rates_data!$Y$2:$Y$75,1,Rates_data!$F$2:$F$75,"Mass General Brigham Health Plan",Rates_data!$G$2:$G$75,"Commercial")&" row(s)") -> not listed | G8: =IF(COUNTIFS(Rates_data!$B$2:$B$75,"Brigham and Women's Faulkner Hospital",Rates_data!$D$2:$D$75,"95923",Rates_data!$Y$2:$Y$75,1,Rates_data!$F$2:$F$75,"Mass General Brigham Health Plan",Rates_data!$G$2:$G$75,"Commercial")=0,"not listed",COUNTIFS(Rates_data!$B$2:$B$75,"Brigham and Women's Faulkner Hospital",Rates_data!$D$2:$D$75,"95923",Rates_data!$Y$2:$Y$75,1,Rates_data!$F$2:$F$75,"Mass General Brigham Health Plan",Rates_data!$G$2:$G$75,"Commercial")&" row(s)") -> not listed | H8: =IF(COUNTIFS(Rates_data!$B$2:$B$75,"Brigham and Women's Faulkner Hospital",Rates_data!$D$2:$D$75,"95924",Rates_data!$Y$2:$Y$75,1,Rates_data!$F$2:$F$75,"Mass General Brigham Health Plan",Rates_data!$G$2:$G$75,"Commercial")=0,"not listed",COUNTIFS(Rates_data!$B$2:$B$75,"Brigham and Women's Faulkner Hospital",Rates_data!$D$2:$D$75,"95924",Rates_data!$Y$2:$Y$75,1,Rates_data!$F$2:$F$75,"Mass General Brigham Health Plan",Rates_data!$G$2:$G$75,"Commercial")&" row(s)") -> not listed | I8: =IF(COUNTIFS(Rates_data!$B$2:$B$75,"Wentworth-Douglass Hospital",Rates_data!$D$2:$D$75,"95923",Rates_data!$Y$2:$Y$75,1,Rates_data!$F$2:$F$75,"Mass General Brigham Health Plan",Rates_data!$G$2:$G$75,"Commercial")=0,"not listed",COUNTIFS(Rates_data!$B$2:$B$75,"Wentworth-Douglass Hospital",Rates_data!$D$2:$D$75,"95923",Rates_data!$Y$2:$Y$75,1,Rates_data!$F$2:$F$75,"Mass General Brigham Health Plan",Rates_data!$G$2:$G$75,"Commercial")&" row(s)") -> not listed | J8: =IF(COUNTIFS(Rates_data!$B$2:$B$75,"Wentworth-Douglass Hospital",Rates_data!$D$2:$D$75,"95924",Rates_data!$Y$2:$Y$75,1,Rates_data!$F$2:$F$75,"Mass General Brigham Health Plan",Rates_data!$G$2:$G$75,"Commercial")=0,"not listed",COUNTIFS(Rates_data!$B$2:$B$75,"Wentworth-Douglass Hospital",Rates_data!$D$2:$D$75,"95924",Rates_data!$Y$2:$Y$75,1,Rates_data!$F$2:$F$75,"Mass General Brigham Health Plan",Rates_data!$G$2:$G$75,"Commercial")&" row(s)") -> not listed | K8: =IF(COUNTIFS(Rates_data!$B$2:$B$75,"Beth Israel Deaconess Medical Center",Rates_data!$D$2:$D$75,"95923",Rates_data!$Y$2:$Y$75,1,Rates_data!$F$2:$F$75,"Mass General Brigham Health Plan",Rates_data!$G$2:$G$75,"Commercial")=0,"not listed",COUNTIFS(Rates_data!$B$2:$B$75,"Beth Israel Deaconess Medical Center",Rates_data!$D$2:$D$75,"95923",Rates_data!$Y$2:$Y$75,1,Rates_data!$F$2:$F$75,"Mass General Brigham Health Plan",Rates_data!$G$2:$G$75,"Commercial")&" row(s)") -> not listed | L8: =IF(COUNTIFS(Rates_data!$B$2:$B$75,"Beth Israel Deaconess Medical Center",Rates_data!$D$2:$D$75,"95924",Rates_data!$Y$2:$Y$75,1,Rates_data!$F$2:$F$75,"Mass General Brigham Health Plan",Rates_data!$G$2:$G$75,"Commercial")=0,"not listed",COUNTIFS(Rates_data!$B$2:$B$75,"Beth Israel Deaconess Medical Center",Rates_data!$D$2:$D$75,"95924",Rates_data!$Y$2:$Y$75,1,Rates_data!$F$2:$F$75,"Mass General Brigham Health Plan",Rates_data!$G$2:$G$75,"Commercial")&" row(s)") -> not listed
A9: UnitedHealthcare | B9: Commercial rows | C9: =IF(COUNTIFS(Rates_data!$B$2:$B$75,"Massachusetts General Hospital",Rates_data!$D$2:$D$75,"95923",Rates_data!$Y$2:$Y$75,1,Rates_data!$F$2:$F$75,"UnitedHealthcare",Rates_data!$G$2:$G$75,"Commercial")=0,"not listed",COUNTIFS(Rates_data!$B$2:$B$75,"Massachusetts General Hospital",Rates_data!$D$2:$D$75,"95923",Rates_data!$Y$2:$Y$75,1,Rates_data!$F$2:$F$75,"UnitedHealthcare",Rates_data!$G$2:$G$75,"Commercial")&" row(s)") -> 2 row(s) | D9: =IF(COUNTIFS(Rates_data!$B$2:$B$75,"Massachusetts General Hospital",Rates_data!$D$2:$D$75,"95924",Rates_data!$Y$2:$Y$75,1,Rates_data!$F$2:$F$75,"UnitedHealthcare",Rates_data!$G$2:$G$75,"Commercial")=0,"not listed",COUNTIFS(Rates_data!$B$2:$B$75,"Massachusetts General Hospital",Rates_data!$D$2:$D$75,"95924",Rates_data!$Y$2:$Y$75,1,Rates_data!$F$2:$F$75,"UnitedHealthcare",Rates_data!$G$2:$G$75,"Commercial")&" row(s)") -> 2 row(s) | E9: =IF(COUNTIFS(Rates_data!$B$2:$B$75,"Brigham and Women's Hospital",Rates_data!$D$2:$D$75,"95923",Rates_data!$Y$2:$Y$75,1,Rates_data!$F$2:$F$75,"UnitedHealthcare",Rates_data!$G$2:$G$75,"Commercial")=0,"not listed",COUNTIFS(Rates_data!$B$2:$B$75,"Brigham and Women's Hospital",Rates_data!$D$2:$D$75,"95923",Rates_data!$Y$2:$Y$75,1,Rates_data!$F$2:$F$75,"UnitedHealthcare",Rates_data!$G$2:$G$75,"Commercial")&" row(s)") -> not listed | F9: =IF(COUNTIFS(Rates_data!$B$2:$B$75,"Brigham and Women's Hospital",Rates_data!$D$2:$D$75,"95924",Rates_data!$Y$2:$Y$75,1,Rates_data!$F$2:$F$75,"UnitedHealthcare",Rates_data!$G$2:$G$75,"Commercial")=0,"not listed",COUNTIFS(Rates_data!$B$2:$B$75,"Brigham and Women's Hospital",Rates_data!$D$2:$D$75,"95924",Rates_data!$Y$2:$Y$75,1,Rates_data!$F$2:$F$75,"UnitedHealthcare",Rates_data!$G$2:$G$75,"Commercial")&" row(s)") -> not listed | G9: =IF(COUNTIFS(Rates_data!$B$2:$B$75,"Brigham and Women's Faulkner Hospital",Rates_data!$D$2:$D$75,"95923",Rates_data!$Y$2:$Y$75,1,Rates_data!$F$2:$F$75,"UnitedHealthcare",Rates_data!$G$2:$G$75,"Commercial")=0,"not listed",COUNTIFS(Rates_data!$B$2:$B$75,"Brigham and Women's Faulkner Hospital",Rates_data!$D$2:$D$75,"95923",Rates_data!$Y$2:$Y$75,1,Rates_data!$F$2:$F$75,"UnitedHealthcare",Rates_data!$G$2:$G$75,"Commercial")&" row(s)") -> 2 row(s) | H9: =IF(COUNTIFS(Rates_data!$B$2:$B$75,"Brigham and Women's Faulkner Hospital",Rates_data!$D$2:$D$75,"95924",Rates_data!$Y$2:$Y$75,1,Rates_data!$F$2:$F$75,"UnitedHealthcare",Rates_data!$G$2:$G$75,"Commercial")=0,"not listed",COUNTIFS(Rates_data!$B$2:$B$75,"Brigham and Women's Faulkner Hospital",Rates_data!$D$2:$D$75,"95924",Rates_data!$Y$2:$Y$75,1,Rates_data!$F$2:$F$75,"UnitedHealthcare",Rates_data!$G$2:$G$75,"Commercial")&" row(s)") -> 2 row(s) | I9: =IF(COUNTIFS(Rates_data!$B$2:$B$75,"Wentworth-Douglass Hospital",Rates_data!$D$2:$D$75,"95923",Rates_data!$Y$2:$Y$75,1,Rates_data!$F$2:$F$75,"UnitedHealthcare",Rates_data!$G$2:$G$75,"Commercial")=0,"not listed",COUNTIFS(Rates_data!$B$2:$B$75,"Wentworth-Douglass Hospital",Rates_data!$D$2:$D$75,"95923",Rates_data!$Y$2:$Y$75,1,Rates_data!$F$2:$F$75,"UnitedHealthcare",Rates_data!$G$2:$G$75,"Commercial")&" row(s)") -> not listed | J9: =IF(COUNTIFS(Rates_data!$B$2:$B$75,"Wentworth-Douglass Hospital",Rates_data!$D$2:$D$75,"95924",Rates_data!$Y$2:$Y$75,1,Rates_data!$F$2:$F$75,"UnitedHealthcare",Rates_data!$G$2:$G$75,"Commercial")=0,"not listed",COUNTIFS(Rates_data!$B$2:$B$75,"Wentworth-Douglass Hospital",Rates_data!$D$2:$D$75,"95924",Rates_data!$Y$2:$Y$75,1,Rates_data!$F$2:$F$75,"UnitedHealthcare",Rates_data!$G$2:$G$75,"Commercial")&" row(s)") -> not listed | K9: =IF(COUNTIFS(Rates_data!$B$2:$B$75,"Beth Israel Deaconess Medical Center",Rates_data!$D$2:$D$75,"95923",Rates_data!$Y$2:$Y$75,1,Rates_data!$F$2:$F$75,"UnitedHealthcare",Rates_data!$G$2:$G$75,"Commercial")=0,"not listed",COUNTIFS(Rates_data!$B$2:$B$75,"Beth Israel Deaconess Medical Center",Rates_data!$D$2:$D$75,"95923",Rates_data!$Y$2:$Y$75,1,Rates_data!$F$2:$F$75,"UnitedHealthcare",Rates_data!$G$2:$G$75,"Commercial")&" row(s)") -> not listed | L9: =IF(COUNTIFS(Rates_data!$B$2:$B$75,"Beth Israel Deaconess Medical Center",Rates_data!$D$2:$D$75,"95924",Rates_data!$Y$2:$Y$75,1,Rates_data!$F$2:$F$75,"UnitedHealthcare",Rates_data!$G$2:$G$75,"Commercial")=0,"not listed",COUNTIFS(Rates_data!$B$2:$B$75,"Beth Israel Deaconess Medical Center",Rates_data!$D$2:$D$75,"95924",Rates_data!$Y$2:$Y$75,1,Rates_data!$F$2:$F$75,"UnitedHealthcare",Rates_data!$G$2:$G$75,"Commercial")&" row(s)") -> not listed
A10: Aetna | B10: Commercial rows | C10: =IF(COUNTIFS(Rates_data!$B$2:$B$75,"Massachusetts General Hospital",Rates_data!$D$2:$D$75,"95923",Rates_data!$Y$2:$Y$75,1,Rates_data!$F$2:$F$75,"Aetna",Rates_data!$G$2:$G$75,"Commercial")=0,"not listed",COUNTIFS(Rates_data!$B$2:$B$75,"Massachusetts General Hospital",Rates_data!$D$2:$D$75,"95923",Rates_data!$Y$2:$Y$75,1,Rates_data!$F$2:$F$75,"Aetna",Rates_data!$G$2:$G$75,"Commercial")&" row(s)") -> 1 row(s) | D10: =IF(COUNTIFS(Rates_data!$B$2:$B$75,"Massachusetts General Hospital",Rates_data!$D$2:$D$75,"95924",Rates_data!$Y$2:$Y$75,1,Rates_data!$F$2:$F$75,"Aetna",Rates_data!$G$2:$G$75,"Commercial")=0,"not listed",COUNTIFS(Rates_data!$B$2:$B$75,"Massachusetts General Hospital",Rates_data!$D$2:$D$75,"95924",Rates_data!$Y$2:$Y$75,1,Rates_data!$F$2:$F$75,"Aetna",Rates_data!$G$2:$G$75,"Commercial")&" row(s)") -> 1 row(s) | E10: =IF(COUNTIFS(Rates_data!$B$2:$B$75,"Brigham and Women's Hospital",Rates_data!$D$2:$D$75,"95923",Rates_data!$Y$2:$Y$75,1,Rates_data!$F$2:$F$75,"Aetna",Rates_data!$G$2:$G$75,"Commercial")=0,"not listed",COUNTIFS(Rates_data!$B$2:$B$75,"Brigham and Women's Hospital",Rates_data!$D$2:$D$75,"95923",Rates_data!$Y$2:$Y$75,1,Rates_data!$F$2:$F$75,"Aetna",Rates_data!$G$2:$G$75,"Commercial")&" row(s)") -> not listed | F10: =IF(COUNTIFS(Rates_data!$B$2:$B$75,"Brigham and Women's Hospital",Rates_data!$D$2:$D$75,"95924",Rates_data!$Y$2:$Y$75,1,Rates_data!$F$2:$F$75,"Aetna",Rates_data!$G$2:$G$75,"Commercial")=0,"not listed",COUNTIFS(Rates_data!$B$2:$B$75,"Brigham and Women's Hospital",Rates_data!$D$2:$D$75,"95924",Rates_data!$Y$2:$Y$75,1,Rates_data!$F$2:$F$75,"Aetna",Rates_data!$G$2:$G$75,"Commercial")&" row(s)") -> not listed | G10: =IF(COUNTIFS(Rates_data!$B$2:$B$75,"Brigham and Women's Faulkner Hospital",Rates_data!$D$2:$D$75,"95923",Rates_data!$Y$2:$Y$75,1,Rates_data!$F$2:$F$75,"Aetna",Rates_data!$G$2:$G$75,"Commercial")=0,"not listed",COUNTIFS(Rates_data!$B$2:$B$75,"Brigham and Women's Faulkner Hospital",Rates_data!$D$2:$D$75,"95923",Rates_data!$Y$2:$Y$75,1,Rates_data!$F$2:$F$75,"Aetna",Rates_data!$G$2:$G$75,"Commercial")&" row(s)") -> not listed | H10: =IF(COUNTIFS(Rates_data!$B$2:$B$75,"Brigham and Women's Faulkner Hospital",Rates_data!$D$2:$D$75,"95924",Rates_data!$Y$2:$Y$75,1,Rates_data!$F$2:$F$75,"Aetna",Rates_data!$G$2:$G$75,"Commercial")=0,"not listed",COUNTIFS(Rates_data!$B$2:$B$75,"Brigham and Women's Faulkner Hospital",Rates_data!$D$2:$D$75,"95924",Rates_data!$Y$2:$Y$75,1,Rates_data!$F$2:$F$75,"Aetna",Rates_data!$G$2:$G$75,"Commercial")&" row(s)") -> not listed | I10: =IF(COUNTIFS(Rates_data!$B$2:$B$75,"Wentworth-Douglass Hospital",Rates_data!$D$2:$D$75,"95923",Rates_data!$Y$2:$Y$75,1,Rates_data!$F$2:$F$75,"Aetna",Rates_data!$G$2:$G$75,"Commercial")=0,"not listed",COUNTIFS(Rates_data!$B$2:$B$75,"Wentworth-Douglass Hospital",Rates_data!$D$2:$D$75,"95923",Rates_data!$Y$2:$Y$75,1,Rates_data!$F$2:$F$75,"Aetna",Rates_data!$G$2:$G$75,"Commercial")&" row(s)") -> not listed | J10: =IF(COUNTIFS(Rates_data!$B$2:$B$75,"Wentworth-Douglass Hospital",Rates_data!$D$2:$D$75,"95924",Rates_data!$Y$2:$Y$75,1,Rates_data!$F$2:$F$75,"Aetna",Rates_data!$G$2:$G$75,"Commercial")=0,"not listed",COUNTIFS(Rates_data!$B$2:$B$75,"Wentworth-Douglass Hospital",Rates_data!$D$2:$D$75,"95924",Rates_data!$Y$2:$Y$75,1,Rates_data!$F$2:$F$75,"Aetna",Rates_data!$G$2:$G$75,"Commercial")&" row(s)") -> not listed | K10: =IF(COUNTIFS(Rates_data!$B$2:$B$75,"Beth Israel Deaconess Medical Center",Rates_data!$D$2:$D$75,"95923",Rates_data!$Y$2:$Y$75,1,Rates_data!$F$2:$F$75,"Aetna",Rates_data!$G$2:$G$75,"Commercial")=0,"not listed",COUNTIFS(Rates_data!$B$2:$B$75,"Beth Israel Deaconess Medical Center",Rates_data!$D$2:$D$75,"95923",Rates_data!$Y$2:$Y$75,1,Rates_data!$F$2:$F$75,"Aetna",Rates_data!$G$2:$G$75,"Commercial")&" row(s)") -> not listed | L10: =IF(COUNTIFS(Rates_data!$B$2:$B$75,"Beth Israel Deaconess Medical Center",Rates_data!$D$2:$D$75,"95924",Rates_data!$Y$2:$Y$75,1,Rates_data!$F$2:$F$75,"Aetna",Rates_data!$G$2:$G$75,"Commercial")=0,"not listed",COUNTIFS(Rates_data!$B$2:$B$75,"Beth Israel Deaconess Medical Center",Rates_data!$D$2:$D$75,"95924",Rates_data!$Y$2:$Y$75,1,Rates_data!$F$2:$F$75,"Aetna",Rates_data!$G$2:$G$75,"Commercial")&" row(s)") -> not listed
A11: Cigna | B11: Commercial rows | C11: =IF(COUNTIFS(Rates_data!$B$2:$B$75,"Massachusetts General Hospital",Rates_data!$D$2:$D$75,"95923",Rates_data!$Y$2:$Y$75,1,Rates_data!$F$2:$F$75,"Cigna",Rates_data!$G$2:$G$75,"Commercial")=0,"not listed",COUNTIFS(Rates_data!$B$2:$B$75,"Massachusetts General Hospital",Rates_data!$D$2:$D$75,"95923",Rates_data!$Y$2:$Y$75,1,Rates_data!$F$2:$F$75,"Cigna",Rates_data!$G$2:$G$75,"Commercial")&" row(s)") -> 2 row(s) | D11: =IF(COUNTIFS(Rates_data!$B$2:$B$75,"Massachusetts General Hospital",Rates_data!$D$2:$D$75,"95924",Rates_data!$Y$2:$Y$75,1,Rates_data!$F$2:$F$75,"Cigna",Rates_data!$G$2:$G$75,"Commercial")=0,"not listed",COUNTIFS(Rates_data!$B$2:$B$75,"Massachusetts General Hospital",Rates_data!$D$2:$D$75,"95924",Rates_data!$Y$2:$Y$75,1,Rates_data!$F$2:$F$75,"Cigna",Rates_data!$G$2:$G$75,"Commercial")&" row(s)") -> 2 row(s) | E11: =IF(COUNTIFS(Rates_data!$B$2:$B$75,"Brigham and Women's Hospital",Rates_data!$D$2:$D$75,"95923",Rates_data!$Y$2:$Y$75,1,Rates_data!$F$2:$F$75,"Cigna",Rates_data!$G$2:$G$75,"Commercial")=0,"not listed",COUNTIFS(Rates_data!$B$2:$B$75,"Brigham and Women's Hospital",Rates_data!$D$2:$D$75,"95923",Rates_data!$Y$2:$Y$75,1,Rates_data!$F$2:$F$75,"Cigna",Rates_data!$G$2:$G$75,"Commercial")&" row(s)") -> not listed | F11: =IF(COUNTIFS(Rates_data!$B$2:$B$75,"Brigham and Women's Hospital",Rates_data!$D$2:$D$75,"95924",Rates_data!$Y$2:$Y$75,1,Rates_data!$F$2:$F$75,"Cigna",Rates_data!$G$2:$G$75,"Commercial")=0,"not listed",COUNTIFS(Rates_data!$B$2:$B$75,"Brigham and Women's Hospital",Rates_data!$D$2:$D$75,"95924",Rates_data!$Y$2:$Y$75,1,Rates_data!$F$2:$F$75,"Cigna",Rates_data!$G$2:$G$75,"Commercial")&" row(s)") -> not listed | G11: =IF(COUNTIFS(Rates_data!$B$2:$B$75,"Brigham and Women's Faulkner Hospital",Rates_data!$D$2:$D$75,"95923",Rates_data!$Y$2:$Y$75,1,Rates_data!$F$2:$F$75,"Cigna",Rates_data!$G$2:$G$75,"Commercial")=0,"not listed",COUNTIFS(Rates_data!$B$2:$B$75,"Brigham and Women's Faulkner Hospital",Rates_data!$D$2:$D$75,"95923",Rates_data!$Y$2:$Y$75,1,Rates_data!$F$2:$F$75,"Cigna",Rates_data!$G$2:$G$75,"Commercial")&" row(s)") -> 1 row(s) | H11: =IF(COUNTIFS(Rates_data!$B$2:$B$75,"Brigham and Women's Faulkner Hospital",Rates_data!$D$2:$D$75,"95924",Rates_data!$Y$2:$Y$75,1,Rates_data!$F$2:$F$75,"Cigna",Rates_data!$G$2:$G$75,"Commercial")=0,"not listed",COUNTIFS(Rates_data!$B$2:$B$75,"Brigham and Women's Faulkner Hospital",Rates_data!$D$2:$D$75,"95924",Rates_data!$Y$2:$Y$75,1,Rates_data!$F$2:$F$75,"Cigna",Rates_data!$G$2:$G$75,"Commercial")&" row(s)") -> 1 row(s) | I11: =IF(COUNTIFS(Rates_data!$B$2:$B$75,"Wentworth-Douglass Hospital",Rates_data!$D$2:$D$75,"95923",Rates_data!$Y$2:$Y$75,1,Rates_data!$F$2:$F$75,"Cigna",Rates_data!$G$2:$G$75,"Commercial")=0,"not listed",COUNTIFS(Rates_data!$B$2:$B$75,"Wentworth-Douglass Hospital",Rates_data!$D$2:$D$75,"95923",Rates_data!$Y$2:$Y$75,1,Rates_data!$F$2:$F$75,"Cigna",Rates_data!$G$2:$G$75,"Commercial")&" row(s)") -> not listed | J11: =IF(COUNTIFS(Rates_data!$B$2:$B$75,"Wentworth-Douglass Hospital",Rates_data!$D$2:$D$75,"95924",Rates_data!$Y$2:$Y$75,1,Rates_data!$F$2:$F$75,"Cigna",Rates_data!$G$2:$G$75,"Commercial")=0,"not listed",COUNTIFS(Rates_data!$B$2:$B$75,"Wentworth-Douglass Hospital",Rates_data!$D$2:$D$75,"95924",Rates_data!$Y$2:$Y$75,1,Rates_data!$F$2:$F$75,"Cigna",Rates_data!$G$2:$G$75,"Commercial")&" row(s)") -> not listed | K11: =IF(COUNTIFS(Rates_data!$B$2:$B$75,"Beth Israel Deaconess Medical Center",Rates_data!$D$2:$D$75,"95923",Rates_data!$Y$2:$Y$75,1,Rates_data!$F$2:$F$75,"Cigna",Rates_data!$G$2:$G$75,"Commercial")=0,"not listed",COUNTIFS(Rates_data!$B$2:$B$75,"Beth Israel Deaconess Medical Center",Rates_data!$D$2:$D$75,"95923",Rates_data!$Y$2:$Y$75,1,Rates_data!$F$2:$F$75,"Cigna",Rates_data!$G$2:$G$75,"Commercial")&" row(s)") -> not listed | L11: =IF(COUNTIFS(Rates_data!$B$2:$B$75,"Beth Israel Deaconess Medical Center",Rates_data!$D$2:$D$75,"95924",Rates_data!$Y$2:$Y$75,1,Rates_data!$F$2:$F$75,"Cigna",Rates_data!$G$2:$G$75,"Commercial")=0,"not listed",COUNTIFS(Rates_data!$B$2:$B$75,"Beth Israel Deaconess Medical Center",Rates_data!$D$2:$D$75,"95924",Rates_data!$Y$2:$Y$75,1,Rates_data!$F$2:$F$75,"Cigna",Rates_data!$G$2:$G$75,"Commercial")&" row(s)") -> not listed
A12: MassHealth managed-care plans | B12: MassHealth / dual managed care rows | C12: =IF(COUNTIFS(Rates_data!$B$2:$B$75,"Massachusetts General Hospital",Rates_data!$D$2:$D$75,"95923",Rates_data!$Y$2:$Y$75,1,Rates_data!$G$2:$G$75,"MassHealth / dual managed care")=0,"not listed",COUNTIFS(Rates_data!$B$2:$B$75,"Massachusetts General Hospital",Rates_data!$D$2:$D$75,"95923",Rates_data!$Y$2:$Y$75,1,Rates_data!$G$2:$G$75,"MassHealth / dual managed care")&" row(s)") -> not listed | D12: =IF(COUNTIFS(Rates_data!$B$2:$B$75,"Massachusetts General Hospital",Rates_data!$D$2:$D$75,"95924",Rates_data!$Y$2:$Y$75,1,Rates_data!$G$2:$G$75,"MassHealth / dual managed care")=0,"not listed",COUNTIFS(Rates_data!$B$2:$B$75,"Massachusetts General Hospital",Rates_data!$D$2:$D$75,"95924",Rates_data!$Y$2:$Y$75,1,Rates_data!$G$2:$G$75,"MassHealth / dual managed care")&" row(s)") -> 1 row(s) | E12: =IF(COUNTIFS(Rates_data!$B$2:$B$75,"Brigham and Women's Hospital",Rates_data!$D$2:$D$75,"95923",Rates_data!$Y$2:$Y$75,1,Rates_data!$G$2:$G$75,"MassHealth / dual managed care")=0,"not listed",COUNTIFS(Rates_data!$B$2:$B$75,"Brigham and Women's Hospital",Rates_data!$D$2:$D$75,"95923",Rates_data!$Y$2:$Y$75,1,Rates_data!$G$2:$G$75,"MassHealth / dual managed care")&" row(s)") -> not listed | F12: =IF(COUNTIFS(Rates_data!$B$2:$B$75,"Brigham and Women's Hospital",Rates_data!$D$2:$D$75,"95924",Rates_data!$Y$2:$Y$75,1,Rates_data!$G$2:$G$75,"MassHealth / dual managed care")=0,"not listed",COUNTIFS(Rates_data!$B$2:$B$75,"Brigham and Women's Hospital",Rates_data!$D$2:$D$75,"95924",Rates_data!$Y$2:$Y$75,1,Rates_data!$G$2:$G$75,"MassHealth / dual managed care")&" row(s)") -> not listed | G12: =IF(COUNTIFS(Rates_data!$B$2:$B$75,"Brigham and Women's Faulkner Hospital",Rates_data!$D$2:$D$75,"95923",Rates_data!$Y$2:$Y$75,1,Rates_data!$G$2:$G$75,"MassHealth / dual managed care")=0,"not listed",COUNTIFS(Rates_data!$B$2:$B$75,"Brigham and Women's Faulkner Hospital",Rates_data!$D$2:$D$75,"95923",Rates_data!$Y$2:$Y$75,1,Rates_data!$G$2:$G$75,"MassHealth / dual managed care")&" row(s)") -> not listed | H12: =IF(COUNTIFS(Rates_data!$B$2:$B$75,"Brigham and Women's Faulkner Hospital",Rates_data!$D$2:$D$75,"95924",Rates_data!$Y$2:$Y$75,1,Rates_data!$G$2:$G$75,"MassHealth / dual managed care")=0,"not listed",COUNTIFS(Rates_data!$B$2:$B$75,"Brigham and Women's Faulkner Hospital",Rates_data!$D$2:$D$75,"95924",Rates_data!$Y$2:$Y$75,1,Rates_data!$G$2:$G$75,"MassHealth / dual managed care")&" row(s)") -> not listed | I12: =IF(COUNTIFS(Rates_data!$B$2:$B$75,"Wentworth-Douglass Hospital",Rates_data!$D$2:$D$75,"95923",Rates_data!$Y$2:$Y$75,1,Rates_data!$G$2:$G$75,"MassHealth / dual managed care")=0,"not listed",COUNTIFS(Rates_data!$B$2:$B$75,"Wentworth-Douglass Hospital",Rates_data!$D$2:$D$75,"95923",Rates_data!$Y$2:$Y$75,1,Rates_data!$G$2:$G$75,"MassHealth / dual managed care")&" row(s)") -> not listed | J12: =IF(COUNTIFS(Rates_data!$B$2:$B$75,"Wentworth-Douglass Hospital",Rates_data!$D$2:$D$75,"95924",Rates_data!$Y$2:$Y$75,1,Rates_data!$G$2:$G$75,"MassHealth / dual managed care")=0,"not listed",COUNTIFS(Rates_data!$B$2:$B$75,"Wentworth-Douglass Hospital",Rates_data!$D$2:$D$75,"95924",Rates_data!$Y$2:$Y$75,1,Rates_data!$G$2:$G$75,"MassHealth / dual managed care")&" row(s)") -> not listed | K12: =IF(COUNTIFS(Rates_data!$B$2:$B$75,"Beth Israel Deaconess Medical Center",Rates_data!$D$2:$D$75,"95923",Rates_data!$Y$2:$Y$75,1,Rates_data!$G$2:$G$75,"MassHealth / dual managed care")=0,"not listed",COUNTIFS(Rates_data!$B$2:$B$75,"Beth Israel Deaconess Medical Center",Rates_data!$D$2:$D$75,"95923",Rates_data!$Y$2:$Y$75,1,Rates_data!$G$2:$G$75,"MassHealth / dual managed care")&" row(s)") -> not listed | L12: =IF(COUNTIFS(Rates_data!$B$2:$B$75,"Beth Israel Deaconess Medical Center",Rates_data!$D$2:$D$75,"95924",Rates_data!$Y$2:$Y$75,1,Rates_data!$G$2:$G$75,"MassHealth / dual managed care")=0,"not listed",COUNTIFS(Rates_data!$B$2:$B$75,"Beth Israel Deaconess Medical Center",Rates_data!$D$2:$D$75,"95924",Rates_data!$Y$2:$Y$75,1,Rates_data!$G$2:$G$75,"MassHealth / dual managed care")&" row(s)") -> not listed
A13: Medicare Advantage plans | B13: Medicare Advantage rows | C13: =IF(COUNTIFS(Rates_data!$B$2:$B$75,"Massachusetts General Hospital",Rates_data!$D$2:$D$75,"95923",Rates_data!$Y$2:$Y$75,1,Rates_data!$G$2:$G$75,"Medicare Advantage")=0,"not listed",COUNTIFS(Rates_data!$B$2:$B$75,"Massachusetts General Hospital",Rates_data!$D$2:$D$75,"95923",Rates_data!$Y$2:$Y$75,1,Rates_data!$G$2:$G$75,"Medicare Advantage")&" row(s)") -> not listed | D13: =IF(COUNTIFS(Rates_data!$B$2:$B$75,"Massachusetts General Hospital",Rates_data!$D$2:$D$75,"95924",Rates_data!$Y$2:$Y$75,1,Rates_data!$G$2:$G$75,"Medicare Advantage")=0,"not listed",COUNTIFS(Rates_data!$B$2:$B$75,"Massachusetts General Hospital",Rates_data!$D$2:$D$75,"95924",Rates_data!$Y$2:$Y$75,1,Rates_data!$G$2:$G$75,"Medicare Advantage")&" row(s)") -> 5 row(s) | E13: =IF(COUNTIFS(Rates_data!$B$2:$B$75,"Brigham and Women's Hospital",Rates_data!$D$2:$D$75,"95923",Rates_data!$Y$2:$Y$75,1,Rates_data!$G$2:$G$75,"Medicare Advantage")=0,"not listed",COUNTIFS(Rates_data!$B$2:$B$75,"Brigham and Women's Hospital",Rates_data!$D$2:$D$75,"95923",Rates_data!$Y$2:$Y$75,1,Rates_data!$G$2:$G$75,"Medicare Advantage")&" row(s)") -> not listed | F13: =IF(COUNTIFS(Rates_data!$B$2:$B$75,"Brigham and Women's Hospital",Rates_data!$D$2:$D$75,"95924",Rates_data!$Y$2:$Y$75,1,Rates_data!$G$2:$G$75,"Medicare Advantage")=0,"not listed",COUNTIFS(Rates_data!$B$2:$B$75,"Brigham and Women's Hospital",Rates_data!$D$2:$D$75,"95924",Rates_data!$Y$2:$Y$75,1,Rates_data!$G$2:$G$75,"Medicare Advantage")&" row(s)") -> not listed | G13: =IF(COUNTIFS(Rates_data!$B$2:$B$75,"Brigham and Women's Faulkner Hospital",Rates_data!$D$2:$D$75,"95923",Rates_data!$Y$2:$Y$75,1,Rates_data!$G$2:$G$75,"Medicare Advantage")=0,"not listed",COUNTIFS(Rates_data!$B$2:$B$75,"Brigham and Women's Faulkner Hospital",Rates_data!$D$2:$D$75,"95923",Rates_data!$Y$2:$Y$75,1,Rates_data!$G$2:$G$75,"Medicare Advantage")&" row(s)") -> 2 row(s) | H13: =IF(COUNTIFS(Rates_data!$B$2:$B$75,"Brigham and Women's Faulkner Hospital",Rates_data!$D$2:$D$75,"95924",Rates_data!$Y$2:$Y$75,1,Rates_data!$G$2:$G$75,"Medicare Advantage")=0,"not listed",COUNTIFS(Rates_data!$B$2:$B$75,"Brigham and Women's Faulkner Hospital",Rates_data!$D$2:$D$75,"95924",Rates_data!$Y$2:$Y$75,1,Rates_data!$G$2:$G$75,"Medicare Advantage")&" row(s)") -> 7 row(s) | I13: =IF(COUNTIFS(Rates_data!$B$2:$B$75,"Wentworth-Douglass Hospital",Rates_data!$D$2:$D$75,"95923",Rates_data!$Y$2:$Y$75,1,Rates_data!$G$2:$G$75,"Medicare Advantage")=0,"not listed",COUNTIFS(Rates_data!$B$2:$B$75,"Wentworth-Douglass Hospital",Rates_data!$D$2:$D$75,"95923",Rates_data!$Y$2:$Y$75,1,Rates_data!$G$2:$G$75,"Medicare Advantage")&" row(s)") -> not listed | J13: =IF(COUNTIFS(Rates_data!$B$2:$B$75,"Wentworth-Douglass Hospital",Rates_data!$D$2:$D$75,"95924",Rates_data!$Y$2:$Y$75,1,Rates_data!$G$2:$G$75,"Medicare Advantage")=0,"not listed",COUNTIFS(Rates_data!$B$2:$B$75,"Wentworth-Douglass Hospital",Rates_data!$D$2:$D$75,"95924",Rates_data!$Y$2:$Y$75,1,Rates_data!$G$2:$G$75,"Medicare Advantage")&" row(s)") -> not listed | K13: =IF(COUNTIFS(Rates_data!$B$2:$B$75,"Beth Israel Deaconess Medical Center",Rates_data!$D$2:$D$75,"95923",Rates_data!$Y$2:$Y$75,1,Rates_data!$G$2:$G$75,"Medicare Advantage")=0,"not listed",COUNTIFS(Rates_data!$B$2:$B$75,"Beth Israel Deaconess Medical Center",Rates_data!$D$2:$D$75,"95923",Rates_data!$Y$2:$Y$75,1,Rates_data!$G$2:$G$75,"Medicare Advantage")&" row(s)") -> not listed | L13: =IF(COUNTIFS(Rates_data!$B$2:$B$75,"Beth Israel Deaconess Medical Center",Rates_data!$D$2:$D$75,"95924",Rates_data!$Y$2:$Y$75,1,Rates_data!$G$2:$G$75,"Medicare Advantage")=0,"not listed",COUNTIFS(Rates_data!$B$2:$B$75,"Beth Israel Deaconess Medical Center",Rates_data!$D$2:$D$75,"95924",Rates_data!$Y$2:$Y$75,1,Rates_data!$G$2:$G$75,"Medicare Advantage")&" row(s)") -> not listed
A14: Medicare fee-for-service | B14: Medicare FFS rows | C14: =IF(COUNTIFS(Rates_data!$B$2:$B$75,"Massachusetts General Hospital",Rates_data!$D$2:$D$75,"95923",Rates_data!$Y$2:$Y$75,1,Rates_data!$G$2:$G$75,"Medicare FFS")=0,"not listed",COUNTIFS(Rates_data!$B$2:$B$75,"Massachusetts General Hospital",Rates_data!$D$2:$D$75,"95923",Rates_data!$Y$2:$Y$75,1,Rates_data!$G$2:$G$75,"Medicare FFS")&" row(s)") -> not listed | D14: =IF(COUNTIFS(Rates_data!$B$2:$B$75,"Massachusetts General Hospital",Rates_data!$D$2:$D$75,"95924",Rates_data!$Y$2:$Y$75,1,Rates_data!$G$2:$G$75,"Medicare FFS")=0,"not listed",COUNTIFS(Rates_data!$B$2:$B$75,"Massachusetts General Hospital",Rates_data!$D$2:$D$75,"95924",Rates_data!$Y$2:$Y$75,1,Rates_data!$G$2:$G$75,"Medicare FFS")&" row(s)") -> 1 row(s) | E14: =IF(COUNTIFS(Rates_data!$B$2:$B$75,"Brigham and Women's Hospital",Rates_data!$D$2:$D$75,"95923",Rates_data!$Y$2:$Y$75,1,Rates_data!$G$2:$G$75,"Medicare FFS")=0,"not listed",COUNTIFS(Rates_data!$B$2:$B$75,"Brigham and Women's Hospital",Rates_data!$D$2:$D$75,"95923",Rates_data!$Y$2:$Y$75,1,Rates_data!$G$2:$G$75,"Medicare FFS")&" row(s)") -> not listed | F14: =IF(COUNTIFS(Rates_data!$B$2:$B$75,"Brigham and Women's Hospital",Rates_data!$D$2:$D$75,"95924",Rates_data!$Y$2:$Y$75,1,Rates_data!$G$2:$G$75,"Medicare FFS")=0,"not listed",COUNTIFS(Rates_data!$B$2:$B$75,"Brigham and Women's Hospital",Rates_data!$D$2:$D$75,"95924",Rates_data!$Y$2:$Y$75,1,Rates_data!$G$2:$G$75,"Medicare FFS")&" row(s)") -> not listed | G14: =IF(COUNTIFS(Rates_data!$B$2:$B$75,"Brigham and Women's Faulkner Hospital",Rates_data!$D$2:$D$75,"95923",Rates_data!$Y$2:$Y$75,1,Rates_data!$G$2:$G$75,"Medicare FFS")=0,"not listed",COUNTIFS(Rates_data!$B$2:$B$75,"Brigham and Women's Faulkner Hospital",Rates_data!$D$2:$D$75,"95923",Rates_data!$Y$2:$Y$75,1,Rates_data!$G$2:$G$75,"Medicare FFS")&" row(s)") -> 1 row(s) | H14: =IF(COUNTIFS(Rates_data!$B$2:$B$75,"Brigham and Women's Faulkner Hospital",Rates_data!$D$2:$D$75,"95924",Rates_data!$Y$2:$Y$75,1,Rates_data!$G$2:$G$75,"Medicare FFS")=0,"not listed",COUNTIFS(Rates_data!$B$2:$B$75,"Brigham and Women's Faulkner Hospital",Rates_data!$D$2:$D$75,"95924",Rates_data!$Y$2:$Y$75,1,Rates_data!$G$2:$G$75,"Medicare FFS")&" row(s)") -> 1 row(s) | I14: =IF(COUNTIFS(Rates_data!$B$2:$B$75,"Wentworth-Douglass Hospital",Rates_data!$D$2:$D$75,"95923",Rates_data!$Y$2:$Y$75,1,Rates_data!$G$2:$G$75,"Medicare FFS")=0,"not listed",COUNTIFS(Rates_data!$B$2:$B$75,"Wentworth-Douglass Hospital",Rates_data!$D$2:$D$75,"95923",Rates_data!$Y$2:$Y$75,1,Rates_data!$G$2:$G$75,"Medicare FFS")&" row(s)") -> not listed | J14: =IF(COUNTIFS(Rates_data!$B$2:$B$75,"Wentworth-Douglass Hospital",Rates_data!$D$2:$D$75,"95924",Rates_data!$Y$2:$Y$75,1,Rates_data!$G$2:$G$75,"Medicare FFS")=0,"not listed",COUNTIFS(Rates_data!$B$2:$B$75,"Wentworth-Douglass Hospital",Rates_data!$D$2:$D$75,"95924",Rates_data!$Y$2:$Y$75,1,Rates_data!$G$2:$G$75,"Medicare FFS")&" row(s)") -> not listed | K14: =IF(COUNTIFS(Rates_data!$B$2:$B$75,"Beth Israel Deaconess Medical Center",Rates_data!$D$2:$D$75,"95923",Rates_data!$Y$2:$Y$75,1,Rates_data!$G$2:$G$75,"Medicare FFS")=0,"not listed",COUNTIFS(Rates_data!$B$2:$B$75,"Beth Israel Deaconess Medical Center",Rates_data!$D$2:$D$75,"95923",Rates_data!$Y$2:$Y$75,1,Rates_data!$G$2:$G$75,"Medicare FFS")&" row(s)") -> not listed | L14: =IF(COUNTIFS(Rates_data!$B$2:$B$75,"Beth Israel Deaconess Medical Center",Rates_data!$D$2:$D$75,"95924",Rates_data!$Y$2:$Y$75,1,Rates_data!$G$2:$G$75,"Medicare FFS")=0,"not listed",COUNTIFS(Rates_data!$B$2:$B$75,"Beth Israel Deaconess Medical Center",Rates_data!$D$2:$D$75,"95924",Rates_data!$Y$2:$Y$75,1,Rates_data!$G$2:$G$75,"Medicare FFS")&" row(s)") -> not listed
A16: MGH's file lists NO Medicare fee-for-service row for 95923, although Medicare pays for 95923 (Q1: separately payable when not billed with an S/T/V code; Faulkner lists an APC price of $153.08). MGH's de-identified minimum for 95923 ($145.42) is below every listed payer rate, consistent with an unlisted low (Medicare-type) payer.
A17: Brigham and Women's Hospital and Wentworth-Douglass Hospital list no rows for any of the five codes, for any payer.
A18: Blue Cross Blue Shield of MA and Harvard Pilgrim appear commercially only at BIDMC. In MGB files BCBS appears only on a Medicare (Advantage) plan; Harvard Pilgrim does not appear for these codes.
A19: Tufts Health Plan appears only on Medicare Advantage ('Medicare replacement') plans.

Sheet Reconciliation
A1: Reconciliation: Medicare FFS rows in hospital files vs CY2024 Medicare claims patient counts
A2: Patient counts supplied by the user (blue). MRF 'count' = number of allowed amounts in the file's look-back period; it counts claims/lines, not patients, and the period is not necessarily CY2024.
A4: Hospital (clinicians) | B4: Code | C4: CY2024 Medicare patients (user) | D4: Medicare FFS rows in MRF | E4: MRF allowed-amount count (Medicare FFS) | F4: MRF Medicare FFS rate | G4: Medicare Advantage rows in MRF | H4: Assessment
A5: MGH (Robbins) | B5: 95924 | C5: 94 | D5: =COUNTIFS(Rates_data!$B$2:$B$75,"Massachusetts General Hospital",Rates_data!$D$2:$D$75,"95924",Rates_data!$G$2:$G$75,"Medicare FFS") -> 1 | E5: =Rates_data!V27 -> 84 | F5: =Rates_data!P27 -> 369.77 | G5: =COUNTIFS(Rates_data!$B$2:$B$75,"Massachusetts General Hospital",Rates_data!$D$2:$D$75,"95924",Rates_data!$G$2:$G$75,"Medicare Advantage") -> 5 | H5: Consistent in scale: 84 allowed amounts vs 94 patients (different period and unit).
A6: MGH (Robbins) | B6: 95923 | C6: 95 | D6: =COUNTIFS(Rates_data!$B$2:$B$75,"Massachusetts General Hospital",Rates_data!$D$2:$D$75,"95923",Rates_data!$G$2:$G$75,"Medicare FFS") -> 0 | E6: not listed | F6: not listed | G6: =COUNTIFS(Rates_data!$B$2:$B$75,"Massachusetts General Hospital",Rates_data!$D$2:$D$75,"95923",Rates_data!$G$2:$G$75,"Medicare Advantage") -> 0 | H6: Gap: 95 Medicare patients but no Medicare row. Likely because 95923 (Q1) is packaged into 95924 on the same claim, leaving no separate allowed amount to publish.
A7: Faulkner (Novak) | B7: 95924 | C7: 114 | D7: =COUNTIFS(Rates_data!$B$2:$B$75,"Brigham and Women's Faulkner Hospital",Rates_data!$D$2:$D$75,"95924",Rates_data!$G$2:$G$75,"Medicare FFS") -> 1 | E7: =Rates_data!V53 -> 121 | F7: =Rates_data!P53 -> 369.81 | G7: =COUNTIFS(Rates_data!$B$2:$B$75,"Brigham and Women's Faulkner Hospital",Rates_data!$D$2:$D$75,"95924",Rates_data!$G$2:$G$75,"Medicare Advantage") -> 7 | H7: Consistent: 121 allowed amounts vs 114 patients.
A8: Faulkner (Novak) | B8: 95923 | C8: 114 | D8: =COUNTIFS(Rates_data!$B$2:$B$75,"Brigham and Women's Faulkner Hospital",Rates_data!$D$2:$D$75,"95923",Rates_data!$G$2:$G$75,"Medicare FFS") -> 1 | E8: =Rates_data!V40 -> 1 through 10 | F8: =Rates_data!P40 -> 153.08 | G8: =COUNTIFS(Rates_data!$B$2:$B$75,"Brigham and Women's Faulkner Hospital",Rates_data!$D$2:$D$75,"95923",Rates_data!$G$2:$G$75,"Medicare Advantage") -> 2 | H8: Row listed but count only '1 through 10' vs 114 patients: consistent with 95923 being packaged on most claims.
A9: BIDMC (Freeman + Gibbons) | B9: 95924 | C9: 99 | D9: =COUNTIFS(Rates_data!$B$2:$B$75,"Beth Israel Deaconess Medical Center",Rates_data!$D$2:$D$75,"95924",Rates_data!$G$2:$G$75,"Medicare FFS") -> 0 | E9: not listed | F9: not listed | G9: =COUNTIFS(Rates_data!$B$2:$B$75,"Beth Israel Deaconess Medical Center",Rates_data!$D$2:$D$75,"95924",Rates_data!$G$2:$G$75,"Medicare Advantage") -> 0 | H9: Gap: 99 Medicare patients but BIDMC's file lists no Medicare rows for any target code (only BCBS, Harvard Pilgrim, Unicare).
